Workbook

Sheet Cover
B2: CoreWeave
B3: Operating and valuation model — 2022 to 2032
B4: Prepared 2026-08-13 · HRPB Research Desk
B6: Contents
B7: Inputs | D7: Every assumption, in blue. Yellow fill marks an estimate.
B8: Raw Data | D8: The stored facts, with source and date.
B9: Model | D9: Revenue, profit and loss, and cash flow.
B10: Valuation | D10: Discounted cash flow and cross-checks.
B11: Outputs | D11: The summary.
B13: Model checks
B14: Gross profit exceeds revenue? | D14: =IF(SUMPRODUCT(--(Model!D13:N13>Model!D9:N9))>0,1,0)
B15: Any negative revenue? | D15: =IF(SUMPRODUCT(--(Model!D9:N9<0))>0,1,0)
B16: Discount rate at or below terminal growth? | D16: =IF(Inputs!$D$28<=Inputs!$D$14,1,0)
B17: Enterprise value non-positive? | D17: =IF(Valuation!$D$17<=0,1,0)
B18: Terminal methods disagree by more than 1.5x? | D18: =IF(Valuation!$D$14>1.5,1,0)
B19: Terminal value more than 75% of enterprise value? | D19: =IF(Valuation!$D$17=0,0,IF(D15/Valuation!$D$17>0.75,1,0))
B20: All checks should read No.
B22: How much of this model is fact
B23: Inputs drawn from sourced facts | D23: 0
B24: Inputs that are desk assumptions | D24: 17
B25: Share sourced | D25: 0
B26: ILLUSTRATIVE ONLY — most inputs are desk assumptions. This company discloses too little to support a decision model. Treat the outputs as a shape, not a number.
B28: Convention
B29: Blue text — an input you may change
B30: Yellow fill — an assumption, not a sourced fact
B31: Black text — a formula; do not overwrite
B32: Green text — a link to another sheet
B34: Every blue cell carries a note with its source and date. Hover to read it.

Sheet Inputs
B2: CoreWeave — Inputs and assumptions
B3: All figures in USD millions unless stated. Blue cells are inputs. Yellow-filled blue cells are assumptions.
D5: 2022 | E5: 2023 | F5: 2024 | G5: 2025 | H5: 2026 | I5: 2027 | J5: 2028 | K5: 2029 | L5: 2030 | M5: 2031 | N5: 2032
B7: Scenario
B8: Driver switch (1 = Base, 2 = Bull, 3 = Bear) | D8: 1
B10: Revenue drivers
B11: Latest annualised revenue ($M) | D11: 100
B12: Latest revenue growth (% YoY) | D12: 0.4
B13: Growth decay per year (points of growth lost) | D13: 0.15
B14: Terminal growth (% a year) | D14: 0.04
B15: Scenario multiplier on growth | D15: =CHOOSE(Inputs!$D$8,1,1.25,0.7)
B17: Margin and cost drivers
B18: Gross margin (%) | D18: 0.7
B19: Gross margin drift per year (points) | D19: -0.005
B20: Sales and marketing (% of revenue) | D20: 0.32
B21: Research and development (% of revenue) | D21: 0.28
B22: General and administrative (% of revenue) | D22: 0.1
B23: Operating expense leverage per year (points) | D23: -0.015
B25: Capital and valuation
B26: Latest valuation ($M) | D26: 0
B27: Equity raised to date ($M) | D27: 0
B28: Discount rate (cost of capital) | D28: 0.12
B29: Tax rate | D29: 0.21
B30: Exit multiple on revenue | D30: 8
B31: Headcount (latest) | D31: 0

Sheet Raw Data
B2: CoreWeave — Historical record from the store
B3: Every figure below is a stored Fact. Source and date sit beside it; hover any value for its full provenance.
B5: Metric | D5: Value | F5: As of | H5: Tier | J5: Source
B6: Legal name | D6: CoreWeave | F6: 2026-07-16 | H6: T2 | J6: canonical refresh, July 16, 2026

Sheet Model
B2: CoreWeave — Operating model
B3: All figures in USD millions. Black cells are formulas.
D5: 2022 | E5: 2023 | F5: 2024 | G5: 2025 | H5: 2026 | I5: 2027 | J5: 2028 | K5: 2029 | L5: 2030 | M5: 2031 | N5: 2032
B7: Revenue
B8: Revenue growth (% YoY) | E8: =E9/D9-1 | F8: =F9/E9-1 | G8: =G9/F9-1 | H8: =H9/G9-1 | I8: =MAX(Inputs!$D$14,H8-Inputs!$D$13)*Inputs!$D$15 | J8: =MAX(Inputs!$D$14,I8-Inputs!$D$13)*Inputs!$D$15 | K8: =MAX(Inputs!$D$14,J8-Inputs!$D$13)*Inputs!$D$15 | L8: =MAX(Inputs!$D$14,K8-Inputs!$D$13)*Inputs!$D$15 | M8: =MAX(Inputs!$D$14,L8-Inputs!$D$13)*Inputs!$D$15 | N8: =MAX(Inputs!$D$14,M8-Inputs!$D$13)*Inputs!$D$15
B9: Revenue | D9: 0 | E9: 0 | F9: 0 | G9: 0 | H9: 0 | I9: =H9*(1+I8) | J9: =I9*(1+J8) | K9: =J9*(1+K8) | L9: =K9*(1+L8) | M9: =L9*(1+M8) | N9: =M9*(1+N8)
B11: Profit and loss
B12: Gross margin (%) | D12: =Inputs!$D$18 | E12: =Inputs!$D$18 | F12: =Inputs!$D$18 | G12: =Inputs!$D$18 | H12: =Inputs!$D$18 | I12: =H12+Inputs!$D$19 | J12: =I12+Inputs!$D$19 | K12: =J12+Inputs!$D$19 | L12: =K12+Inputs!$D$19 | M12: =L12+Inputs!$D$19 | N12: =M12+Inputs!$D$19
B13: Gross profit | D13: =D9*D12 | E13: =E9*E12 | F13: =F9*F12 | G13: =G9*G12 | H13: =H9*H12 | I13: =I9*I12 | J13: =J9*J12 | K13: =K9*K12 | ... N13: =N9*N12
B14: Sales and marketing | D14: =D9*MAX(0.02,Inputs!$D$20+Inputs!$D$23*MAX(0,D5-2026)) | E14: =E9*MAX(0.02,Inputs!$D$20+Inputs!$D$23*MAX(0,E5-2026)) | F14: =F9*MAX(0.02,Inputs!$D$20+Inputs!$D$23*MAX(0,F5-2026)) | G14: =G9*MAX(0.02,Inputs!$D$20+Inputs!$D$23*MAX(0,G5-2026)) | H14: =H9*MAX(0.02,Inputs!$D$20+Inputs!$D$23*MAX(0,H5-2026)) | I14: =I9*MAX(0.02,Inputs!$D$20+Inputs!$D$23*MAX(0,I5-2026)) | J14: =J9*MAX(0.02,Inputs!$D$20+Inputs!$D$23*MAX(0,J5-2026)) | K14: =K9*MAX(0.02,Inputs!$D$20+Inputs!$D$23*MAX(0,K5-2026)) | ... N14: =N9*MAX(0.02,Inputs!$D$20+Inputs!$D$23*MAX(0,N5-2026))
B15: Research and development | D15: =D9*MAX(0.02,Inputs!$D$21+Inputs!$D$23*MAX(0,D5-2026)) | E15: =E9*MAX(0.02,Inputs!$D$21+Inputs!$D$23*MAX(0,E5-2026)) | F15: =F9*MAX(0.02,Inputs!$D$21+Inputs!$D$23*MAX(0,F5-2026)) | G15: =G9*MAX(0.02,Inputs!$D$21+Inputs!$D$23*MAX(0,G5-2026)) | H15: =H9*MAX(0.02,Inputs!$D$21+Inputs!$D$23*MAX(0,H5-2026)) | I15: =I9*MAX(0.02,Inputs!$D$21+Inputs!$D$23*MAX(0,I5-2026)) | J15: =J9*MAX(0.02,Inputs!$D$21+Inputs!$D$23*MAX(0,J5-2026)) | K15: =K9*MAX(0.02,Inputs!$D$21+Inputs!$D$23*MAX(0,K5-2026)) | ... N15: =N9*MAX(0.02,Inputs!$D$21+Inputs!$D$23*MAX(0,N5-2026))
B16: General and administrative | D16: =D9*MAX(0.02,Inputs!$D$22+Inputs!$D$23*MAX(0,D5-2026)) | E16: =E9*MAX(0.02,Inputs!$D$22+Inputs!$D$23*MAX(0,E5-2026)) | F16: =F9*MAX(0.02,Inputs!$D$22+Inputs!$D$23*MAX(0,F5-2026)) | G16: =G9*MAX(0.02,Inputs!$D$22+Inputs!$D$23*MAX(0,G5-2026)) | H16: =H9*MAX(0.02,Inputs!$D$22+Inputs!$D$23*MAX(0,H5-2026)) | I16: =I9*MAX(0.02,Inputs!$D$22+Inputs!$D$23*MAX(0,I5-2026)) | J16: =J9*MAX(0.02,Inputs!$D$22+Inputs!$D$23*MAX(0,J5-2026)) | K16: =K9*MAX(0.02,Inputs!$D$22+Inputs!$D$23*MAX(0,K5-2026)) | ... N16: =N9*MAX(0.02,Inputs!$D$22+Inputs!$D$23*MAX(0,N5-2026))
B17: Total operating expenses | D17: =SUM(D14:D16) | E17: =SUM(E14:E16) | F17: =SUM(F14:F16) | G17: =SUM(G14:G16) | H17: =SUM(H14:H16) | I17: =SUM(I14:I16) | J17: =SUM(J14:J16) | K17: =SUM(K14:K16) | ... N17: =SUM(N14:N16)
B18: Operating profit | D18: =D13-D17 | E18: =E13-E17 | F18: =F13-F17 | G18: =G13-G17 | H18: =H13-H17 | I18: =I13-I17 | J18: =J13-J17 | K18: =K13-K17 | ... N18: =N13-N17
B19: Operating margin (%) | D19: =IF(D9=0,0,D18/D9) | E19: =IF(E9=0,0,E18/E9) | F19: =IF(F9=0,0,F18/F9) | G19: =IF(G9=0,0,G18/G9) | H19: =IF(H9=0,0,H18/H9) | I19: =IF(I9=0,0,I18/I9) | J19: =IF(J9=0,0,J18/J9) | K19: =IF(K9=0,0,K18/K9) | ... N19: =IF(N9=0,0,N18/N9)
B21: Cash flow
B22: Tax | D22: =-MAX(0,D18)*Inputs!$D$29 | E22: =-MAX(0,E18)*Inputs!$D$29 | F22: =-MAX(0,F18)*Inputs!$D$29 | G22: =-MAX(0,G18)*Inputs!$D$29 | H22: =-MAX(0,H18)*Inputs!$D$29 | I22: =-MAX(0,I18)*Inputs!$D$29 | J22: =-MAX(0,J18)*Inputs!$D$29 | K22: =-MAX(0,K18)*Inputs!$D$29 | ... N22: =-MAX(0,N18)*Inputs!$D$29
B23: Capital expenditure and working capital (% of revenue) | D23: 0.04
B24: Capital expenditure and working capital | D24: =-D9*Model!$D$23 | E24: =-E9*Model!$D$23 | F24: =-F9*Model!$D$23 | G24: =-G9*Model!$D$23 | H24: =-H9*Model!$D$23 | I24: =-I9*Model!$D$23 | J24: =-J9*Model!$D$23 | K24: =-K9*Model!$D$23 | ... N24: =-N9*Model!$D$23
B25: Free cash flow | D25: =D18+D22+D24 | E25: =E18+E22+E24 | F25: =F18+F22+F24 | G25: =G18+G22+G24 | H25: =H18+H22+H24 | I25: =I18+I22+I24 | J25: =J18+J22+J24 | K25: =K18+K22+K24 | ... N25: =N18+N22+N24
B27: Per-employee and efficiency
B28: Revenue per employee ($000) | D28: =IF(D9=0,0,D9*1000/MAX(1,Inputs!$D$34)) | E28: =IF(E9=0,0,E9*1000/MAX(1,Inputs!$D$34)) | F28: =IF(F9=0,0,F9*1000/MAX(1,Inputs!$D$34)) | G28: =IF(G9=0,0,G9*1000/MAX(1,Inputs!$D$34)) | H28: =IF(H9=0,0,H9*1000/MAX(1,Inputs!$D$34)) | I28: =IF(I9=0,0,I9*1000/MAX(1,Inputs!$D$34)) | J28: =IF(J9=0,0,J9*1000/MAX(1,Inputs!$D$34)) | K28: =IF(K9=0,0,K9*1000/MAX(1,Inputs!$D$34)) | ... N28: =IF(N9=0,0,N9*1000/MAX(1,Inputs!$D$34))

Sheet Valuation
B2: CoreWeave — Valuation
B3: Discounted cash flow and an exit-multiple cross-check. All figures in USD millions.
D5: 2022 | E5: 2023 | F5: 2024 | G5: 2025 | H5: 2026 | I5: 2027 | J5: 2028 | K5: 2029 | L5: 2030 | M5: 2031 | N5: 2032
B7: Discounted cash flow
B8: Discount factor | D8: 0 | E8: 0 | F8: 0 | G8: 0 | H8: 0 | I8: =1/(1+Inputs!$D$28)^1 | J8: =1/(1+Inputs!$D$28)^2 | K8: =1/(1+Inputs!$D$28)^3 | L8: =1/(1+Inputs!$D$28)^4 | M8: =1/(1+Inputs!$D$28)^5 | N8: =1/(1+Inputs!$D$28)^6
B9: Present value of free cash flow | D9: 0 | E9: 0 | F9: 0 | G9: 0 | H9: 0 | I9: =Model!I25*I8 | J9: =Model!J25*J8 | K9: =Model!K25*K8 | L9: =Model!L25*L8 | M9: =Model!M25*M8 | N9: =Model!N25*N8
B11: Sum of discounted cash flows | D11: =SUM(I9:N9)
B12: Terminal value (perpetuity) | D12: =Model!N25*(1+Inputs!$D$14)/(Inputs!$D$28-Inputs!$D$14)*N8
B13: Terminal value (exit multiple) | D13: =Model!N9*Inputs!$D$30*N8
B14: Spread between the two methods | D14: =IF(MIN(D12,D13)=0,0,MAX(D12,D13)/MIN(D12,D13))
B15: Terminal value used (perpetuity; multiple is the cross-check) | D15: =D12
B17: Enterprise value | D17: =D11+D15
B19: Cross-checks against the stored mark
B20: Latest stored valuation | D20: =Inputs!$D$26
B21: Model value against the stored mark | D21: =IF(D20=0,0,Valuation!$D$17/D20)
B22: Stored mark against latest revenue | D22: =IF(Model!H9=0,0,D20/Model!H9)
B23: Stored mark per dollar of equity raised | D23: =IF(Inputs!$D$27=0,0,D20/Inputs!$D$27)

Sheet Outputs
B2: CoreWeave — Summary
B3: All figures in USD millions.
D5: 2022 | E5: 2023 | F5: 2024 | G5: 2025 | H5: 2026 | I5: 2027 | J5: 2028 | K5: 2029 | L5: 2030 | M5: 2031 | N5: 2032
B7: Revenue | D7: =Model!D9 | E7: =Model!E9 | F7: =Model!F9 | G7: =Model!G9 | H7: =Model!H9 | I7: =Model!I9 | J7: =Model!J9 | K7: =Model!K9 | ... N7: =Model!N9
B8: Gross profit | D8: =Model!D13 | E8: =Model!E13 | F8: =Model!F13 | G8: =Model!G13 | H8: =Model!H13 | I8: =Model!I13 | J8: =Model!J13 | K8: =Model!K13 | ... N8: =Model!N13
B9: Operating profit | D9: =Model!D18 | E9: =Model!E18 | F9: =Model!F18 | G9: =Model!G18 | H9: =Model!H18 | I9: =Model!I18 | J9: =Model!J18 | K9: =Model!K18 | ... N9: =Model!N18
B10: Free cash flow | D10: =Model!D25 | E10: =Model!E25 | F10: =Model!F25 | G10: =Model!G25 | H10: =Model!H25 | I10: =Model!I25 | J10: =Model!J25 | K10: =Model!K25 | ... N10: =Model!N25
B12: Enterprise value (discounted cash flow) | D12: =Valuation!$D$17
B14: What this business does
B15: Rents out AI computing power. Now a public company.
