Workbook

Sheet Controls
A1: Anthropic Operating Model - Controls
A3: SCENARIO | B3: Base
A4: BASIS | B4: Run-rate
A6: Block index | B6: =IF(B3="Base",IF(B4="Run-rate",1,2),IF(B3="Best",IF(B4="Run-rate",3,4),IF(B4="Run-rate",5,6)))
A8: How it works | B8: Pick a SCENARIO and BASIS above. The P&L Build sheet recomputes live via the block index in B6.
A9: SCENARIO | B9: Base / Best / Worst flex 2027-32 revenue growth plus inference and training-intensity margin levers. 2022-26 are actuals and identical across scenarios.
A10: BASIS | B10: Run-rate = annualized/exit basis (matches PitchBook TTM; 2026 ~breakeven). Recognized = GAAP-style recognized revenue (~50% of run-rate in 2026); workforce and capex are held at absolute levels, so the recognized view carries a wider operating loss.
A11: Charts | B11: The Charts sheet is a fixed Base / Run-rate snapshot (renders without recalculation). The P&L Build table is the live switchable view.
A12: Recalc | B12: If figures look blank on open, press Ctrl+Alt+F9 (Excel) to force a full recalculation.

Sheet P&L Build
A1: Anthropic PBC - Operating Model 2022A-2032E | Base / Run-rate view ($M unless noted). Live Scenario/Basis switch: see Controls + "Live Switch" sheet.
A2: Line Item | B2: Type | C2: Unit | D2: What it is | E2: 2022 | F2: 2023 | G2: 2024 | H2: 2025 | I2: 2026 | J2: 2027 | K2: 2028 | L2: 2029 | M2: 2030 | N2: 2031 | O2: 2032
A3: REVENUE
A4: Booked revenue | B4: IN | C4: $M | D4: Anchor. 2022-26 PitchBook TTM (10/100/1,000/9,000/47,000); 2027-32 base case. PB carries 55,000 for 2027 as a conservative mark. | E4: 10 | F4: 100 | G4: 1000 | H4: 9000 | I4: 47000 | J4: 80000 | K4: 115000 | L4: 150000 | M4: 185000 | N4: 215000 | O4: 245000
A5: API PRICING AND BLENDED EFFECTIVE RATE
A6: Model mix % - Mythos | B6: IN | C6: % | D6: Token share, flagship tier (Fable 5 / Mythos 5, $10/$50). Introduced 2026. | E6: 0 | F6: 0 | G6: 0 | H6: 0 | I6: 0.03 | J6: 0.05 | K6: 0.06 | L6: 0.07 | M6: 0.08 | N6: 0.09 | O6: 0.1
A7: Model mix % - Opus | B7: IN | C7: % | D7: Token share, Opus ($15/$75 to Aug-2025, cut to $5/$25 at Opus 4.5). | E7: 0 | F7: 0.1 | G7: 0.08 | H7: 0.1 | I7: 0.12 | J7: 0.12 | K7: 0.12 | L7: 0.12 | M7: 0.12 | N7: 0.12 | O7: 0.12
A8: Model mix % - Sonnet | B8: IN | C8: % | D8: Token share, Sonnet workhorse ($3/$15). | E8: 0.4 | F8: 0.3 | G8: 0.32 | H8: 0.45 | I8: 0.45 | J8: 0.44 | K8: 0.43 | L8: 0.42 | M8: 0.41 | N8: 0.4 | O8: 0.4
A9: Model mix % - Haiku | B9: IN | C9: % | D9: Token share, Haiku ($0.25/$1.25 -> $1/$5). | E9: 0.6 | F9: 0.6 | G9: 0.6 | H9: 0.45 | I9: 0.4 | J9: 0.39 | K9: 0.39 | L9: 0.39 | M9: 0.39 | N9: 0.39 | O9: 0.38
A10: List input $/Mtok - Mythos | B10: IN | C10: $ | D10: List input price, flagship. | E10: 15 | F10: 15 | G10: 15 | H10: 15 | I10: 15 | J10: 15 | K10: 14 | L10: 13 | M10: 12 | N10: 12 | O10: 11
A11: List input $/Mtok - Opus | B11: IN | C11: $ | D11: List input price, Opus. | E11: 11 | F11: 8 | G11: 15 | H11: 15 | I11: 5 | J11: 5 | K11: 5 | L11: 4.5 | M11: 4.5 | N11: 4 | O11: 4
A12: List input $/Mtok - Sonnet | B12: IN | C12: $ | D12: List input price, Sonnet. | E12: 3 | F12: 3 | G12: 3 | H12: 3 | I12: 3 | J12: 3 | K12: 3 | L12: 2.5 | M12: 2.5 | N12: 2 | O12: 2
A13: List input $/Mtok - Haiku | B13: IN | C13: $ | D13: List input price, Haiku. | E13: 0.8 | F13: 0.8 | G13: 0.25 | H13: 0.8 | I13: 1 | J13: 1 | K13: 1 | L13: 0.9 | M13: 0.9 | N13: 0.8 | O13: 0.8
A14: List output $/Mtok - Mythos | B14: IN | C14: $ | D14: List output price, flagship. | E14: 75 | F14: 75 | G14: 75 | H14: 75 | I14: 75 | J14: 70 | K14: 65 | L14: 60 | M14: 55 | N14: 55 | O14: 50
A15: List output $/Mtok - Opus | B15: IN | C15: $ | D15: List output price, Opus. | E15: 33 | F15: 24 | G15: 75 | H15: 75 | I15: 25 | J15: 25 | K15: 22 | L15: 22 | M15: 20 | N15: 20 | O15: 18
A16: List output $/Mtok - Sonnet | B16: IN | C16: $ | D16: List output price, Sonnet. | E16: 15 | F16: 15 | G16: 15 | H16: 15 | I16: 15 | J16: 15 | K16: 13 | L16: 13 | M16: 12 | N16: 10 | O16: 10
A17: List output $/Mtok - Haiku | B17: IN | C17: $ | D17: List output price, Haiku. | E17: 2.4 | F17: 2.4 | G17: 1.25 | H17: 4 | I17: 5 | J17: 5 | K17: 4.5 | L17: 4.5 | M17: 4 | N17: 4 | O17: 3.6
... A27: Blended effective $/Mtok | B27: CALC | C27: $ | D27: Mix-weighted, adjusted for input share, caching, batch. | E27: 2.9806452 | F27: 3.4768421 | G27: 3.793749 | H27: 4.1467112 | I27: 3.0571739 | J27: 2.9587834 | K27: 2.6527823 | L27: 2.3780343 | M27: 2.2407352 | N27: 2.0581018 | O27: 1.9921081
A28: NON-API REVENUE STREAMS
A29: # Enterprise contracts (>$1M ARR) | B29: IN | C29: count | D29: ~1,000+ at $1M+ ACV by 2026. | E29: 0 | F29: 5 | G29: 60 | H29: 300 | I29: 1000 | J29: 1700 | K29: 2400 | L29: 3100 | M29: 3700 | N29: 4200 | O29: 4600
A30: Committed-use discount % (memo) | B30: IN | C30: % | D30: Volume discount realized on enterprise API. | E30: 0 | F30: 0.05 | G30: 0.1 | H30: 0.12 | I30: 0.15 | J30: 0.15 | K30: 0.16 | L30: 0.16 | M30: 0.17 | N30: 0.17 | O30: 0.18
A31: Active enterprise dashboard seats | B31: IN | C31: count | D31: Console/admin seats. | E31: 0 | F31: 2000 | G31: 40000 | H31: 250000 | I31: 900000 | J31: 1600000 | K31: 2300000 | L31: 3000000 | M31: 3600000 | N31: 4100000 | O31: 4500000
A32: Enterprise platform fee / seat / mo | B32: IN | C32: $ | D32: Monthly platform fee per seat. | E32: 0 | F32: 30 | G32: 35 | H32: 40 | I32: 45 | J32: 48 | K32: 50 | L32: 52 | M32: 54 | N32: 55 | O32: 56
A33: Enterprise seat revenue | B33: CALC | C33: $M | D33: seats x fee x 12. | E33: 0 | F33: 0.72 | G33: 16.8 | H33: 120 | I33: 486 | J33: 921.6 | K33: 1380 | L33: 1872 | M33: 2332.8 | N33: 2706 | O33: 3024
A34: Consumer subscription revenue (anchor) | B34: IN | C34: $M | D34: Claude Pro ($20) + Max ($100/$200). | E34: 0 | F34: 8 | G34: 120 | H34: 1300 | I34: 6600 | J34: 11200 | K34: 16100 | L34: 21000 | M34: 25900 | N34: 30100 | O34: 34300
A35: Blended consumer ARPU ($/mo) | B35: IN | C35: $ | D35: Blend of Pro and Max. | E35: 20 | F35: 20 | G35: 21 | H35: 23 | I35: 26 | J35: 28 | K35: 29 | L35: 30 | M35: 31 | N35: 32 | O35: 33
A36: Paying consumer subs (implied) | B36: PLUG | C36: Count | D36: consumer rev / (ARPU x 12). | E36: 0 | F36: 33333.333 | G36: 476190.48 | H36: 4710144.9 | I36: 21153846 | J36: 33333333 | K36: 46264368 | L36: 58333333 | M36: 69623656 | N36: 78385417 | O36: 86616162
A37: Active developer seats | B37: IN | C37: Count | D37: Claude Code seats (Feb-2025). | E37: 0 | F37: 0 | G37: 0 | H37: 350000 | I37: 1100000 | J37: 1800000 | K37: 2500000 | L37: 3100000 | M37: 3600000 | N37: 4000000 | O37: 4300000
A38: Base seat fee ($/mo) | B38: IN | C38: $ | D38: Claude Code base seat fee. | E38: 0 | F38: 0 | G38: 0 | H38: 20 | I38: 22 | J38: 24 | K38: 25 | L38: 26 | M38: 27 | N38: 28 | O38: 28
A39: Claude Code base seat revenue | B39: CALC | C39: $M | D39: seats x fee x 12. | E39: 0 | F39: 0 | G39: 0 | H39: 84 | I39: 290.4 | J39: 518.4 | K39: 750 | L39: 967.2 | M39: 1166.4 | N39: 1344 | O39: 1444.8
A40: Avg overage tokens / dev / mo | B40: IN | C40: Mtok | D40: Usage above base seat. | E40: 0 | F40: 0 | G40: 0 | H40: 12 | I40: 20 | J40: 26 | K40: 30 | L40: 33 | M40: 36 | N40: 38 | O40: 40
... A60: Total non-API revenue | B60: CALC | C60: $M | D60: Sum of non-API streams. | E60: 0 | F60: 17.72 | G60: 300.115 | H60: 3188.7792 | I60: 13998.754 | J60: 23319.133 | K60: 32789.275 | L60: 41925.307 | M60: 50563.131 | N60: 57976.56 | O60: 64889.009
A61: FIRST PARTY DIRECT API REVENUE
A62: First-party API revenue | B62: PLUG | C62: $M | D62: Booked revenue minus non-API streams. | E62: 10 | F62: 82.28 | G62: 699.885 | H62: 5811.2208 | I62: 33001.246 | J62: 56680.867 | K62: 82210.725 | L62: 108074.69 | M62: 134436.87 | N62: 157023.44 | O62: 180110.99
A63: API TOKEN ENGINE
A64: Total tokens processed (all) | B64: PLUG | C64: T | D64: API revenue / blended $/Mtok (trillions). | E64: 3.3549784 | F64: 23.665153 | G64: 184.48374 | H64: 1401.4047 | I64: 10794.69 | J64: 19156.816 | K64: 30990.377 | L64: 45447.071 | M64: 59996.768 | N64: 76295.274 | O64: 90412.257
A65: Total input tokens | B65: CALC | C65: T | D65: tokens x input share. | E65: 2.5974026 | F65: 18.683015 | G65: 151.21618 | H65: 1208.1075 | I65: 9386.6874 | J65: 16857.998 | K65: 27459.828 | L65: 40663.169 | M65: 53770.689 | N65: 68470.117 | O65: 81229.762
A66: Total output tokens | B66: CALC | C66: T | D66: tokens x (1 - input share). | E66: 0.75757576 | F66: 4.9821375 | G66: 33.26756 | H66: 193.29721 | I66: 1408.0031 | J66: 2298.8179 | K66: 3530.5493 | L66: 4783.9022 | M66: 6226.0797 | N66: 7825.1563 | O66: 9182.4948
A67: Total first-party API calls | B67: CALC | C67: B | D67: tokens / tokens-per-call (billions). | E67: 2.1645022 | F67: 12.455344 | G67: 60.486472 | H67: 241.62151 | I67: 1173.3359 | J67: 1532.5452 | K67: 1961.4163 | L67: 2391.9511 | M67: 2830.0362 | N67: 3260.4818 | O67: 3531.7288
A68: Memo: calls / contract / day | B68: CALC | C68: # | D68: calls / contracts / 365. | E68: 5930142.9 | F68: 6824845.8 | G68: 2761939.4 | H68: 2206589.1 | I68: 3214619 | J68: 2469855.4 | K68: 2239059.7 | L68: 2113964.8 | M68: 2095547 | N68: 2126863.5 | O68: 2103471.6
A69: COSTS - Inference and infrastructure
A70: Billed tokens (Anthropic-served) | B70: LINK | C70: T | D70: API + consumer + Claude Code (excl Bedrock/Vertex). | E70: 3.3549784 | F70: 23.685153 | G70: 184.88374 | H70: 1457.8047 | I70: 11092.69 | J70: 19780.416 | K70: 31982.377 | L70: 46796.671 | M70: 61701.968 | N70: 78295.274 | O70: 92676.257
A71: Free-tier tokens served | B71: IN | C71: T | D71: Non-billed free-tier usage. | E71: 1.6774892 | F71: 10.658319 | G71: 73.953496 | H71: 510.23166 | I71: 3327.8071 | J71: 5538.5164 | K71: 8315.4181 | L71: 11699.168 | M71: 14808.472 | N71: 18007.913 | O71: 20388.776
A72: Internal / testing tokens | B72: IN | C72: T | D72: Evals/red-team/internal. | E72: 1.0064935 | F72: 5.9212882 | G72: 36.976748 | H72: 218.67071 | I72: 1331.1229 | J72: 2175.8457 | K72: 3198.2377 | L72: 4679.6671 | M72: 5553.1772 | N72: 7046.5746 | O72: 7414.1005
A73: Gross tokens served | B73: CALC | C73: T | D73: billed + free + internal. | E73: 6.038961 | F73: 40.26476 | G73: 295.81398 | H73: 2186.7071 | I73: 15751.62 | J73: 27494.778 | K73: 43496.033 | L73: 63175.506 | M73: 82063.618 | N73: 103349.76 | O73: 120479.13
A74: Tokens per GPU-hour | B74: IN | C74: tok/hr | D74: Serving throughput (back-solved for consistency). | E74: 3358566.6 | F74: 3155545.4 | G74: 2862716 | H74: 2822349.3 | I74: 4051153.3 | J74: 4176724 | K74: 4555605.6 | L74: 5105091.4 | M74: 5419767.5 | N74: 5930671.9 | O74: 6138599.2
A75: Required GPU-hours | B75: CALC | C75: hr | D75: gross tokens / tokens-per-GPU-hour. | E75: 1798076.9 | F75: 12760000 | G75: 1.0333333e+08 | H75: 7.7478261e+08 | I75: 3.8881818e+09 | J75: 6.5828571e+09 | K75: 9.5478049e+09 | L75: 12375000000 | M75: 1.5141538e+10 | N75: 1.7426316e+10 | O75: 1.9626486e+10
A76: Fleet utilization % | B76: IN | C76: % | D76: Effective serving utilization. | E76: 0.55 | F76: 0.58 | G76: 0.62 | H76: 0.66 | I76: 0.7 | J76: 0.72 | K76: 0.74 | L76: 0.75 | M76: 0.76 | N76: 0.77 | O76: 0.78
A77: Total provisioned GPU-hours | B77: CALC | C77: hr | D77: required / utilization. | E77: 3269230.8 | F77: 22000000 | G77: 1.6666667e+08 | H77: 1.173913e+09 | I77: 5.5545455e+09 | J77: 9.1428571e+09 | K77: 1.2902439e+10 | L77: 16500000000 | M77: 1.9923077e+10 | N77: 2.2631579e+10 | O77: 2.5162162e+10
A78: Blended $/GPU-hour | B78: IN | C78: $ | D78: Owned + rented all-in hourly cost. | E78: 2.6 | F78: 2.5 | G78: 2.4 | H78: 2.3 | I78: 2.2 | J78: 2.1 | K78: 2.05 | L78: 2 | M78: 1.95 | N78: 1.9 | O78: 1.85
A79: Inference compute cost | B79: CALC | C79: $M | D79: Declining share of revenue; GPU-hrs x $/GPU-hr. | E79: 8.5 | F79: 55 | G79: 400 | H79: 2700 | I79: 12220 | J79: 19200 | K79: 26450 | L79: 33000 | M79: 38850 | N79: 43000 | O79: 46550
A80: Data egress volume (PB) | B80: IN | C80: PB | D80: Outbound data volume. | E80: 0.5 | F80: 3 | G80: 20 | H80: 120 | I80: 480 | J80: 800 | K80: 1150 | L80: 1500 | M80: 1850 | N80: 2150 | O80: 2450
A81: Egress cost ($/TB) | B81: IN | C81: $ | D81: Blended egress unit cost. | E81: 20 | F81: 18 | G81: 16 | H81: 14 | I81: 12 | J81: 11 | K81: 10 | L81: 9 | M81: 9 | N81: 8 | O81: 8
... A84: API gateway and load-balancing | B84: IN | C84: $M | D84: Edge/gateway/LB. | E84: 0.3 | F84: 2 | G84: 10 | H84: 55 | I84: 200 | J84: 320 | K84: 440 | L84: 560 | M84: 680 | N84: 780 | O84: 880
A85: COSTS - SAFETY, PAYMENTS, SUPPORT
A86: Content moderation cost $/Mtok | B86: IN | C86: $ | D86: Classifier cost per Mtok gross. | E86: 0.05 | F86: 0.05 | G86: 0.04 | H86: 0.035 | I86: 0.03 | J86: 0.028 | K86: 0.026 | L86: 0.025 | M86: 0.024 | N86: 0.023 | O86: 0.022
A87: Automated moderation cost | B87: CALC | C87: $M | D87: gross tokens x $/Mtok. | E87: 0.30194805 | F87: 2.013238 | G87: 11.832559 | H87: 76.534749 | I87: 472.54861 | J87: 769.85378 | K87: 1130.8969 | L87: 1579.3877 | M87: 1969.5268 | N87: 2377.0445 | O87: 2650.5409
A88: HITL review volume | B88: IN | C88: Count | D88: Human safety reviews / yr. | E88: 20000 | F88: 120000 | G88: 700000 | H88: 3500000 | I88: 12000000 | J88: 19000000 | K88: 26000000 | L88: 33000000 | M88: 39000000 | N88: 44000000 | O88: 48000000
A89: Cost per HITL review | B89: IN | C89: $ | D89: BPO hourly x hours. | E89: 4 | F89: 4 | G89: 3.8 | H89: 3.6 | I89: 3.5 | J89: 3.4 | K89: 3.3 | L89: 3.2 | M89: 3.2 | N89: 3.1 | O89: 3
A90: HITL review cost | B90: CALC | C90: $M | D90: volume x cost. | E90: 0.08 | F90: 0.48 | G90: 2.66 | H90: 12.6 | I90: 42 | J90: 64.6 | K90: 85.8 | L90: 105.6 | M90: 124.8 | N90: 136.4 | O90: 144
A91: B2B gross cash collections | B91: LINK | C91: $M | D91: API + seats + CC + FT + PT + PS. | E91: 10 | F91: 84.8 | G91: 747.9 | H91: 6424 | I91: 35342 | J91: 61142 | K91: 88720 | L91: 116478 | M91: 144676 | N91: 168647 | O91: 193038
A92: Payment processing fee % (Stripe) | B92: IN | C92: % | D92: Blended processor fee. | E92: 0.029 | F92: 0.028 | G92: 0.027 | H92: 0.026 | I92: 0.025 | J92: 0.024 | K92: 0.024 | L92: 0.023 | M92: 0.023 | N92: 0.022 | O92: 0.022
A93: B2B payment processing cost | B93: CALC | C93: $M | D93: collections x fee. | E93: 0.29 | F93: 2.3744 | G93: 20.1933 | H93: 167.024 | I93: 883.55 | J93: 1467.408 | K93: 2129.28 | L93: 2678.994 | M93: 3327.548 | N93: 3710.234 | O93: 4246.836
A94: Mobile share of consumer revenue % | B94: IN | C94: % | D94: Consumer via mobile stores. | E94: 0 | F94: 0.2 | G94: 0.3 | H94: 0.35 | I94: 0.38 | J94: 0.4 | K94: 0.4 | L94: 0.4 | M94: 0.39 | N94: 0.39 | O94: 0.38
A95: B2C mobile collections | B95: CALC | C95: $M | D95: consumer rev x mobile share. | E95: 0 | F95: 1.6 | G95: 36 | H95: 455 | I95: 2508 | J95: 4480 | K95: 6440 | L95: 8400 | M95: 10101 | N95: 11739 | O95: 13034
A96: App store take-rate % | B96: IN | C96: % | D96: Apple/Google store take. | E96: 0 | F96: 0.3 | G96: 0.3 | H96: 0.28 | I96: 0.2 | J96: 0.2 | K96: 0.18 | L96: 0.18 | M96: 0.17 | N96: 0.17 | O96: 0.15
A97: App store cost | B97: CALC | C97: $M | D97: mobile collections x take. | E97: 0 | F97: 0.48 | G97: 10.8 | H97: 127.4 | I97: 501.6 | J97: 896 | K97: 1159.2 | L97: 1512 | M97: 1717.17 | N97: 1995.63 | O97: 1955.1
... A106: Memo: implied gross margin % | B106: CALC | C106: % | D106: Inference-only gross margin. | E106: 0.030605195 | F106: 0.36418362 | G106: 0.53679914 | H106: 0.64648458 | I106: 0.69225194 | J106: 0.71317646 | K106: 0.72429775 | L106: 0.73448534 | M106: 0.74519012 | N106: 0.75564615 | O106: 0.76722654
A107: OpEx & Comp (ex-SBC)
A108: R&D headcount | B108: IN | C108: count | D108: Research + eng (~65-75% of total). | E108: 40 | F108: 130 | G108: 270 | H108: 700 | I108: 3250 | J108: 4800 | K108: 6000 | L108: 6900 | M108: 7500 | N108: 7900 | O108: 8300
A109: Fully-burdened R&D cash comp ($/head) | B109: IN | C109: $ | D109: Levels.fyi eng $619-841k, research ~$746k median. | E109: 400000 | F109: 420000 | G109: 450000 | H109: 480000 | I109: 520000 | J109: 545000 | K109: 565000 | L109: 580000 | M109: 595000 | N109: 605000 | O109: 615000
A110: R&D personnel cost | B110: CALC | C110: $M | D110: heads x comp. | E110: 16 | F110: 54.6 | G110: 121.5 | H110: 336 | I110: 1690 | J110: 2616 | K110: 3390 | L110: 4002 | M110: 4462.5 | N110: 4779.5 | O110: 5104.5
A111: RLHF & data annotation | B111: IN | C111: $M | D111: Human feedback/annotation. | E111: 2 | F111: 8 | G111: 60 | H111: 300 | I111: 620 | J111: 900 | K111: 1150 | L111: 1400 | M111: 1600 | N111: 1750 | O111: 1900
A112: Proprietary data licensing | B112: IN | C112: $M | D112: Licensed training data. | E112: 0 | F112: 3 | G112: 25 | H112: 120 | I112: 400 | J112: 620 | K112: 820 | L112: 1000 | M112: 1150 | N112: 1280 | O112: 1400
A113: Experimental / failed training runs | B113: IN | C113: $M | D113: Abandoned run compute. | E113: 3 | F113: 12 | G113: 90 | H113: 380 | I113: 620 | J113: 850 | K113: 1050 | L113: 1250 | M113: 1400 | N113: 1520 | O113: 1650
A114: Internal tooling & subscriptions | B114: IN | C114: $M | D114: Dev tooling/SaaS. | E114: 1 | F114: 4 | G114: 30 | H114: 150 | I114: 380 | J114: 560 | K114: 720 | L114: 880 | M114: 1010 | N114: 1130 | O114: 1240
A115: Capitalizable frontier-training runs | B115: IN | C115: $M | D115: Capitalizable portion (~30% of training). | E115: 10.5 | F115: 36 | G115: 1050 | H115: 1215 | I115: 6063 | J115: 8400 | K115: 10350 | L115: 11700 | M115: 12765 | N115: 13545 | O115: 13965
A116: Cap toggle (1=capitalized, 0=ASC 730 expense) | B116: IN | C116: 0/1 | D116: 0 = expense training to R&D (base). | E116: 0 | F116: 0 | G116: 0 | H116: 0 | I116: 0 | J116: 0 | K116: 0 | L116: 0 | M116: 0 | N116: 0 | O116: 0
A117: Training compute expenses to R&D | B117: CALC | C117: $M | D117: Training (expensed) + research compute. Primary loss driver. | E117: 41 | F117: 145 | G117: 4050 | H117: 4950 | I117: 24440 | J117: 34400 | K117: 42550 | L117: 48000 | M117: 52725 | N117: 55900 | O117: 57575
A118: Total R&D (ex-SBC) | B118: CALC | C118: $M | D118: Personnel + RLHF + licensing + failed + tooling + training. | E118: 63 | F118: 226.6 | G118: 4376.5 | H118: 6236 | I118: 28150 | J118: 39946 | K118: 49680 | L118: 56532 | M118: 62347.5 | N118: 66359.5 | O118: 68869.5
A119: S&M Headcount | B119: IN | C119: count | D119: GTM heads (small org). | E119: 8 | F119: 30 | G119: 70 | H119: 180 | I119: 900 | J119: 1450 | K119: 1900 | L119: 2250 | M119: 2500 | N119: 2700 | O119: 2850
... A133: One-time litigation services | B133: IN | C133: $M | D133: Non-recurring litigation. | E133: 0 | F133: 0 | G133: 5 | H133: 40 | I133: 150 | J133: 90 | K133: 60 | L133: 50 | M133: 45 | N133: 40 | O133: 40
A134: STOCK BASED COMP
A135: SBC issue rate (% of base cash comp) | B135: IN | C135: % | D135: RSU grant value as % of cash comp. | E135: 0.4 | F135: 0.45 | G135: 0.5 | H135: 0.55 | I135: 0.55 | J135: 0.5 | K135: 0.45 | L135: 0.42 | M135: 0.4 | N135: 0.38 | O135: 0.36
A136: R&D SBC | B136: CALC | C136: $M | D136: R&D cash x SBC rate. | E136: 6.4 | F136: 24.57 | G136: 60.75 | H136: 184.8 | I136: 929.5 | J136: 1308 | K136: 1525.5 | L136: 1680.84 | M136: 1785 | N136: 1816.21 | O136: 1837.62
A137: S&M SBC | B137: CALC | C137: $M | D137: S&M cash x SBC rate. | E137: 0.896 | F137: 3.915 | G137: 10.5 | H137: 30.69 | I137: 158.4 | J137: 239.25 | K137: 290.7 | L137: 330.75 | M137: 358 | N137: 374.49 | O137: 381.672
A138: G&A SBC | B138: CALC | C138: $M | D138: G&A cash x SBC rate. | E138: 1.248 | F138: 3.888 | G138: 8.4 | H138: 27.115 | I138: 140.25 | J138: 192.5 | K138: 226.8 | L138: 250.194 | M138: 262.4 | N138: 279.224 | O138: 287.64
A139: Total SBC | B139: CALC | C139: $M | D139: Sum of function SBC. | E139: 8.544 | F139: 32.373 | G139: 79.65 | H139: 242.605 | I139: 1228.15 | J139: 1739.75 | K139: 2043 | L139: 2261.784 | M139: 2405.4 | N139: 2469.924 | O139: 2506.932
A140: DEPRECIATION & AMORTIZATION
A141: Amort life - models (yrs) | B141: IN | C141: yr | D141: Life of capitalized models. | E141: 2 | F141: 2 | G141: 2 | H141: 2 | I141: 2 | J141: 2 | K141: 2 | L141: 2 | M141: 2 | N141: 2 | O141: 2
A142: Amort of capitalized frontier models | B142: CALC | C142: $M | D142: 2-yr straight-line of cap pool. | E142: 5.25 | F142: 23.25 | G142: 543 | H142: 1132.5 | I142: 3639 | J142: 7231.5 | K142: 9375 | L142: 11025 | M142: 12232.5 | N142: 13155 | O142: 13755
A143: Owned GPU / datacenter capex | B143: IN | C143: $M | D143: Owned hardware capex (Fluidstack $50B ramps 2026+). | E143: 2 | F143: 8 | G143: 40 | H143: 220 | I143: 1400 | J143: 3200 | K143: 5000 | L143: 6500 | M143: 7500 | N143: 8200 | O143: 8800
A144: Depreciation life - HW (yrs) | B144: IN | C144: yr | D144: Life of owned accelerators. | E144: 4 | F144: 4 | G144: 4 | H144: 5 | I144: 5 | J144: 5 | K144: 6 | L144: 6 | M144: 6 | N144: 6 | O144: 6
A145: Depreciation of owned GPU / datacenter | B145: CALC | C145: $M | D145: Vintage straight-line depreciation. | E145: 0.5 | F145: 2.5 | G145: 12.5 | H145: 56.5 | I145: 336 | J145: 974 | K145: 1797.3333 | L145: 2880.6667 | M145: 4086.6667 | N145: 5173.3333 | O145: 6000
A146: Amort of prepaid cloud commits (reclass) | B146: MEMO | C146: $M | D146: Reclass memo. NOT added to P&L D&A (guard). | E146: 0 | F146: 0 | G146: 20 | H146: 120 | I146: 500 | J146: 800 | K146: 1050 | L146: 1300 | M146: 1500 | N146: 1650 | O146: 1800
A147: Total D&A | B147: CALC | C147: $M | D147: Model amort + owned HW dep (prepaid-cloud excluded). | E147: 5.75 | F147: 25.75 | G147: 555.5 | H147: 1189 | I147: 3975 | J147: 8205.5 | K147: 11172.333 | L147: 13905.667 | M147: 16319.167 | N147: 18328.333 | O147: 19755
A148: P&L SUMMARY (memo)
A149: Gross profit | B149: CALC | C149: $M | D149: Revenue - cost of revenue. | E149: 0.30605195 | F149: 36.418362 | G149: 536.79914 | H149: 5818.3613 | I149: 32535.841 | J149: 57054.117 | K149: 83294.241 | L149: 110172.8 | M149: 137860.17 | N149: 162463.92 | O149: 187970.5
A150: Operating income (ex-SBC) | B150: CALC | C150: $M | D150: GP - R&D - S&M - G&A - D&A. | E150: -75.803948 | F150: -244.27164 | G150: -4514.0009 | H150: -2191.7387 | I150: -1922.1586 | J150: 5269.117 | K150: 17741.907 | L150: 34081.934 | M150: 52737.505 | N150: 70598.788 | O150: 91561.802
A151: Operating income (incl-SBC) | B151: CALC | C151: $M | D151: After stock-based comp. | E151: -84.347948 | F151: -276.64464 | G151: -4593.6509 | H151: -2434.3437 | I151: -3150.3086 | J151: 3529.367 | K151: 15698.907 | L151: 31820.15 | M151: 50332.105 | N151: 68128.864 | O151: 89054.87
...

Sheet Live Switch
A1: LIVE SWITCH - reflects Scenario & Basis chosen on the Controls sheet (press Ctrl+Alt+F9 if cells look blank)
A2: Line Item | B2: Type | C2: Unit | D2: What it is | E2: 2022 | F2: 2023 | G2: 2024 | H2: 2025 | I2: 2026 | J2: 2027 | K2: 2028 | L2: 2029 | M2: 2030 | N2: 2031 | O2: 2032
A3: REVENUE
A4: Booked revenue | B4: IN | C4: $M | D4: Anchor. 2022-26 PitchBook TTM (10/100/1,000/9,000/47,000); 2027-32 base case. PB carries 55,000 for 2027 as a conservative mark. | E4: =CHOOSE(Controls!$B$6,D1!E4,D2!E4,D3!E4,D4!E4,D5!E4,D6!E4) | F4: =CHOOSE(Controls!$B$6,D1!F4,D2!F4,D3!F4,D4!F4,D5!F4,D6!F4) | G4: =CHOOSE(Controls!$B$6,D1!G4,D2!G4,D3!G4,D4!G4,D5!G4,D6!G4) | H4: =CHOOSE(Controls!$B$6,D1!H4,D2!H4,D3!H4,D4!H4,D5!H4,D6!H4) | I4: =CHOOSE(Controls!$B$6,D1!I4,D2!I4,D3!I4,D4!I4,D5!I4,D6!I4) | J4: =CHOOSE(Controls!$B$6,D1!J4,D2!J4,D3!J4,D4!J4,D5!J4,D6!J4) | K4: =CHOOSE(Controls!$B$6,D1!K4,D2!K4,D3!K4,D4!K4,D5!K4,D6!K4) | L4: =CHOOSE(Controls!$B$6,D1!L4,D2!L4,D3!L4,D4!L4,D5!L4,D6!L4) | ... O4: =CHOOSE(Controls!$B$6,D1!O4,D2!O4,D3!O4,D4!O4,D5!O4,D6!O4)
A5: API PRICING AND BLENDED EFFECTIVE RATE
A6: Model mix % - Mythos | B6: IN | C6: % | D6: Token share, flagship tier (Fable 5 / Mythos 5, $10/$50). Introduced 2026. | E6: =CHOOSE(Controls!$B$6,D1!E6,D2!E6,D3!E6,D4!E6,D5!E6,D6!E6) | F6: =CHOOSE(Controls!$B$6,D1!F6,D2!F6,D3!F6,D4!F6,D5!F6,D6!F6) | G6: =CHOOSE(Controls!$B$6,D1!G6,D2!G6,D3!G6,D4!G6,D5!G6,D6!G6) | H6: =CHOOSE(Controls!$B$6,D1!H6,D2!H6,D3!H6,D4!H6,D5!H6,D6!H6) | I6: =CHOOSE(Controls!$B$6,D1!I6,D2!I6,D3!I6,D4!I6,D5!I6,D6!I6) | J6: =CHOOSE(Controls!$B$6,D1!J6,D2!J6,D3!J6,D4!J6,D5!J6,D6!J6) | K6: =CHOOSE(Controls!$B$6,D1!K6,D2!K6,D3!K6,D4!K6,D5!K6,D6!K6) | L6: =CHOOSE(Controls!$B$6,D1!L6,D2!L6,D3!L6,D4!L6,D5!L6,D6!L6) | ... O6: =CHOOSE(Controls!$B$6,D1!O6,D2!O6,D3!O6,D4!O6,D5!O6,D6!O6)
A7: Model mix % - Opus | B7: IN | C7: % | D7: Token share, Opus ($15/$75 to Aug-2025, cut to $5/$25 at Opus 4.5). | E7: =CHOOSE(Controls!$B$6,D1!E7,D2!E7,D3!E7,D4!E7,D5!E7,D6!E7) | F7: =CHOOSE(Controls!$B$6,D1!F7,D2!F7,D3!F7,D4!F7,D5!F7,D6!F7) | G7: =CHOOSE(Controls!$B$6,D1!G7,D2!G7,D3!G7,D4!G7,D5!G7,D6!G7) | H7: =CHOOSE(Controls!$B$6,D1!H7,D2!H7,D3!H7,D4!H7,D5!H7,D6!H7) | I7: =CHOOSE(Controls!$B$6,D1!I7,D2!I7,D3!I7,D4!I7,D5!I7,D6!I7) | J7: =CHOOSE(Controls!$B$6,D1!J7,D2!J7,D3!J7,D4!J7,D5!J7,D6!J7) | K7: =CHOOSE(Controls!$B$6,D1!K7,D2!K7,D3!K7,D4!K7,D5!K7,D6!K7) | L7: =CHOOSE(Controls!$B$6,D1!L7,D2!L7,D3!L7,D4!L7,D5!L7,D6!L7) | ... O7: =CHOOSE(Controls!$B$6,D1!O7,D2!O7,D3!O7,D4!O7,D5!O7,D6!O7)
A8: Model mix % - Sonnet | B8: IN | C8: % | D8: Token share, Sonnet workhorse ($3/$15). | E8: =CHOOSE(Controls!$B$6,D1!E8,D2!E8,D3!E8,D4!E8,D5!E8,D6!E8) | F8: =CHOOSE(Controls!$B$6,D1!F8,D2!F8,D3!F8,D4!F8,D5!F8,D6!F8) | G8: =CHOOSE(Controls!$B$6,D1!G8,D2!G8,D3!G8,D4!G8,D5!G8,D6!G8) | H8: =CHOOSE(Controls!$B$6,D1!H8,D2!H8,D3!H8,D4!H8,D5!H8,D6!H8) | I8: =CHOOSE(Controls!$B$6,D1!I8,D2!I8,D3!I8,D4!I8,D5!I8,D6!I8) | J8: =CHOOSE(Controls!$B$6,D1!J8,D2!J8,D3!J8,D4!J8,D5!J8,D6!J8) | K8: =CHOOSE(Controls!$B$6,D1!K8,D2!K8,D3!K8,D4!K8,D5!K8,D6!K8) | L8: =CHOOSE(Controls!$B$6,D1!L8,D2!L8,D3!L8,D4!L8,D5!L8,D6!L8) | ... O8: =CHOOSE(Controls!$B$6,D1!O8,D2!O8,D3!O8,D4!O8,D5!O8,D6!O8)
A9: Model mix % - Haiku | B9: IN | C9: % | D9: Token share, Haiku ($0.25/$1.25 -> $1/$5). | E9: =CHOOSE(Controls!$B$6,D1!E9,D2!E9,D3!E9,D4!E9,D5!E9,D6!E9) | F9: =CHOOSE(Controls!$B$6,D1!F9,D2!F9,D3!F9,D4!F9,D5!F9,D6!F9) | G9: =CHOOSE(Controls!$B$6,D1!G9,D2!G9,D3!G9,D4!G9,D5!G9,D6!G9) | H9: =CHOOSE(Controls!$B$6,D1!H9,D2!H9,D3!H9,D4!H9,D5!H9,D6!H9) | I9: =CHOOSE(Controls!$B$6,D1!I9,D2!I9,D3!I9,D4!I9,D5!I9,D6!I9) | J9: =CHOOSE(Controls!$B$6,D1!J9,D2!J9,D3!J9,D4!J9,D5!J9,D6!J9) | K9: =CHOOSE(Controls!$B$6,D1!K9,D2!K9,D3!K9,D4!K9,D5!K9,D6!K9) | L9: =CHOOSE(Controls!$B$6,D1!L9,D2!L9,D3!L9,D4!L9,D5!L9,D6!L9) | ... O9: =CHOOSE(Controls!$B$6,D1!O9,D2!O9,D3!O9,D4!O9,D5!O9,D6!O9)
A10: List input $/Mtok - Mythos | B10: IN | C10: $ | D10: List input price, flagship. | E10: =CHOOSE(Controls!$B$6,D1!E10,D2!E10,D3!E10,D4!E10,D5!E10,D6!E10) | F10: =CHOOSE(Controls!$B$6,D1!F10,D2!F10,D3!F10,D4!F10,D5!F10,D6!F10) | G10: =CHOOSE(Controls!$B$6,D1!G10,D2!G10,D3!G10,D4!G10,D5!G10,D6!G10) | H10: =CHOOSE(Controls!$B$6,D1!H10,D2!H10,D3!H10,D4!H10,D5!H10,D6!H10) | I10: =CHOOSE(Controls!$B$6,D1!I10,D2!I10,D3!I10,D4!I10,D5!I10,D6!I10) | J10: =CHOOSE(Controls!$B$6,D1!J10,D2!J10,D3!J10,D4!J10,D5!J10,D6!J10) | K10: =CHOOSE(Controls!$B$6,D1!K10,D2!K10,D3!K10,D4!K10,D5!K10,D6!K10) | L10: =CHOOSE(Controls!$B$6,D1!L10,D2!L10,D3!L10,D4!L10,D5!L10,D6!L10) | ... O10: =CHOOSE(Controls!$B$6,D1!O10,D2!O10,D3!O10,D4!O10,D5!O10,D6!O10)
A11: List input $/Mtok - Opus | B11: IN | C11: $ | D11: List input price, Opus. | E11: =CHOOSE(Controls!$B$6,D1!E11,D2!E11,D3!E11,D4!E11,D5!E11,D6!E11) | F11: =CHOOSE(Controls!$B$6,D1!F11,D2!F11,D3!F11,D4!F11,D5!F11,D6!F11) | G11: =CHOOSE(Controls!$B$6,D1!G11,D2!G11,D3!G11,D4!G11,D5!G11,D6!G11) | H11: =CHOOSE(Controls!$B$6,D1!H11,D2!H11,D3!H11,D4!H11,D5!H11,D6!H11) | I11: =CHOOSE(Controls!$B$6,D1!I11,D2!I11,D3!I11,D4!I11,D5!I11,D6!I11) | J11: =CHOOSE(Controls!$B$6,D1!J11,D2!J11,D3!J11,D4!J11,D5!J11,D6!J11) | K11: =CHOOSE(Controls!$B$6,D1!K11,D2!K11,D3!K11,D4!K11,D5!K11,D6!K11) | L11: =CHOOSE(Controls!$B$6,D1!L11,D2!L11,D3!L11,D4!L11,D5!L11,D6!L11) | ... O11: =CHOOSE(Controls!$B$6,D1!O11,D2!O11,D3!O11,D4!O11,D5!O11,D6!O11)
A12: List input $/Mtok - Sonnet | B12: IN | C12: $ | D12: List input price, Sonnet. | E12: =CHOOSE(Controls!$B$6,D1!E12,D2!E12,D3!E12,D4!E12,D5!E12,D6!E12) | F12: =CHOOSE(Controls!$B$6,D1!F12,D2!F12,D3!F12,D4!F12,D5!F12,D6!F12) | G12: =CHOOSE(Controls!$B$6,D1!G12,D2!G12,D3!G12,D4!G12,D5!G12,D6!G12) | H12: =CHOOSE(Controls!$B$6,D1!H12,D2!H12,D3!H12,D4!H12,D5!H12,D6!H12) | I12: =CHOOSE(Controls!$B$6,D1!I12,D2!I12,D3!I12,D4!I12,D5!I12,D6!I12) | J12: =CHOOSE(Controls!$B$6,D1!J12,D2!J12,D3!J12,D4!J12,D5!J12,D6!J12) | K12: =CHOOSE(Controls!$B$6,D1!K12,D2!K12,D3!K12,D4!K12,D5!K12,D6!K12) | L12: =CHOOSE(Controls!$B$6,D1!L12,D2!L12,D3!L12,D4!L12,D5!L12,D6!L12) | ... O12: =CHOOSE(Controls!$B$6,D1!O12,D2!O12,D3!O12,D4!O12,D5!O12,D6!O12)
A13: List input $/Mtok - Haiku | B13: IN | C13: $ | D13: List input price, Haiku. | E13: =CHOOSE(Controls!$B$6,D1!E13,D2!E13,D3!E13,D4!E13,D5!E13,D6!E13) | F13: =CHOOSE(Controls!$B$6,D1!F13,D2!F13,D3!F13,D4!F13,D5!F13,D6!F13) | G13: =CHOOSE(Controls!$B$6,D1!G13,D2!G13,D3!G13,D4!G13,D5!G13,D6!G13) | H13: =CHOOSE(Controls!$B$6,D1!H13,D2!H13,D3!H13,D4!H13,D5!H13,D6!H13) | I13: =CHOOSE(Controls!$B$6,D1!I13,D2!I13,D3!I13,D4!I13,D5!I13,D6!I13) | J13: =CHOOSE(Controls!$B$6,D1!J13,D2!J13,D3!J13,D4!J13,D5!J13,D6!J13) | K13: =CHOOSE(Controls!$B$6,D1!K13,D2!K13,D3!K13,D4!K13,D5!K13,D6!K13) | L13: =CHOOSE(Controls!$B$6,D1!L13,D2!L13,D3!L13,D4!L13,D5!L13,D6!L13) | ... O13: =CHOOSE(Controls!$B$6,D1!O13,D2!O13,D3!O13,D4!O13,D5!O13,D6!O13)
A14: List output $/Mtok - Mythos | B14: IN | C14: $ | D14: List output price, flagship. | E14: =CHOOSE(Controls!$B$6,D1!E14,D2!E14,D3!E14,D4!E14,D5!E14,D6!E14) | F14: =CHOOSE(Controls!$B$6,D1!F14,D2!F14,D3!F14,D4!F14,D5!F14,D6!F14) | G14: =CHOOSE(Controls!$B$6,D1!G14,D2!G14,D3!G14,D4!G14,D5!G14,D6!G14) | H14: =CHOOSE(Controls!$B$6,D1!H14,D2!H14,D3!H14,D4!H14,D5!H14,D6!H14) | I14: =CHOOSE(Controls!$B$6,D1!I14,D2!I14,D3!I14,D4!I14,D5!I14,D6!I14) | J14: =CHOOSE(Controls!$B$6,D1!J14,D2!J14,D3!J14,D4!J14,D5!J14,D6!J14) | K14: =CHOOSE(Controls!$B$6,D1!K14,D2!K14,D3!K14,D4!K14,D5!K14,D6!K14) | L14: =CHOOSE(Controls!$B$6,D1!L14,D2!L14,D3!L14,D4!L14,D5!L14,D6!L14) | ... O14: =CHOOSE(Controls!$B$6,D1!O14,D2!O14,D3!O14,D4!O14,D5!O14,D6!O14)
A15: List output $/Mtok - Opus | B15: IN | C15: $ | D15: List output price, Opus. | E15: =CHOOSE(Controls!$B$6,D1!E15,D2!E15,D3!E15,D4!E15,D5!E15,D6!E15) | F15: =CHOOSE(Controls!$B$6,D1!F15,D2!F15,D3!F15,D4!F15,D5!F15,D6!F15) | G15: =CHOOSE(Controls!$B$6,D1!G15,D2!G15,D3!G15,D4!G15,D5!G15,D6!G15) | H15: =CHOOSE(Controls!$B$6,D1!H15,D2!H15,D3!H15,D4!H15,D5!H15,D6!H15) | I15: =CHOOSE(Controls!$B$6,D1!I15,D2!I15,D3!I15,D4!I15,D5!I15,D6!I15) | J15: =CHOOSE(Controls!$B$6,D1!J15,D2!J15,D3!J15,D4!J15,D5!J15,D6!J15) | K15: =CHOOSE(Controls!$B$6,D1!K15,D2!K15,D3!K15,D4!K15,D5!K15,D6!K15) | L15: =CHOOSE(Controls!$B$6,D1!L15,D2!L15,D3!L15,D4!L15,D5!L15,D6!L15) | ... O15: =CHOOSE(Controls!$B$6,D1!O15,D2!O15,D3!O15,D4!O15,D5!O15,D6!O15)
A16: List output $/Mtok - Sonnet | B16: IN | C16: $ | D16: List output price, Sonnet. | E16: =CHOOSE(Controls!$B$6,D1!E16,D2!E16,D3!E16,D4!E16,D5!E16,D6!E16) | F16: =CHOOSE(Controls!$B$6,D1!F16,D2!F16,D3!F16,D4!F16,D5!F16,D6!F16) | G16: =CHOOSE(Controls!$B$6,D1!G16,D2!G16,D3!G16,D4!G16,D5!G16,D6!G16) | H16: =CHOOSE(Controls!$B$6,D1!H16,D2!H16,D3!H16,D4!H16,D5!H16,D6!H16) | I16: =CHOOSE(Controls!$B$6,D1!I16,D2!I16,D3!I16,D4!I16,D5!I16,D6!I16) | J16: =CHOOSE(Controls!$B$6,D1!J16,D2!J16,D3!J16,D4!J16,D5!J16,D6!J16) | K16: =CHOOSE(Controls!$B$6,D1!K16,D2!K16,D3!K16,D4!K16,D5!K16,D6!K16) | L16: =CHOOSE(Controls!$B$6,D1!L16,D2!L16,D3!L16,D4!L16,D5!L16,D6!L16) | ... O16: =CHOOSE(Controls!$B$6,D1!O16,D2!O16,D3!O16,D4!O16,D5!O16,D6!O16)
A17: List output $/Mtok - Haiku | B17: IN | C17: $ | D17: List output price, Haiku. | E17: =CHOOSE(Controls!$B$6,D1!E17,D2!E17,D3!E17,D4!E17,D5!E17,D6!E17) | F17: =CHOOSE(Controls!$B$6,D1!F17,D2!F17,D3!F17,D4!F17,D5!F17,D6!F17) | G17: =CHOOSE(Controls!$B$6,D1!G17,D2!G17,D3!G17,D4!G17,D5!G17,D6!G17) | H17: =CHOOSE(Controls!$B$6,D1!H17,D2!H17,D3!H17,D4!H17,D5!H17,D6!H17) | I17: =CHOOSE(Controls!$B$6,D1!I17,D2!I17,D3!I17,D4!I17,D5!I17,D6!I17) | J17: =CHOOSE(Controls!$B$6,D1!J17,D2!J17,D3!J17,D4!J17,D5!J17,D6!J17) | K17: =CHOOSE(Controls!$B$6,D1!K17,D2!K17,D3!K17,D4!K17,D5!K17,D6!K17) | L17: =CHOOSE(Controls!$B$6,D1!L17,D2!L17,D3!L17,D4!L17,D5!L17,D6!L17) | ... O17: =CHOOSE(Controls!$B$6,D1!O17,D2!O17,D3!O17,D4!O17,D5!O17,D6!O17)
... A27: Blended effective $/Mtok | B27: CALC | C27: $ | D27: Mix-weighted, adjusted for input share, caching, batch. | E27: =CHOOSE(Controls!$B$6,D1!E27,D2!E27,D3!E27,D4!E27,D5!E27,D6!E27) | F27: =CHOOSE(Controls!$B$6,D1!F27,D2!F27,D3!F27,D4!F27,D5!F27,D6!F27) | G27: =CHOOSE(Controls!$B$6,D1!G27,D2!G27,D3!G27,D4!G27,D5!G27,D6!G27) | H27: =CHOOSE(Controls!$B$6,D1!H27,D2!H27,D3!H27,D4!H27,D5!H27,D6!H27) | I27: =CHOOSE(Controls!$B$6,D1!I27,D2!I27,D3!I27,D4!I27,D5!I27,D6!I27) | J27: =CHOOSE(Controls!$B$6,D1!J27,D2!J27,D3!J27,D4!J27,D5!J27,D6!J27) | K27: =CHOOSE(Controls!$B$6,D1!K27,D2!K27,D3!K27,D4!K27,D5!K27,D6!K27) | L27: =CHOOSE(Controls!$B$6,D1!L27,D2!L27,D3!L27,D4!L27,D5!L27,D6!L27) | ... O27: =CHOOSE(Controls!$B$6,D1!O27,D2!O27,D3!O27,D4!O27,D5!O27,D6!O27)
A28: NON-API REVENUE STREAMS
A29: # Enterprise contracts (>$1M ARR) | B29: IN | C29: count | D29: ~1,000+ at $1M+ ACV by 2026. | E29: =CHOOSE(Controls!$B$6,D1!E29,D2!E29,D3!E29,D4!E29,D5!E29,D6!E29) | F29: =CHOOSE(Controls!$B$6,D1!F29,D2!F29,D3!F29,D4!F29,D5!F29,D6!F29) | G29: =CHOOSE(Controls!$B$6,D1!G29,D2!G29,D3!G29,D4!G29,D5!G29,D6!G29) | H29: =CHOOSE(Controls!$B$6,D1!H29,D2!H29,D3!H29,D4!H29,D5!H29,D6!H29) | I29: =CHOOSE(Controls!$B$6,D1!I29,D2!I29,D3!I29,D4!I29,D5!I29,D6!I29) | J29: =CHOOSE(Controls!$B$6,D1!J29,D2!J29,D3!J29,D4!J29,D5!J29,D6!J29) | K29: =CHOOSE(Controls!$B$6,D1!K29,D2!K29,D3!K29,D4!K29,D5!K29,D6!K29) | L29: =CHOOSE(Controls!$B$6,D1!L29,D2!L29,D3!L29,D4!L29,D5!L29,D6!L29) | ... O29: =CHOOSE(Controls!$B$6,D1!O29,D2!O29,D3!O29,D4!O29,D5!O29,D6!O29)
A30: Committed-use discount % (memo) | B30: IN | C30: % | D30: Volume discount realized on enterprise API. | E30: =CHOOSE(Controls!$B$6,D1!E30,D2!E30,D3!E30,D4!E30,D5!E30,D6!E30) | F30: =CHOOSE(Controls!$B$6,D1!F30,D2!F30,D3!F30,D4!F30,D5!F30,D6!F30) | G30: =CHOOSE(Controls!$B$6,D1!G30,D2!G30,D3!G30,D4!G30,D5!G30,D6!G30) | H30: =CHOOSE(Controls!$B$6,D1!H30,D2!H30,D3!H30,D4!H30,D5!H30,D6!H30) | I30: =CHOOSE(Controls!$B$6,D1!I30,D2!I30,D3!I30,D4!I30,D5!I30,D6!I30) | J30: =CHOOSE(Controls!$B$6,D1!J30,D2!J30,D3!J30,D4!J30,D5!J30,D6!J30) | K30: =CHOOSE(Controls!$B$6,D1!K30,D2!K30,D3!K30,D4!K30,D5!K30,D6!K30) | L30: =CHOOSE(Controls!$B$6,D1!L30,D2!L30,D3!L30,D4!L30,D5!L30,D6!L30) | ... O30: =CHOOSE(Controls!$B$6,D1!O30,D2!O30,D3!O30,D4!O30,D5!O30,D6!O30)
A31: Active enterprise dashboard seats | B31: IN | C31: count | D31: Console/admin seats. | E31: =CHOOSE(Controls!$B$6,D1!E31,D2!E31,D3!E31,D4!E31,D5!E31,D6!E31) | F31: =CHOOSE(Controls!$B$6,D1!F31,D2!F31,D3!F31,D4!F31,D5!F31,D6!F31) | G31: =CHOOSE(Controls!$B$6,D1!G31,D2!G31,D3!G31,D4!G31,D5!G31,D6!G31) | H31: =CHOOSE(Controls!$B$6,D1!H31,D2!H31,D3!H31,D4!H31,D5!H31,D6!H31) | I31: =CHOOSE(Controls!$B$6,D1!I31,D2!I31,D3!I31,D4!I31,D5!I31,D6!I31) | J31: =CHOOSE(Controls!$B$6,D1!J31,D2!J31,D3!J31,D4!J31,D5!J31,D6!J31) | K31: =CHOOSE(Controls!$B$6,D1!K31,D2!K31,D3!K31,D4!K31,D5!K31,D6!K31) | L31: =CHOOSE(Controls!$B$6,D1!L31,D2!L31,D3!L31,D4!L31,D5!L31,D6!L31) | ... O31: =CHOOSE(Controls!$B$6,D1!O31,D2!O31,D3!O31,D4!O31,D5!O31,D6!O31)
A32: Enterprise platform fee / seat / mo | B32: IN | C32: $ | D32: Monthly platform fee per seat. | E32: =CHOOSE(Controls!$B$6,D1!E32,D2!E32,D3!E32,D4!E32,D5!E32,D6!E32) | F32: =CHOOSE(Controls!$B$6,D1!F32,D2!F32,D3!F32,D4!F32,D5!F32,D6!F32) | G32: =CHOOSE(Controls!$B$6,D1!G32,D2!G32,D3!G32,D4!G32,D5!G32,D6!G32) | H32: =CHOOSE(Controls!$B$6,D1!H32,D2!H32,D3!H32,D4!H32,D5!H32,D6!H32) | I32: =CHOOSE(Controls!$B$6,D1!I32,D2!I32,D3!I32,D4!I32,D5!I32,D6!I32) | J32: =CHOOSE(Controls!$B$6,D1!J32,D2!J32,D3!J32,D4!J32,D5!J32,D6!J32) | K32: =CHOOSE(Controls!$B$6,D1!K32,D2!K32,D3!K32,D4!K32,D5!K32,D6!K32) | L32: =CHOOSE(Controls!$B$6,D1!L32,D2!L32,D3!L32,D4!L32,D5!L32,D6!L32) | ... O32: =CHOOSE(Controls!$B$6,D1!O32,D2!O32,D3!O32,D4!O32,D5!O32,D6!O32)
A33: Enterprise seat revenue | B33: CALC | C33: $M | D33: seats x fee x 12. | E33: =CHOOSE(Controls!$B$6,D1!E33,D2!E33,D3!E33,D4!E33,D5!E33,D6!E33) | F33: =CHOOSE(Controls!$B$6,D1!F33,D2!F33,D3!F33,D4!F33,D5!F33,D6!F33) | G33: =CHOOSE(Controls!$B$6,D1!G33,D2!G33,D3!G33,D4!G33,D5!G33,D6!G33) | H33: =CHOOSE(Controls!$B$6,D1!H33,D2!H33,D3!H33,D4!H33,D5!H33,D6!H33) | I33: =CHOOSE(Controls!$B$6,D1!I33,D2!I33,D3!I33,D4!I33,D5!I33,D6!I33) | J33: =CHOOSE(Controls!$B$6,D1!J33,D2!J33,D3!J33,D4!J33,D5!J33,D6!J33) | K33: =CHOOSE(Controls!$B$6,D1!K33,D2!K33,D3!K33,D4!K33,D5!K33,D6!K33) | L33: =CHOOSE(Controls!$B$6,D1!L33,D2!L33,D3!L33,D4!L33,D5!L33,D6!L33) | ... O33: =CHOOSE(Controls!$B$6,D1!O33,D2!O33,D3!O33,D4!O33,D5!O33,D6!O33)
A34: Consumer subscription revenue (anchor) | B34: IN | C34: $M | D34: Claude Pro ($20) + Max ($100/$200). | E34: =CHOOSE(Controls!$B$6,D1!E34,D2!E34,D3!E34,D4!E34,D5!E34,D6!E34) | F34: =CHOOSE(Controls!$B$6,D1!F34,D2!F34,D3!F34,D4!F34,D5!F34,D6!F34) | G34: =CHOOSE(Controls!$B$6,D1!G34,D2!G34,D3!G34,D4!G34,D5!G34,D6!G34) | H34: =CHOOSE(Controls!$B$6,D1!H34,D2!H34,D3!H34,D4!H34,D5!H34,D6!H34) | I34: =CHOOSE(Controls!$B$6,D1!I34,D2!I34,D3!I34,D4!I34,D5!I34,D6!I34) | J34: =CHOOSE(Controls!$B$6,D1!J34,D2!J34,D3!J34,D4!J34,D5!J34,D6!J34) | K34: =CHOOSE(Controls!$B$6,D1!K34,D2!K34,D3!K34,D4!K34,D5!K34,D6!K34) | L34: =CHOOSE(Controls!$B$6,D1!L34,D2!L34,D3!L34,D4!L34,D5!L34,D6!L34) | ... O34: =CHOOSE(Controls!$B$6,D1!O34,D2!O34,D3!O34,D4!O34,D5!O34,D6!O34)
A35: Blended consumer ARPU ($/mo) | B35: IN | C35: $ | D35: Blend of Pro and Max. | E35: =CHOOSE(Controls!$B$6,D1!E35,D2!E35,D3!E35,D4!E35,D5!E35,D6!E35) | F35: =CHOOSE(Controls!$B$6,D1!F35,D2!F35,D3!F35,D4!F35,D5!F35,D6!F35) | G35: =CHOOSE(Controls!$B$6,D1!G35,D2!G35,D3!G35,D4!G35,D5!G35,D6!G35) | H35: =CHOOSE(Controls!$B$6,D1!H35,D2!H35,D3!H35,D4!H35,D5!H35,D6!H35) | I35: =CHOOSE(Controls!$B$6,D1!I35,D2!I35,D3!I35,D4!I35,D5!I35,D6!I35) | J35: =CHOOSE(Controls!$B$6,D1!J35,D2!J35,D3!J35,D4!J35,D5!J35,D6!J35) | K35: =CHOOSE(Controls!$B$6,D1!K35,D2!K35,D3!K35,D4!K35,D5!K35,D6!K35) | L35: =CHOOSE(Controls!$B$6,D1!L35,D2!L35,D3!L35,D4!L35,D5!L35,D6!L35) | ... O35: =CHOOSE(Controls!$B$6,D1!O35,D2!O35,D3!O35,D4!O35,D5!O35,D6!O35)
A36: Paying consumer subs (implied) | B36: PLUG | C36: Count | D36: consumer rev / (ARPU x 12). | E36: =CHOOSE(Controls!$B$6,D1!E36,D2!E36,D3!E36,D4!E36,D5!E36,D6!E36) | F36: =CHOOSE(Controls!$B$6,D1!F36,D2!F36,D3!F36,D4!F36,D5!F36,D6!F36) | G36: =CHOOSE(Controls!$B$6,D1!G36,D2!G36,D3!G36,D4!G36,D5!G36,D6!G36) | H36: =CHOOSE(Controls!$B$6,D1!H36,D2!H36,D3!H36,D4!H36,D5!H36,D6!H36) | I36: =CHOOSE(Controls!$B$6,D1!I36,D2!I36,D3!I36,D4!I36,D5!I36,D6!I36) | J36: =CHOOSE(Controls!$B$6,D1!J36,D2!J36,D3!J36,D4!J36,D5!J36,D6!J36) | K36: =CHOOSE(Controls!$B$6,D1!K36,D2!K36,D3!K36,D4!K36,D5!K36,D6!K36) | L36: =CHOOSE(Controls!$B$6,D1!L36,D2!L36,D3!L36,D4!L36,D5!L36,D6!L36) | ... O36: =CHOOSE(Controls!$B$6,D1!O36,D2!O36,D3!O36,D4!O36,D5!O36,D6!O36)
A37: Active developer seats | B37: IN | C37: Count | D37: Claude Code seats (Feb-2025). | E37: =CHOOSE(Controls!$B$6,D1!E37,D2!E37,D3!E37,D4!E37,D5!E37,D6!E37) | F37: =CHOOSE(Controls!$B$6,D1!F37,D2!F37,D3!F37,D4!F37,D5!F37,D6!F37) | G37: =CHOOSE(Controls!$B$6,D1!G37,D2!G37,D3!G37,D4!G37,D5!G37,D6!G37) | H37: =CHOOSE(Controls!$B$6,D1!H37,D2!H37,D3!H37,D4!H37,D5!H37,D6!H37) | I37: =CHOOSE(Controls!$B$6,D1!I37,D2!I37,D3!I37,D4!I37,D5!I37,D6!I37) | J37: =CHOOSE(Controls!$B$6,D1!J37,D2!J37,D3!J37,D4!J37,D5!J37,D6!J37) | K37: =CHOOSE(Controls!$B$6,D1!K37,D2!K37,D3!K37,D4!K37,D5!K37,D6!K37) | L37: =CHOOSE(Controls!$B$6,D1!L37,D2!L37,D3!L37,D4!L37,D5!L37,D6!L37) | ... O37: =CHOOSE(Controls!$B$6,D1!O37,D2!O37,D3!O37,D4!O37,D5!O37,D6!O37)
A38: Base seat fee ($/mo) | B38: IN | C38: $ | D38: Claude Code base seat fee. | E38: =CHOOSE(Controls!$B$6,D1!E38,D2!E38,D3!E38,D4!E38,D5!E38,D6!E38) | F38: =CHOOSE(Controls!$B$6,D1!F38,D2!F38,D3!F38,D4!F38,D5!F38,D6!F38) | G38: =CHOOSE(Controls!$B$6,D1!G38,D2!G38,D3!G38,D4!G38,D5!G38,D6!G38) | H38: =CHOOSE(Controls!$B$6,D1!H38,D2!H38,D3!H38,D4!H38,D5!H38,D6!H38) | I38: =CHOOSE(Controls!$B$6,D1!I38,D2!I38,D3!I38,D4!I38,D5!I38,D6!I38) | J38: =CHOOSE(Controls!$B$6,D1!J38,D2!J38,D3!J38,D4!J38,D5!J38,D6!J38) | K38: =CHOOSE(Controls!$B$6,D1!K38,D2!K38,D3!K38,D4!K38,D5!K38,D6!K38) | L38: =CHOOSE(Controls!$B$6,D1!L38,D2!L38,D3!L38,D4!L38,D5!L38,D6!L38) | ... O38: =CHOOSE(Controls!$B$6,D1!O38,D2!O38,D3!O38,D4!O38,D5!O38,D6!O38)
A39: Claude Code base seat revenue | B39: CALC | C39: $M | D39: seats x fee x 12. | E39: =CHOOSE(Controls!$B$6,D1!E39,D2!E39,D3!E39,D4!E39,D5!E39,D6!E39) | F39: =CHOOSE(Controls!$B$6,D1!F39,D2!F39,D3!F39,D4!F39,D5!F39,D6!F39) | G39: =CHOOSE(Controls!$B$6,D1!G39,D2!G39,D3!G39,D4!G39,D5!G39,D6!G39) | H39: =CHOOSE(Controls!$B$6,D1!H39,D2!H39,D3!H39,D4!H39,D5!H39,D6!H39) | I39: =CHOOSE(Controls!$B$6,D1!I39,D2!I39,D3!I39,D4!I39,D5!I39,D6!I39) | J39: =CHOOSE(Controls!$B$6,D1!J39,D2!J39,D3!J39,D4!J39,D5!J39,D6!J39) | K39: =CHOOSE(Controls!$B$6,D1!K39,D2!K39,D3!K39,D4!K39,D5!K39,D6!K39) | L39: =CHOOSE(Controls!$B$6,D1!L39,D2!L39,D3!L39,D4!L39,D5!L39,D6!L39) | ... O39: =CHOOSE(Controls!$B$6,D1!O39,D2!O39,D3!O39,D4!O39,D5!O39,D6!O39)
A40: Avg overage tokens / dev / mo | B40: IN | C40: Mtok | D40: Usage above base seat. | E40: =CHOOSE(Controls!$B$6,D1!E40,D2!E40,D3!E40,D4!E40,D5!E40,D6!E40) | F40: =CHOOSE(Controls!$B$6,D1!F40,D2!F40,D3!F40,D4!F40,D5!F40,D6!F40) | G40: =CHOOSE(Controls!$B$6,D1!G40,D2!G40,D3!G40,D4!G40,D5!G40,D6!G40) | H40: =CHOOSE(Controls!$B$6,D1!H40,D2!H40,D3!H40,D4!H40,D5!H40,D6!H40) | I40: =CHOOSE(Controls!$B$6,D1!I40,D2!I40,D3!I40,D4!I40,D5!I40,D6!I40) | J40: =CHOOSE(Controls!$B$6,D1!J40,D2!J40,D3!J40,D4!J40,D5!J40,D6!J40) | K40: =CHOOSE(Controls!$B$6,D1!K40,D2!K40,D3!K40,D4!K40,D5!K40,D6!K40) | L40: =CHOOSE(Controls!$B$6,D1!L40,D2!L40,D3!L40,D4!L40,D5!L40,D6!L40) | ... O40: =CHOOSE(Controls!$B$6,D1!O40,D2!O40,D3!O40,D4!O40,D5!O40,D6!O40)
... A60: Total non-API revenue | B60: CALC | C60: $M | D60: Sum of non-API streams. | E60: =CHOOSE(Controls!$B$6,D1!E60,D2!E60,D3!E60,D4!E60,D5!E60,D6!E60) | F60: =CHOOSE(Controls!$B$6,D1!F60,D2!F60,D3!F60,D4!F60,D5!F60,D6!F60) | G60: =CHOOSE(Controls!$B$6,D1!G60,D2!G60,D3!G60,D4!G60,D5!G60,D6!G60) | H60: =CHOOSE(Controls!$B$6,D1!H60,D2!H60,D3!H60,D4!H60,D5!H60,D6!H60) | I60: =CHOOSE(Controls!$B$6,D1!I60,D2!I60,D3!I60,D4!I60,D5!I60,D6!I60) | J60: =CHOOSE(Controls!$B$6,D1!J60,D2!J60,D3!J60,D4!J60,D5!J60,D6!J60) | K60: =CHOOSE(Controls!$B$6,D1!K60,D2!K60,D3!K60,D4!K60,D5!K60,D6!K60) | L60: =CHOOSE(Controls!$B$6,D1!L60,D2!L60,D3!L60,D4!L60,D5!L60,D6!L60) | ... O60: =CHOOSE(Controls!$B$6,D1!O60,D2!O60,D3!O60,D4!O60,D5!O60,D6!O60)
A61: FIRST PARTY DIRECT API REVENUE
A62: First-party API revenue | B62: PLUG | C62: $M | D62: Booked revenue minus non-API streams. | E62: =CHOOSE(Controls!$B$6,D1!E62,D2!E62,D3!E62,D4!E62,D5!E62,D6!E62) | F62: =CHOOSE(Controls!$B$6,D1!F62,D2!F62,D3!F62,D4!F62,D5!F62,D6!F62) | G62: =CHOOSE(Controls!$B$6,D1!G62,D2!G62,D3!G62,D4!G62,D5!G62,D6!G62) | H62: =CHOOSE(Controls!$B$6,D1!H62,D2!H62,D3!H62,D4!H62,D5!H62,D6!H62) | I62: =CHOOSE(Controls!$B$6,D1!I62,D2!I62,D3!I62,D4!I62,D5!I62,D6!I62) | J62: =CHOOSE(Controls!$B$6,D1!J62,D2!J62,D3!J62,D4!J62,D5!J62,D6!J62) | K62: =CHOOSE(Controls!$B$6,D1!K62,D2!K62,D3!K62,D4!K62,D5!K62,D6!K62) | L62: =CHOOSE(Controls!$B$6,D1!L62,D2!L62,D3!L62,D4!L62,D5!L62,D6!L62) | ... O62: =CHOOSE(Controls!$B$6,D1!O62,D2!O62,D3!O62,D4!O62,D5!O62,D6!O62)
A63: API TOKEN ENGINE
A64: Total tokens processed (all) | B64: PLUG | C64: T | D64: API revenue / blended $/Mtok (trillions). | E64: =CHOOSE(Controls!$B$6,D1!E64,D2!E64,D3!E64,D4!E64,D5!E64,D6!E64) | F64: =CHOOSE(Controls!$B$6,D1!F64,D2!F64,D3!F64,D4!F64,D5!F64,D6!F64) | G64: =CHOOSE(Controls!$B$6,D1!G64,D2!G64,D3!G64,D4!G64,D5!G64,D6!G64) | H64: =CHOOSE(Controls!$B$6,D1!H64,D2!H64,D3!H64,D4!H64,D5!H64,D6!H64) | I64: =CHOOSE(Controls!$B$6,D1!I64,D2!I64,D3!I64,D4!I64,D5!I64,D6!I64) | J64: =CHOOSE(Controls!$B$6,D1!J64,D2!J64,D3!J64,D4!J64,D5!J64,D6!J64) | K64: =CHOOSE(Controls!$B$6,D1!K64,D2!K64,D3!K64,D4!K64,D5!K64,D6!K64) | L64: =CHOOSE(Controls!$B$6,D1!L64,D2!L64,D3!L64,D4!L64,D5!L64,D6!L64) | ... O64: =CHOOSE(Controls!$B$6,D1!O64,D2!O64,D3!O64,D4!O64,D5!O64,D6!O64)
A65: Total input tokens | B65: CALC | C65: T | D65: tokens x input share. | E65: =CHOOSE(Controls!$B$6,D1!E65,D2!E65,D3!E65,D4!E65,D5!E65,D6!E65) | F65: =CHOOSE(Controls!$B$6,D1!F65,D2!F65,D3!F65,D4!F65,D5!F65,D6!F65) | G65: =CHOOSE(Controls!$B$6,D1!G65,D2!G65,D3!G65,D4!G65,D5!G65,D6!G65) | H65: =CHOOSE(Controls!$B$6,D1!H65,D2!H65,D3!H65,D4!H65,D5!H65,D6!H65) | I65: =CHOOSE(Controls!$B$6,D1!I65,D2!I65,D3!I65,D4!I65,D5!I65,D6!I65) | J65: =CHOOSE(Controls!$B$6,D1!J65,D2!J65,D3!J65,D4!J65,D5!J65,D6!J65) | K65: =CHOOSE(Controls!$B$6,D1!K65,D2!K65,D3!K65,D4!K65,D5!K65,D6!K65) | L65: =CHOOSE(Controls!$B$6,D1!L65,D2!L65,D3!L65,D4!L65,D5!L65,D6!L65) | ... O65: =CHOOSE(Controls!$B$6,D1!O65,D2!O65,D3!O65,D4!O65,D5!O65,D6!O65)
A66: Total output tokens | B66: CALC | C66: T | D66: tokens x (1 - input share). | E66: =CHOOSE(Controls!$B$6,D1!E66,D2!E66,D3!E66,D4!E66,D5!E66,D6!E66) | F66: =CHOOSE(Controls!$B$6,D1!F66,D2!F66,D3!F66,D4!F66,D5!F66,D6!F66) | G66: =CHOOSE(Controls!$B$6,D1!G66,D2!G66,D3!G66,D4!G66,D5!G66,D6!G66) | H66: =CHOOSE(Controls!$B$6,D1!H66,D2!H66,D3!H66,D4!H66,D5!H66,D6!H66) | I66: =CHOOSE(Controls!$B$6,D1!I66,D2!I66,D3!I66,D4!I66,D5!I66,D6!I66) | J66: =CHOOSE(Controls!$B$6,D1!J66,D2!J66,D3!J66,D4!J66,D5!J66,D6!J66) | K66: =CHOOSE(Controls!$B$6,D1!K66,D2!K66,D3!K66,D4!K66,D5!K66,D6!K66) | L66: =CHOOSE(Controls!$B$6,D1!L66,D2!L66,D3!L66,D4!L66,D5!L66,D6!L66) | ... O66: =CHOOSE(Controls!$B$6,D1!O66,D2!O66,D3!O66,D4!O66,D5!O66,D6!O66)
A67: Total first-party API calls | B67: CALC | C67: B | D67: tokens / tokens-per-call (billions). | E67: =CHOOSE(Controls!$B$6,D1!E67,D2!E67,D3!E67,D4!E67,D5!E67,D6!E67) | F67: =CHOOSE(Controls!$B$6,D1!F67,D2!F67,D3!F67,D4!F67,D5!F67,D6!F67) | G67: =CHOOSE(Controls!$B$6,D1!G67,D2!G67,D3!G67,D4!G67,D5!G67,D6!G67) | H67: =CHOOSE(Controls!$B$6,D1!H67,D2!H67,D3!H67,D4!H67,D5!H67,D6!H67) | I67: =CHOOSE(Controls!$B$6,D1!I67,D2!I67,D3!I67,D4!I67,D5!I67,D6!I67) | J67: =CHOOSE(Controls!$B$6,D1!J67,D2!J67,D3!J67,D4!J67,D5!J67,D6!J67) | K67: =CHOOSE(Controls!$B$6,D1!K67,D2!K67,D3!K67,D4!K67,D5!K67,D6!K67) | L67: =CHOOSE(Controls!$B$6,D1!L67,D2!L67,D3!L67,D4!L67,D5!L67,D6!L67) | ... O67: =CHOOSE(Controls!$B$6,D1!O67,D2!O67,D3!O67,D4!O67,D5!O67,D6!O67)
A68: Memo: calls / contract / day | B68: CALC | C68: # | D68: calls / contracts / 365. | E68: =CHOOSE(Controls!$B$6,D1!E68,D2!E68,D3!E68,D4!E68,D5!E68,D6!E68) | F68: =CHOOSE(Controls!$B$6,D1!F68,D2!F68,D3!F68,D4!F68,D5!F68,D6!F68) | G68: =CHOOSE(Controls!$B$6,D1!G68,D2!G68,D3!G68,D4!G68,D5!G68,D6!G68) | H68: =CHOOSE(Controls!$B$6,D1!H68,D2!H68,D3!H68,D4!H68,D5!H68,D6!H68) | I68: =CHOOSE(Controls!$B$6,D1!I68,D2!I68,D3!I68,D4!I68,D5!I68,D6!I68) | J68: =CHOOSE(Controls!$B$6,D1!J68,D2!J68,D3!J68,D4!J68,D5!J68,D6!J68) | K68: =CHOOSE(Controls!$B$6,D1!K68,D2!K68,D3!K68,D4!K68,D5!K68,D6!K68) | L68: =CHOOSE(Controls!$B$6,D1!L68,D2!L68,D3!L68,D4!L68,D5!L68,D6!L68) | ... O68: =CHOOSE(Controls!$B$6,D1!O68,D2!O68,D3!O68,D4!O68,D5!O68,D6!O68)
A69: COSTS - Inference and infrastructure
A70: Billed tokens (Anthropic-served) | B70: LINK | C70: T | D70: API + consumer + Claude Code (excl Bedrock/Vertex). | E70: =CHOOSE(Controls!$B$6,D1!E70,D2!E70,D3!E70,D4!E70,D5!E70,D6!E70) | F70: =CHOOSE(Controls!$B$6,D1!F70,D2!F70,D3!F70,D4!F70,D5!F70,D6!F70) | G70: =CHOOSE(Controls!$B$6,D1!G70,D2!G70,D3!G70,D4!G70,D5!G70,D6!G70) | H70: =CHOOSE(Controls!$B$6,D1!H70,D2!H70,D3!H70,D4!H70,D5!H70,D6!H70) | I70: =CHOOSE(Controls!$B$6,D1!I70,D2!I70,D3!I70,D4!I70,D5!I70,D6!I70) | J70: =CHOOSE(Controls!$B$6,D1!J70,D2!J70,D3!J70,D4!J70,D5!J70,D6!J70) | K70: =CHOOSE(Controls!$B$6,D1!K70,D2!K70,D3!K70,D4!K70,D5!K70,D6!K70) | L70: =CHOOSE(Controls!$B$6,D1!L70,D2!L70,D3!L70,D4!L70,D5!L70,D6!L70) | ... O70: =CHOOSE(Controls!$B$6,D1!O70,D2!O70,D3!O70,D4!O70,D5!O70,D6!O70)
A71: Free-tier tokens served | B71: IN | C71: T | D71: Non-billed free-tier usage. | E71: =CHOOSE(Controls!$B$6,D1!E71,D2!E71,D3!E71,D4!E71,D5!E71,D6!E71) | F71: =CHOOSE(Controls!$B$6,D1!F71,D2!F71,D3!F71,D4!F71,D5!F71,D6!F71) | G71: =CHOOSE(Controls!$B$6,D1!G71,D2!G71,D3!G71,D4!G71,D5!G71,D6!G71) | H71: =CHOOSE(Controls!$B$6,D1!H71,D2!H71,D3!H71,D4!H71,D5!H71,D6!H71) | I71: =CHOOSE(Controls!$B$6,D1!I71,D2!I71,D3!I71,D4!I71,D5!I71,D6!I71) | J71: =CHOOSE(Controls!$B$6,D1!J71,D2!J71,D3!J71,D4!J71,D5!J71,D6!J71) | K71: =CHOOSE(Controls!$B$6,D1!K71,D2!K71,D3!K71,D4!K71,D5!K71,D6!K71) | L71: =CHOOSE(Controls!$B$6,D1!L71,D2!L71,D3!L71,D4!L71,D5!L71,D6!L71) | ... O71: =CHOOSE(Controls!$B$6,D1!O71,D2!O71,D3!O71,D4!O71,D5!O71,D6!O71)
A72: Internal / testing tokens | B72: IN | C72: T | D72: Evals/red-team/internal. | E72: =CHOOSE(Controls!$B$6,D1!E72,D2!E72,D3!E72,D4!E72,D5!E72,D6!E72) | F72: =CHOOSE(Controls!$B$6,D1!F72,D2!F72,D3!F72,D4!F72,D5!F72,D6!F72) | G72: =CHOOSE(Controls!$B$6,D1!G72,D2!G72,D3!G72,D4!G72,D5!G72,D6!G72) | H72: =CHOOSE(Controls!$B$6,D1!H72,D2!H72,D3!H72,D4!H72,D5!H72,D6!H72) | I72: =CHOOSE(Controls!$B$6,D1!I72,D2!I72,D3!I72,D4!I72,D5!I72,D6!I72) | J72: =CHOOSE(Controls!$B$6,D1!J72,D2!J72,D3!J72,D4!J72,D5!J72,D6!J72) | K72: =CHOOSE(Controls!$B$6,D1!K72,D2!K72,D3!K72,D4!K72,D5!K72,D6!K72) | L72: =CHOOSE(Controls!$B$6,D1!L72,D2!L72,D3!L72,D4!L72,D5!L72,D6!L72) | ... O72: =CHOOSE(Controls!$B$6,D1!O72,D2!O72,D3!O72,D4!O72,D5!O72,D6!O72)
A73: Gross tokens served | B73: CALC | C73: T | D73: billed + free + internal. | E73: =CHOOSE(Controls!$B$6,D1!E73,D2!E73,D3!E73,D4!E73,D5!E73,D6!E73) | F73: =CHOOSE(Controls!$B$6,D1!F73,D2!F73,D3!F73,D4!F73,D5!F73,D6!F73) | G73: =CHOOSE(Controls!$B$6,D1!G73,D2!G73,D3!G73,D4!G73,D5!G73,D6!G73) | H73: =CHOOSE(Controls!$B$6,D1!H73,D2!H73,D3!H73,D4!H73,D5!H73,D6!H73) | I73: =CHOOSE(Controls!$B$6,D1!I73,D2!I73,D3!I73,D4!I73,D5!I73,D6!I73) | J73: =CHOOSE(Controls!$B$6,D1!J73,D2!J73,D3!J73,D4!J73,D5!J73,D6!J73) | K73: =CHOOSE(Controls!$B$6,D1!K73,D2!K73,D3!K73,D4!K73,D5!K73,D6!K73) | L73: =CHOOSE(Controls!$B$6,D1!L73,D2!L73,D3!L73,D4!L73,D5!L73,D6!L73) | ... O73: =CHOOSE(Controls!$B$6,D1!O73,D2!O73,D3!O73,D4!O73,D5!O73,D6!O73)
A74: Tokens per GPU-hour | B74: IN | C74: tok/hr | D74: Serving throughput (back-solved for consistency). | E74: =CHOOSE(Controls!$B$6,D1!E74,D2!E74,D3!E74,D4!E74,D5!E74,D6!E74) | F74: =CHOOSE(Controls!$B$6,D1!F74,D2!F74,D3!F74,D4!F74,D5!F74,D6!F74) | G74: =CHOOSE(Controls!$B$6,D1!G74,D2!G74,D3!G74,D4!G74,D5!G74,D6!G74) | H74: =CHOOSE(Controls!$B$6,D1!H74,D2!H74,D3!H74,D4!H74,D5!H74,D6!H74) | I74: =CHOOSE(Controls!$B$6,D1!I74,D2!I74,D3!I74,D4!I74,D5!I74,D6!I74) | J74: =CHOOSE(Controls!$B$6,D1!J74,D2!J74,D3!J74,D4!J74,D5!J74,D6!J74) | K74: =CHOOSE(Controls!$B$6,D1!K74,D2!K74,D3!K74,D4!K74,D5!K74,D6!K74) | L74: =CHOOSE(Controls!$B$6,D1!L74,D2!L74,D3!L74,D4!L74,D5!L74,D6!L74) | ... O74: =CHOOSE(Controls!$B$6,D1!O74,D2!O74,D3!O74,D4!O74,D5!O74,D6!O74)
A75: Required GPU-hours | B75: CALC | C75: hr | D75: gross tokens / tokens-per-GPU-hour. | E75: =CHOOSE(Controls!$B$6,D1!E75,D2!E75,D3!E75,D4!E75,D5!E75,D6!E75) | F75: =CHOOSE(Controls!$B$6,D1!F75,D2!F75,D3!F75,D4!F75,D5!F75,D6!F75) | G75: =CHOOSE(Controls!$B$6,D1!G75,D2!G75,D3!G75,D4!G75,D5!G75,D6!G75) | H75: =CHOOSE(Controls!$B$6,D1!H75,D2!H75,D3!H75,D4!H75,D5!H75,D6!H75) | I75: =CHOOSE(Controls!$B$6,D1!I75,D2!I75,D3!I75,D4!I75,D5!I75,D6!I75) | J75: =CHOOSE(Controls!$B$6,D1!J75,D2!J75,D3!J75,D4!J75,D5!J75,D6!J75) | K75: =CHOOSE(Controls!$B$6,D1!K75,D2!K75,D3!K75,D4!K75,D5!K75,D6!K75) | L75: =CHOOSE(Controls!$B$6,D1!L75,D2!L75,D3!L75,D4!L75,D5!L75,D6!L75) | ... O75: =CHOOSE(Controls!$B$6,D1!O75,D2!O75,D3!O75,D4!O75,D5!O75,D6!O75)
A76: Fleet utilization % | B76: IN | C76: % | D76: Effective serving utilization. | E76: =CHOOSE(Controls!$B$6,D1!E76,D2!E76,D3!E76,D4!E76,D5!E76,D6!E76) | F76: =CHOOSE(Controls!$B$6,D1!F76,D2!F76,D3!F76,D4!F76,D5!F76,D6!F76) | G76: =CHOOSE(Controls!$B$6,D1!G76,D2!G76,D3!G76,D4!G76,D5!G76,D6!G76) | H76: =CHOOSE(Controls!$B$6,D1!H76,D2!H76,D3!H76,D4!H76,D5!H76,D6!H76) | I76: =CHOOSE(Controls!$B$6,D1!I76,D2!I76,D3!I76,D4!I76,D5!I76,D6!I76) | J76: =CHOOSE(Controls!$B$6,D1!J76,D2!J76,D3!J76,D4!J76,D5!J76,D6!J76) | K76: =CHOOSE(Controls!$B$6,D1!K76,D2!K76,D3!K76,D4!K76,D5!K76,D6!K76) | L76: =CHOOSE(Controls!$B$6,D1!L76,D2!L76,D3!L76,D4!L76,D5!L76,D6!L76) | ... O76: =CHOOSE(Controls!$B$6,D1!O76,D2!O76,D3!O76,D4!O76,D5!O76,D6!O76)
A77: Total provisioned GPU-hours | B77: CALC | C77: hr | D77: required / utilization. | E77: =CHOOSE(Controls!$B$6,D1!E77,D2!E77,D3!E77,D4!E77,D5!E77,D6!E77) | F77: =CHOOSE(Controls!$B$6,D1!F77,D2!F77,D3!F77,D4!F77,D5!F77,D6!F77) | G77: =CHOOSE(Controls!$B$6,D1!G77,D2!G77,D3!G77,D4!G77,D5!G77,D6!G77) | H77: =CHOOSE(Controls!$B$6,D1!H77,D2!H77,D3!H77,D4!H77,D5!H77,D6!H77) | I77: =CHOOSE(Controls!$B$6,D1!I77,D2!I77,D3!I77,D4!I77,D5!I77,D6!I77) | J77: =CHOOSE(Controls!$B$6,D1!J77,D2!J77,D3!J77,D4!J77,D5!J77,D6!J77) | K77: =CHOOSE(Controls!$B$6,D1!K77,D2!K77,D3!K77,D4!K77,D5!K77,D6!K77) | L77: =CHOOSE(Controls!$B$6,D1!L77,D2!L77,D3!L77,D4!L77,D5!L77,D6!L77) | ... O77: =CHOOSE(Controls!$B$6,D1!O77,D2!O77,D3!O77,D4!O77,D5!O77,D6!O77)
A78: Blended $/GPU-hour | B78: IN | C78: $ | D78: Owned + rented all-in hourly cost. | E78: =CHOOSE(Controls!$B$6,D1!E78,D2!E78,D3!E78,D4!E78,D5!E78,D6!E78) | F78: =CHOOSE(Controls!$B$6,D1!F78,D2!F78,D3!F78,D4!F78,D5!F78,D6!F78) | G78: =CHOOSE(Controls!$B$6,D1!G78,D2!G78,D3!G78,D4!G78,D5!G78,D6!G78) | H78: =CHOOSE(Controls!$B$6,D1!H78,D2!H78,D3!H78,D4!H78,D5!H78,D6!H78) | I78: =CHOOSE(Controls!$B$6,D1!I78,D2!I78,D3!I78,D4!I78,D5!I78,D6!I78) | J78: =CHOOSE(Controls!$B$6,D1!J78,D2!J78,D3!J78,D4!J78,D5!J78,D6!J78) | K78: =CHOOSE(Controls!$B$6,D1!K78,D2!K78,D3!K78,D4!K78,D5!K78,D6!K78) | L78: =CHOOSE(Controls!$B$6,D1!L78,D2!L78,D3!L78,D4!L78,D5!L78,D6!L78) | ... O78: =CHOOSE(Controls!$B$6,D1!O78,D2!O78,D3!O78,D4!O78,D5!O78,D6!O78)
A79: Inference compute cost | B79: CALC | C79: $M | D79: Declining share of revenue; GPU-hrs x $/GPU-hr. | E79: =CHOOSE(Controls!$B$6,D1!E79,D2!E79,D3!E79,D4!E79,D5!E79,D6!E79) | F79: =CHOOSE(Controls!$B$6,D1!F79,D2!F79,D3!F79,D4!F79,D5!F79,D6!F79) | G79: =CHOOSE(Controls!$B$6,D1!G79,D2!G79,D3!G79,D4!G79,D5!G79,D6!G79) | H79: =CHOOSE(Controls!$B$6,D1!H79,D2!H79,D3!H79,D4!H79,D5!H79,D6!H79) | I79: =CHOOSE(Controls!$B$6,D1!I79,D2!I79,D3!I79,D4!I79,D5!I79,D6!I79) | J79: =CHOOSE(Controls!$B$6,D1!J79,D2!J79,D3!J79,D4!J79,D5!J79,D6!J79) | K79: =CHOOSE(Controls!$B$6,D1!K79,D2!K79,D3!K79,D4!K79,D5!K79,D6!K79) | L79: =CHOOSE(Controls!$B$6,D1!L79,D2!L79,D3!L79,D4!L79,D5!L79,D6!L79) | ... O79: =CHOOSE(Controls!$B$6,D1!O79,D2!O79,D3!O79,D4!O79,D5!O79,D6!O79)
A80: Data egress volume (PB) | B80: IN | C80: PB | D80: Outbound data volume. | E80: =CHOOSE(Controls!$B$6,D1!E80,D2!E80,D3!E80,D4!E80,D5!E80,D6!E80) | F80: =CHOOSE(Controls!$B$6,D1!F80,D2!F80,D3!F80,D4!F80,D5!F80,D6!F80) | G80: =CHOOSE(Controls!$B$6,D1!G80,D2!G80,D3!G80,D4!G80,D5!G80,D6!G80) | H80: =CHOOSE(Controls!$B$6,D1!H80,D2!H80,D3!H80,D4!H80,D5!H80,D6!H80) | I80: =CHOOSE(Controls!$B$6,D1!I80,D2!I80,D3!I80,D4!I80,D5!I80,D6!I80) | J80: =CHOOSE(Controls!$B$6,D1!J80,D2!J80,D3!J80,D4!J80,D5!J80,D6!J80) | K80: =CHOOSE(Controls!$B$6,D1!K80,D2!K80,D3!K80,D4!K80,D5!K80,D6!K80) | L80: =CHOOSE(Controls!$B$6,D1!L80,D2!L80,D3!L80,D4!L80,D5!L80,D6!L80) | ... O80: =CHOOSE(Controls!$B$6,D1!O80,D2!O80,D3!O80,D4!O80,D5!O80,D6!O80)
A81: Egress cost ($/TB) | B81: IN | C81: $ | D81: Blended egress unit cost. | E81: =CHOOSE(Controls!$B$6,D1!E81,D2!E81,D3!E81,D4!E81,D5!E81,D6!E81) | F81: =CHOOSE(Controls!$B$6,D1!F81,D2!F81,D3!F81,D4!F81,D5!F81,D6!F81) | G81: =CHOOSE(Controls!$B$6,D1!G81,D2!G81,D3!G81,D4!G81,D5!G81,D6!G81) | H81: =CHOOSE(Controls!$B$6,D1!H81,D2!H81,D3!H81,D4!H81,D5!H81,D6!H81) | I81: =CHOOSE(Controls!$B$6,D1!I81,D2!I81,D3!I81,D4!I81,D5!I81,D6!I81) | J81: =CHOOSE(Controls!$B$6,D1!J81,D2!J81,D3!J81,D4!J81,D5!J81,D6!J81) | K81: =CHOOSE(Controls!$B$6,D1!K81,D2!K81,D3!K81,D4!K81,D5!K81,D6!K81) | L81: =CHOOSE(Controls!$B$6,D1!L81,D2!L81,D3!L81,D4!L81,D5!L81,D6!L81) | ... O81: =CHOOSE(Controls!$B$6,D1!O81,D2!O81,D3!O81,D4!O81,D5!O81,D6!O81)
... A84: API gateway and load-balancing | B84: IN | C84: $M | D84: Edge/gateway/LB. | E84: =CHOOSE(Controls!$B$6,D1!E84,D2!E84,D3!E84,D4!E84,D5!E84,D6!E84) | F84: =CHOOSE(Controls!$B$6,D1!F84,D2!F84,D3!F84,D4!F84,D5!F84,D6!F84) | G84: =CHOOSE(Controls!$B$6,D1!G84,D2!G84,D3!G84,D4!G84,D5!G84,D6!G84) | H84: =CHOOSE(Controls!$B$6,D1!H84,D2!H84,D3!H84,D4!H84,D5!H84,D6!H84) | I84: =CHOOSE(Controls!$B$6,D1!I84,D2!I84,D3!I84,D4!I84,D5!I84,D6!I84) | J84: =CHOOSE(Controls!$B$6,D1!J84,D2!J84,D3!J84,D4!J84,D5!J84,D6!J84) | K84: =CHOOSE(Controls!$B$6,D1!K84,D2!K84,D3!K84,D4!K84,D5!K84,D6!K84) | L84: =CHOOSE(Controls!$B$6,D1!L84,D2!L84,D3!L84,D4!L84,D5!L84,D6!L84) | ... O84: =CHOOSE(Controls!$B$6,D1!O84,D2!O84,D3!O84,D4!O84,D5!O84,D6!O84)
A85: COSTS - SAFETY, PAYMENTS, SUPPORT
A86: Content moderation cost $/Mtok | B86: IN | C86: $ | D86: Classifier cost per Mtok gross. | E86: =CHOOSE(Controls!$B$6,D1!E86,D2!E86,D3!E86,D4!E86,D5!E86,D6!E86) | F86: =CHOOSE(Controls!$B$6,D1!F86,D2!F86,D3!F86,D4!F86,D5!F86,D6!F86) | G86: =CHOOSE(Controls!$B$6,D1!G86,D2!G86,D3!G86,D4!G86,D5!G86,D6!G86) | H86: =CHOOSE(Controls!$B$6,D1!H86,D2!H86,D3!H86,D4!H86,D5!H86,D6!H86) | I86: =CHOOSE(Controls!$B$6,D1!I86,D2!I86,D3!I86,D4!I86,D5!I86,D6!I86) | J86: =CHOOSE(Controls!$B$6,D1!J86,D2!J86,D3!J86,D4!J86,D5!J86,D6!J86) | K86: =CHOOSE(Controls!$B$6,D1!K86,D2!K86,D3!K86,D4!K86,D5!K86,D6!K86) | L86: =CHOOSE(Controls!$B$6,D1!L86,D2!L86,D3!L86,D4!L86,D5!L86,D6!L86) | ... O86: =CHOOSE(Controls!$B$6,D1!O86,D2!O86,D3!O86,D4!O86,D5!O86,D6!O86)
A87: Automated moderation cost | B87: CALC | C87: $M | D87: gross tokens x $/Mtok. | E87: =CHOOSE(Controls!$B$6,D1!E87,D2!E87,D3!E87,D4!E87,D5!E87,D6!E87) | F87: =CHOOSE(Controls!$B$6,D1!F87,D2!F87,D3!F87,D4!F87,D5!F87,D6!F87) | G87: =CHOOSE(Controls!$B$6,D1!G87,D2!G87,D3!G87,D4!G87,D5!G87,D6!G87) | H87: =CHOOSE(Controls!$B$6,D1!H87,D2!H87,D3!H87,D4!H87,D5!H87,D6!H87) | I87: =CHOOSE(Controls!$B$6,D1!I87,D2!I87,D3!I87,D4!I87,D5!I87,D6!I87) | J87: =CHOOSE(Controls!$B$6,D1!J87,D2!J87,D3!J87,D4!J87,D5!J87,D6!J87) | K87: =CHOOSE(Controls!$B$6,D1!K87,D2!K87,D3!K87,D4!K87,D5!K87,D6!K87) | L87: =CHOOSE(Controls!$B$6,D1!L87,D2!L87,D3!L87,D4!L87,D5!L87,D6!L87) | ... O87: =CHOOSE(Controls!$B$6,D1!O87,D2!O87,D3!O87,D4!O87,D5!O87,D6!O87)
A88: HITL review volume | B88: IN | C88: Count | D88: Human safety reviews / yr. | E88: =CHOOSE(Controls!$B$6,D1!E88,D2!E88,D3!E88,D4!E88,D5!E88,D6!E88) | F88: =CHOOSE(Controls!$B$6,D1!F88,D2!F88,D3!F88,D4!F88,D5!F88,D6!F88) | G88: =CHOOSE(Controls!$B$6,D1!G88,D2!G88,D3!G88,D4!G88,D5!G88,D6!G88) | H88: =CHOOSE(Controls!$B$6,D1!H88,D2!H88,D3!H88,D4!H88,D5!H88,D6!H88) | I88: =CHOOSE(Controls!$B$6,D1!I88,D2!I88,D3!I88,D4!I88,D5!I88,D6!I88) | J88: =CHOOSE(Controls!$B$6,D1!J88,D2!J88,D3!J88,D4!J88,D5!J88,D6!J88) | K88: =CHOOSE(Controls!$B$6,D1!K88,D2!K88,D3!K88,D4!K88,D5!K88,D6!K88) | L88: =CHOOSE(Controls!$B$6,D1!L88,D2!L88,D3!L88,D4!L88,D5!L88,D6!L88) | ... O88: =CHOOSE(Controls!$B$6,D1!O88,D2!O88,D3!O88,D4!O88,D5!O88,D6!O88)
A89: Cost per HITL review | B89: IN | C89: $ | D89: BPO hourly x hours. | E89: =CHOOSE(Controls!$B$6,D1!E89,D2!E89,D3!E89,D4!E89,D5!E89,D6!E89) | F89: =CHOOSE(Controls!$B$6,D1!F89,D2!F89,D3!F89,D4!F89,D5!F89,D6!F89) | G89: =CHOOSE(Controls!$B$6,D1!G89,D2!G89,D3!G89,D4!G89,D5!G89,D6!G89) | H89: =CHOOSE(Controls!$B$6,D1!H89,D2!H89,D3!H89,D4!H89,D5!H89,D6!H89) | I89: =CHOOSE(Controls!$B$6,D1!I89,D2!I89,D3!I89,D4!I89,D5!I89,D6!I89) | J89: =CHOOSE(Controls!$B$6,D1!J89,D2!J89,D3!J89,D4!J89,D5!J89,D6!J89) | K89: =CHOOSE(Controls!$B$6,D1!K89,D2!K89,D3!K89,D4!K89,D5!K89,D6!K89) | L89: =CHOOSE(Controls!$B$6,D1!L89,D2!L89,D3!L89,D4!L89,D5!L89,D6!L89) | ... O89: =CHOOSE(Controls!$B$6,D1!O89,D2!O89,D3!O89,D4!O89,D5!O89,D6!O89)
A90: HITL review cost | B90: CALC | C90: $M | D90: volume x cost. | E90: =CHOOSE(Controls!$B$6,D1!E90,D2!E90,D3!E90,D4!E90,D5!E90,D6!E90) | F90: =CHOOSE(Controls!$B$6,D1!F90,D2!F90,D3!F90,D4!F90,D5!F90,D6!F90) | G90: =CHOOSE(Controls!$B$6,D1!G90,D2!G90,D3!G90,D4!G90,D5!G90,D6!G90) | H90: =CHOOSE(Controls!$B$6,D1!H90,D2!H90,D3!H90,D4!H90,D5!H90,D6!H90) | I90: =CHOOSE(Controls!$B$6,D1!I90,D2!I90,D3!I90,D4!I90,D5!I90,D6!I90) | J90: =CHOOSE(Controls!$B$6,D1!J90,D2!J90,D3!J90,D4!J90,D5!J90,D6!J90) | K90: =CHOOSE(Controls!$B$6,D1!K90,D2!K90,D3!K90,D4!K90,D5!K90,D6!K90) | L90: =CHOOSE(Controls!$B$6,D1!L90,D2!L90,D3!L90,D4!L90,D5!L90,D6!L90) | ... O90: =CHOOSE(Controls!$B$6,D1!O90,D2!O90,D3!O90,D4!O90,D5!O90,D6!O90)
A91: B2B gross cash collections | B91: LINK | C91: $M | D91: API + seats + CC + FT + PT + PS. | E91: =CHOOSE(Controls!$B$6,D1!E91,D2!E91,D3!E91,D4!E91,D5!E91,D6!E91) | F91: =CHOOSE(Controls!$B$6,D1!F91,D2!F91,D3!F91,D4!F91,D5!F91,D6!F91) | G91: =CHOOSE(Controls!$B$6,D1!G91,D2!G91,D3!G91,D4!G91,D5!G91,D6!G91) | H91: =CHOOSE(Controls!$B$6,D1!H91,D2!H91,D3!H91,D4!H91,D5!H91,D6!H91) | I91: =CHOOSE(Controls!$B$6,D1!I91,D2!I91,D3!I91,D4!I91,D5!I91,D6!I91) | J91: =CHOOSE(Controls!$B$6,D1!J91,D2!J91,D3!J91,D4!J91,D5!J91,D6!J91) | K91: =CHOOSE(Controls!$B$6,D1!K91,D2!K91,D3!K91,D4!K91,D5!K91,D6!K91) | L91: =CHOOSE(Controls!$B$6,D1!L91,D2!L91,D3!L91,D4!L91,D5!L91,D6!L91) | ... O91: =CHOOSE(Controls!$B$6,D1!O91,D2!O91,D3!O91,D4!O91,D5!O91,D6!O91)
A92: Payment processing fee % (Stripe) | B92: IN | C92: % | D92: Blended processor fee. | E92: =CHOOSE(Controls!$B$6,D1!E92,D2!E92,D3!E92,D4!E92,D5!E92,D6!E92) | F92: =CHOOSE(Controls!$B$6,D1!F92,D2!F92,D3!F92,D4!F92,D5!F92,D6!F92) | G92: =CHOOSE(Controls!$B$6,D1!G92,D2!G92,D3!G92,D4!G92,D5!G92,D6!G92) | H92: =CHOOSE(Controls!$B$6,D1!H92,D2!H92,D3!H92,D4!H92,D5!H92,D6!H92) | I92: =CHOOSE(Controls!$B$6,D1!I92,D2!I92,D3!I92,D4!I92,D5!I92,D6!I92) | J92: =CHOOSE(Controls!$B$6,D1!J92,D2!J92,D3!J92,D4!J92,D5!J92,D6!J92) | K92: =CHOOSE(Controls!$B$6,D1!K92,D2!K92,D3!K92,D4!K92,D5!K92,D6!K92) | L92: =CHOOSE(Controls!$B$6,D1!L92,D2!L92,D3!L92,D4!L92,D5!L92,D6!L92) | ... O92: =CHOOSE(Controls!$B$6,D1!O92,D2!O92,D3!O92,D4!O92,D5!O92,D6!O92)
A93: B2B payment processing cost | B93: CALC | C93: $M | D93: collections x fee. | E93: =CHOOSE(Controls!$B$6,D1!E93,D2!E93,D3!E93,D4!E93,D5!E93,D6!E93) | F93: =CHOOSE(Controls!$B$6,D1!F93,D2!F93,D3!F93,D4!F93,D5!F93,D6!F93) | G93: =CHOOSE(Controls!$B$6,D1!G93,D2!G93,D3!G93,D4!G93,D5!G93,D6!G93) | H93: =CHOOSE(Controls!$B$6,D1!H93,D2!H93,D3!H93,D4!H93,D5!H93,D6!H93) | I93: =CHOOSE(Controls!$B$6,D1!I93,D2!I93,D3!I93,D4!I93,D5!I93,D6!I93) | J93: =CHOOSE(Controls!$B$6,D1!J93,D2!J93,D3!J93,D4!J93,D5!J93,D6!J93) | K93: =CHOOSE(Controls!$B$6,D1!K93,D2!K93,D3!K93,D4!K93,D5!K93,D6!K93) | L93: =CHOOSE(Controls!$B$6,D1!L93,D2!L93,D3!L93,D4!L93,D5!L93,D6!L93) | ... O93: =CHOOSE(Controls!$B$6,D1!O93,D2!O93,D3!O93,D4!O93,D5!O93,D6!O93)
A94: Mobile share of consumer revenue % | B94: IN | C94: % | D94: Consumer via mobile stores. | E94: =CHOOSE(Controls!$B$6,D1!E94,D2!E94,D3!E94,D4!E94,D5!E94,D6!E94) | F94: =CHOOSE(Controls!$B$6,D1!F94,D2!F94,D3!F94,D4!F94,D5!F94,D6!F94) | G94: =CHOOSE(Controls!$B$6,D1!G94,D2!G94,D3!G94,D4!G94,D5!G94,D6!G94) | H94: =CHOOSE(Controls!$B$6,D1!H94,D2!H94,D3!H94,D4!H94,D5!H94,D6!H94) | I94: =CHOOSE(Controls!$B$6,D1!I94,D2!I94,D3!I94,D4!I94,D5!I94,D6!I94) | J94: =CHOOSE(Controls!$B$6,D1!J94,D2!J94,D3!J94,D4!J94,D5!J94,D6!J94) | K94: =CHOOSE(Controls!$B$6,D1!K94,D2!K94,D3!K94,D4!K94,D5!K94,D6!K94) | L94: =CHOOSE(Controls!$B$6,D1!L94,D2!L94,D3!L94,D4!L94,D5!L94,D6!L94) | ... O94: =CHOOSE(Controls!$B$6,D1!O94,D2!O94,D3!O94,D4!O94,D5!O94,D6!O94)
A95: B2C mobile collections | B95: CALC | C95: $M | D95: consumer rev x mobile share. | E95: =CHOOSE(Controls!$B$6,D1!E95,D2!E95,D3!E95,D4!E95,D5!E95,D6!E95) | F95: =CHOOSE(Controls!$B$6,D1!F95,D2!F95,D3!F95,D4!F95,D5!F95,D6!F95) | G95: =CHOOSE(Controls!$B$6,D1!G95,D2!G95,D3!G95,D4!G95,D5!G95,D6!G95) | H95: =CHOOSE(Controls!$B$6,D1!H95,D2!H95,D3!H95,D4!H95,D5!H95,D6!H95) | I95: =CHOOSE(Controls!$B$6,D1!I95,D2!I95,D3!I95,D4!I95,D5!I95,D6!I95) | J95: =CHOOSE(Controls!$B$6,D1!J95,D2!J95,D3!J95,D4!J95,D5!J95,D6!J95) | K95: =CHOOSE(Controls!$B$6,D1!K95,D2!K95,D3!K95,D4!K95,D5!K95,D6!K95) | L95: =CHOOSE(Controls!$B$6,D1!L95,D2!L95,D3!L95,D4!L95,D5!L95,D6!L95) | ... O95: =CHOOSE(Controls!$B$6,D1!O95,D2!O95,D3!O95,D4!O95,D5!O95,D6!O95)
A96: App store take-rate % | B96: IN | C96: % | D96: Apple/Google store take. | E96: =CHOOSE(Controls!$B$6,D1!E96,D2!E96,D3!E96,D4!E96,D5!E96,D6!E96) | F96: =CHOOSE(Controls!$B$6,D1!F96,D2!F96,D3!F96,D4!F96,D5!F96,D6!F96) | G96: =CHOOSE(Controls!$B$6,D1!G96,D2!G96,D3!G96,D4!G96,D5!G96,D6!G96) | H96: =CHOOSE(Controls!$B$6,D1!H96,D2!H96,D3!H96,D4!H96,D5!H96,D6!H96) | I96: =CHOOSE(Controls!$B$6,D1!I96,D2!I96,D3!I96,D4!I96,D5!I96,D6!I96) | J96: =CHOOSE(Controls!$B$6,D1!J96,D2!J96,D3!J96,D4!J96,D5!J96,D6!J96) | K96: =CHOOSE(Controls!$B$6,D1!K96,D2!K96,D3!K96,D4!K96,D5!K96,D6!K96) | L96: =CHOOSE(Controls!$B$6,D1!L96,D2!L96,D3!L96,D4!L96,D5!L96,D6!L96) | ... O96: =CHOOSE(Controls!$B$6,D1!O96,D2!O96,D3!O96,D4!O96,D5!O96,D6!O96)
A97: App store cost | B97: CALC | C97: $M | D97: mobile collections x take. | E97: =CHOOSE(Controls!$B$6,D1!E97,D2!E97,D3!E97,D4!E97,D5!E97,D6!E97) | F97: =CHOOSE(Controls!$B$6,D1!F97,D2!F97,D3!F97,D4!F97,D5!F97,D6!F97) | G97: =CHOOSE(Controls!$B$6,D1!G97,D2!G97,D3!G97,D4!G97,D5!G97,D6!G97) | H97: =CHOOSE(Controls!$B$6,D1!H97,D2!H97,D3!H97,D4!H97,D5!H97,D6!H97) | I97: =CHOOSE(Controls!$B$6,D1!I97,D2!I97,D3!I97,D4!I97,D5!I97,D6!I97) | J97: =CHOOSE(Controls!$B$6,D1!J97,D2!J97,D3!J97,D4!J97,D5!J97,D6!J97) | K97: =CHOOSE(Controls!$B$6,D1!K97,D2!K97,D3!K97,D4!K97,D5!K97,D6!K97) | L97: =CHOOSE(Controls!$B$6,D1!L97,D2!L97,D3!L97,D4!L97,D5!L97,D6!L97) | ... O97: =CHOOSE(Controls!$B$6,D1!O97,D2!O97,D3!O97,D4!O97,D5!O97,D6!O97)
... A106: Memo: implied gross margin % | B106: CALC | C106: % | D106: Inference-only gross margin. | E106: =CHOOSE(Controls!$B$6,D1!E106,D2!E106,D3!E106,D4!E106,D5!E106,D6!E106) | F106: =CHOOSE(Controls!$B$6,D1!F106,D2!F106,D3!F106,D4!F106,D5!F106,D6!F106) | G106: =CHOOSE(Controls!$B$6,D1!G106,D2!G106,D3!G106,D4!G106,D5!G106,D6!G106) | H106: =CHOOSE(Controls!$B$6,D1!H106,D2!H106,D3!H106,D4!H106,D5!H106,D6!H106) | I106: =CHOOSE(Controls!$B$6,D1!I106,D2!I106,D3!I106,D4!I106,D5!I106,D6!I106) | J106: =CHOOSE(Controls!$B$6,D1!J106,D2!J106,D3!J106,D4!J106,D5!J106,D6!J106) | K106: =CHOOSE(Controls!$B$6,D1!K106,D2!K106,D3!K106,D4!K106,D5!K106,D6!K106) | L106: =CHOOSE(Controls!$B$6,D1!L106,D2!L106,D3!L106,D4!L106,D5!L106,D6!L106) | ... O106: =CHOOSE(Controls!$B$6,D1!O106,D2!O106,D3!O106,D4!O106,D5!O106,D6!O106)
A107: OpEx & Comp (ex-SBC)
A108: R&D headcount | B108: IN | C108: count | D108: Research + eng (~65-75% of total). | E108: =CHOOSE(Controls!$B$6,D1!E108,D2!E108,D3!E108,D4!E108,D5!E108,D6!E108) | F108: =CHOOSE(Controls!$B$6,D1!F108,D2!F108,D3!F108,D4!F108,D5!F108,D6!F108) | G108: =CHOOSE(Controls!$B$6,D1!G108,D2!G108,D3!G108,D4!G108,D5!G108,D6!G108) | H108: =CHOOSE(Controls!$B$6,D1!H108,D2!H108,D3!H108,D4!H108,D5!H108,D6!H108) | I108: =CHOOSE(Controls!$B$6,D1!I108,D2!I108,D3!I108,D4!I108,D5!I108,D6!I108) | J108: =CHOOSE(Controls!$B$6,D1!J108,D2!J108,D3!J108,D4!J108,D5!J108,D6!J108) | K108: =CHOOSE(Controls!$B$6,D1!K108,D2!K108,D3!K108,D4!K108,D5!K108,D6!K108) | L108: =CHOOSE(Controls!$B$6,D1!L108,D2!L108,D3!L108,D4!L108,D5!L108,D6!L108) | ... O108: =CHOOSE(Controls!$B$6,D1!O108,D2!O108,D3!O108,D4!O108,D5!O108,D6!O108)
A109: Fully-burdened R&D cash comp ($/head) | B109: IN | C109: $ | D109: Levels.fyi eng $619-841k, research ~$746k median. | E109: =CHOOSE(Controls!$B$6,D1!E109,D2!E109,D3!E109,D4!E109,D5!E109,D6!E109) | F109: =CHOOSE(Controls!$B$6,D1!F109,D2!F109,D3!F109,D4!F109,D5!F109,D6!F109) | G109: =CHOOSE(Controls!$B$6,D1!G109,D2!G109,D3!G109,D4!G109,D5!G109,D6!G109) | H109: =CHOOSE(Controls!$B$6,D1!H109,D2!H109,D3!H109,D4!H109,D5!H109,D6!H109) | I109: =CHOOSE(Controls!$B$6,D1!I109,D2!I109,D3!I109,D4!I109,D5!I109,D6!I109) | J109: =CHOOSE(Controls!$B$6,D1!J109,D2!J109,D3!J109,D4!J109,D5!J109,D6!J109) | K109: =CHOOSE(Controls!$B$6,D1!K109,D2!K109,D3!K109,D4!K109,D5!K109,D6!K109) | L109: =CHOOSE(Controls!$B$6,D1!L109,D2!L109,D3!L109,D4!L109,D5!L109,D6!L109) | ... O109: =CHOOSE(Controls!$B$6,D1!O109,D2!O109,D3!O109,D4!O109,D5!O109,D6!O109)
A110: R&D personnel cost | B110: CALC | C110: $M | D110: heads x comp. | E110: =CHOOSE(Controls!$B$6,D1!E110,D2!E110,D3!E110,D4!E110,D5!E110,D6!E110) | F110: =CHOOSE(Controls!$B$6,D1!F110,D2!F110,D3!F110,D4!F110,D5!F110,D6!F110) | G110: =CHOOSE(Controls!$B$6,D1!G110,D2!G110,D3!G110,D4!G110,D5!G110,D6!G110) | H110: =CHOOSE(Controls!$B$6,D1!H110,D2!H110,D3!H110,D4!H110,D5!H110,D6!H110) | I110: =CHOOSE(Controls!$B$6,D1!I110,D2!I110,D3!I110,D4!I110,D5!I110,D6!I110) | J110: =CHOOSE(Controls!$B$6,D1!J110,D2!J110,D3!J110,D4!J110,D5!J110,D6!J110) | K110: =CHOOSE(Controls!$B$6,D1!K110,D2!K110,D3!K110,D4!K110,D5!K110,D6!K110) | L110: =CHOOSE(Controls!$B$6,D1!L110,D2!L110,D3!L110,D4!L110,D5!L110,D6!L110) | ... O110: =CHOOSE(Controls!$B$6,D1!O110,D2!O110,D3!O110,D4!O110,D5!O110,D6!O110)
A111: RLHF & data annotation | B111: IN | C111: $M | D111: Human feedback/annotation. | E111: =CHOOSE(Controls!$B$6,D1!E111,D2!E111,D3!E111,D4!E111,D5!E111,D6!E111) | F111: =CHOOSE(Controls!$B$6,D1!F111,D2!F111,D3!F111,D4!F111,D5!F111,D6!F111) | G111: =CHOOSE(Controls!$B$6,D1!G111,D2!G111,D3!G111,D4!G111,D5!G111,D6!G111) | H111: =CHOOSE(Controls!$B$6,D1!H111,D2!H111,D3!H111,D4!H111,D5!H111,D6!H111) | I111: =CHOOSE(Controls!$B$6,D1!I111,D2!I111,D3!I111,D4!I111,D5!I111,D6!I111) | J111: =CHOOSE(Controls!$B$6,D1!J111,D2!J111,D3!J111,D4!J111,D5!J111,D6!J111) | K111: =CHOOSE(Controls!$B$6,D1!K111,D2!K111,D3!K111,D4!K111,D5!K111,D6!K111) | L111: =CHOOSE(Controls!$B$6,D1!L111,D2!L111,D3!L111,D4!L111,D5!L111,D6!L111) | ... O111: =CHOOSE(Controls!$B$6,D1!O111,D2!O111,D3!O111,D4!O111,D5!O111,D6!O111)
A112: Proprietary data licensing | B112: IN | C112: $M | D112: Licensed training data. | E112: =CHOOSE(Controls!$B$6,D1!E112,D2!E112,D3!E112,D4!E112,D5!E112,D6!E112) | F112: =CHOOSE(Controls!$B$6,D1!F112,D2!F112,D3!F112,D4!F112,D5!F112,D6!F112) | G112: =CHOOSE(Controls!$B$6,D1!G112,D2!G112,D3!G112,D4!G112,D5!G112,D6!G112) | H112: =CHOOSE(Controls!$B$6,D1!H112,D2!H112,D3!H112,D4!H112,D5!H112,D6!H112) | I112: =CHOOSE(Controls!$B$6,D1!I112,D2!I112,D3!I112,D4!I112,D5!I112,D6!I112) | J112: =CHOOSE(Controls!$B$6,D1!J112,D2!J112,D3!J112,D4!J112,D5!J112,D6!J112) | K112: =CHOOSE(Controls!$B$6,D1!K112,D2!K112,D3!K112,D4!K112,D5!K112,D6!K112) | L112: =CHOOSE(Controls!$B$6,D1!L112,D2!L112,D3!L112,D4!L112,D5!L112,D6!L112) | ... O112: =CHOOSE(Controls!$B$6,D1!O112,D2!O112,D3!O112,D4!O112,D5!O112,D6!O112)
A113: Experimental / failed training runs | B113: IN | C113: $M | D113: Abandoned run compute. | E113: =CHOOSE(Controls!$B$6,D1!E113,D2!E113,D3!E113,D4!E113,D5!E113,D6!E113) | F113: =CHOOSE(Controls!$B$6,D1!F113,D2!F113,D3!F113,D4!F113,D5!F113,D6!F113) | G113: =CHOOSE(Controls!$B$6,D1!G113,D2!G113,D3!G113,D4!G113,D5!G113,D6!G113) | H113: =CHOOSE(Controls!$B$6,D1!H113,D2!H113,D3!H113,D4!H113,D5!H113,D6!H113) | I113: =CHOOSE(Controls!$B$6,D1!I113,D2!I113,D3!I113,D4!I113,D5!I113,D6!I113) | J113: =CHOOSE(Controls!$B$6,D1!J113,D2!J113,D3!J113,D4!J113,D5!J113,D6!J113) | K113: =CHOOSE(Controls!$B$6,D1!K113,D2!K113,D3!K113,D4!K113,D5!K113,D6!K113) | L113: =CHOOSE(Controls!$B$6,D1!L113,D2!L113,D3!L113,D4!L113,D5!L113,D6!L113) | ... O113: =CHOOSE(Controls!$B$6,D1!O113,D2!O113,D3!O113,D4!O113,D5!O113,D6!O113)
A114: Internal tooling & subscriptions | B114: IN | C114: $M | D114: Dev tooling/SaaS. | E114: =CHOOSE(Controls!$B$6,D1!E114,D2!E114,D3!E114,D4!E114,D5!E114,D6!E114) | F114: =CHOOSE(Controls!$B$6,D1!F114,D2!F114,D3!F114,D4!F114,D5!F114,D6!F114) | G114: =CHOOSE(Controls!$B$6,D1!G114,D2!G114,D3!G114,D4!G114,D5!G114,D6!G114) | H114: =CHOOSE(Controls!$B$6,D1!H114,D2!H114,D3!H114,D4!H114,D5!H114,D6!H114) | I114: =CHOOSE(Controls!$B$6,D1!I114,D2!I114,D3!I114,D4!I114,D5!I114,D6!I114) | J114: =CHOOSE(Controls!$B$6,D1!J114,D2!J114,D3!J114,D4!J114,D5!J114,D6!J114) | K114: =CHOOSE(Controls!$B$6,D1!K114,D2!K114,D3!K114,D4!K114,D5!K114,D6!K114) | L114: =CHOOSE(Controls!$B$6,D1!L114,D2!L114,D3!L114,D4!L114,D5!L114,D6!L114) | ... O114: =CHOOSE(Controls!$B$6,D1!O114,D2!O114,D3!O114,D4!O114,D5!O114,D6!O114)
A115: Capitalizable frontier-training runs | B115: IN | C115: $M | D115: Capitalizable portion (~30% of training). | E115: =CHOOSE(Controls!$B$6,D1!E115,D2!E115,D3!E115,D4!E115,D5!E115,D6!E115) | F115: =CHOOSE(Controls!$B$6,D1!F115,D2!F115,D3!F115,D4!F115,D5!F115,D6!F115) | G115: =CHOOSE(Controls!$B$6,D1!G115,D2!G115,D3!G115,D4!G115,D5!G115,D6!G115) | H115: =CHOOSE(Controls!$B$6,D1!H115,D2!H115,D3!H115,D4!H115,D5!H115,D6!H115) | I115: =CHOOSE(Controls!$B$6,D1!I115,D2!I115,D3!I115,D4!I115,D5!I115,D6!I115) | J115: =CHOOSE(Controls!$B$6,D1!J115,D2!J115,D3!J115,D4!J115,D5!J115,D6!J115) | K115: =CHOOSE(Controls!$B$6,D1!K115,D2!K115,D3!K115,D4!K115,D5!K115,D6!K115) | L115: =CHOOSE(Controls!$B$6,D1!L115,D2!L115,D3!L115,D4!L115,D5!L115,D6!L115) | ... O115: =CHOOSE(Controls!$B$6,D1!O115,D2!O115,D3!O115,D4!O115,D5!O115,D6!O115)
A116: Cap toggle (1=capitalized, 0=ASC 730 expense) | B116: IN | C116: 0/1 | D116: 0 = expense training to R&D (base). | E116: =CHOOSE(Controls!$B$6,D1!E116,D2!E116,D3!E116,D4!E116,D5!E116,D6!E116) | F116: =CHOOSE(Controls!$B$6,D1!F116,D2!F116,D3!F116,D4!F116,D5!F116,D6!F116) | G116: =CHOOSE(Controls!$B$6,D1!G116,D2!G116,D3!G116,D4!G116,D5!G116,D6!G116) | H116: =CHOOSE(Controls!$B$6,D1!H116,D2!H116,D3!H116,D4!H116,D5!H116,D6!H116) | I116: =CHOOSE(Controls!$B$6,D1!I116,D2!I116,D3!I116,D4!I116,D5!I116,D6!I116) | J116: =CHOOSE(Controls!$B$6,D1!J116,D2!J116,D3!J116,D4!J116,D5!J116,D6!J116) | K116: =CHOOSE(Controls!$B$6,D1!K116,D2!K116,D3!K116,D4!K116,D5!K116,D6!K116) | L116: =CHOOSE(Controls!$B$6,D1!L116,D2!L116,D3!L116,D4!L116,D5!L116,D6!L116) | ... O116: =CHOOSE(Controls!$B$6,D1!O116,D2!O116,D3!O116,D4!O116,D5!O116,D6!O116)
A117: Training compute expenses to R&D | B117: CALC | C117: $M | D117: Training (expensed) + research compute. Primary loss driver. | E117: =CHOOSE(Controls!$B$6,D1!E117,D2!E117,D3!E117,D4!E117,D5!E117,D6!E117) | F117: =CHOOSE(Controls!$B$6,D1!F117,D2!F117,D3!F117,D4!F117,D5!F117,D6!F117) | G117: =CHOOSE(Controls!$B$6,D1!G117,D2!G117,D3!G117,D4!G117,D5!G117,D6!G117) | H117: =CHOOSE(Controls!$B$6,D1!H117,D2!H117,D3!H117,D4!H117,D5!H117,D6!H117) | I117: =CHOOSE(Controls!$B$6,D1!I117,D2!I117,D3!I117,D4!I117,D5!I117,D6!I117) | J117: =CHOOSE(Controls!$B$6,D1!J117,D2!J117,D3!J117,D4!J117,D5!J117,D6!J117) | K117: =CHOOSE(Controls!$B$6,D1!K117,D2!K117,D3!K117,D4!K117,D5!K117,D6!K117) | L117: =CHOOSE(Controls!$B$6,D1!L117,D2!L117,D3!L117,D4!L117,D5!L117,D6!L117) | ... O117: =CHOOSE(Controls!$B$6,D1!O117,D2!O117,D3!O117,D4!O117,D5!O117,D6!O117)
A118: Total R&D (ex-SBC) | B118: CALC | C118: $M | D118: Personnel + RLHF + licensing + failed + tooling + training. | E118: =CHOOSE(Controls!$B$6,D1!E118,D2!E118,D3!E118,D4!E118,D5!E118,D6!E118) | F118: =CHOOSE(Controls!$B$6,D1!F118,D2!F118,D3!F118,D4!F118,D5!F118,D6!F118) | G118: =CHOOSE(Controls!$B$6,D1!G118,D2!G118,D3!G118,D4!G118,D5!G118,D6!G118) | H118: =CHOOSE(Controls!$B$6,D1!H118,D2!H118,D3!H118,D4!H118,D5!H118,D6!H118) | I118: =CHOOSE(Controls!$B$6,D1!I118,D2!I118,D3!I118,D4!I118,D5!I118,D6!I118) | J118: =CHOOSE(Controls!$B$6,D1!J118,D2!J118,D3!J118,D4!J118,D5!J118,D6!J118) | K118: =CHOOSE(Controls!$B$6,D1!K118,D2!K118,D3!K118,D4!K118,D5!K118,D6!K118) | L118: =CHOOSE(Controls!$B$6,D1!L118,D2!L118,D3!L118,D4!L118,D5!L118,D6!L118) | ... O118: =CHOOSE(Controls!$B$6,D1!O118,D2!O118,D3!O118,D4!O118,D5!O118,D6!O118)
A119: S&M Headcount | B119: IN | C119: count | D119: GTM heads (small org). | E119: =CHOOSE(Controls!$B$6,D1!E119,D2!E119,D3!E119,D4!E119,D5!E119,D6!E119) | F119: =CHOOSE(Controls!$B$6,D1!F119,D2!F119,D3!F119,D4!F119,D5!F119,D6!F119) | G119: =CHOOSE(Controls!$B$6,D1!G119,D2!G119,D3!G119,D4!G119,D5!G119,D6!G119) | H119: =CHOOSE(Controls!$B$6,D1!H119,D2!H119,D3!H119,D4!H119,D5!H119,D6!H119) | I119: =CHOOSE(Controls!$B$6,D1!I119,D2!I119,D3!I119,D4!I119,D5!I119,D6!I119) | J119: =CHOOSE(Controls!$B$6,D1!J119,D2!J119,D3!J119,D4!J119,D5!J119,D6!J119) | K119: =CHOOSE(Controls!$B$6,D1!K119,D2!K119,D3!K119,D4!K119,D5!K119,D6!K119) | L119: =CHOOSE(Controls!$B$6,D1!L119,D2!L119,D3!L119,D4!L119,D5!L119,D6!L119) | ... O119: =CHOOSE(Controls!$B$6,D1!O119,D2!O119,D3!O119,D4!O119,D5!O119,D6!O119)
... A133: One-time litigation services | B133: IN | C133: $M | D133: Non-recurring litigation. | E133: =CHOOSE(Controls!$B$6,D1!E133,D2!E133,D3!E133,D4!E133,D5!E133,D6!E133) | F133: =CHOOSE(Controls!$B$6,D1!F133,D2!F133,D3!F133,D4!F133,D5!F133,D6!F133) | G133: =CHOOSE(Controls!$B$6,D1!G133,D2!G133,D3!G133,D4!G133,D5!G133,D6!G133) | H133: =CHOOSE(Controls!$B$6,D1!H133,D2!H133,D3!H133,D4!H133,D5!H133,D6!H133) | I133: =CHOOSE(Controls!$B$6,D1!I133,D2!I133,D3!I133,D4!I133,D5!I133,D6!I133) | J133: =CHOOSE(Controls!$B$6,D1!J133,D2!J133,D3!J133,D4!J133,D5!J133,D6!J133) | K133: =CHOOSE(Controls!$B$6,D1!K133,D2!K133,D3!K133,D4!K133,D5!K133,D6!K133) | L133: =CHOOSE(Controls!$B$6,D1!L133,D2!L133,D3!L133,D4!L133,D5!L133,D6!L133) | ... O133: =CHOOSE(Controls!$B$6,D1!O133,D2!O133,D3!O133,D4!O133,D5!O133,D6!O133)
A134: STOCK BASED COMP
A135: SBC issue rate (% of base cash comp) | B135: IN | C135: % | D135: RSU grant value as % of cash comp. | E135: =CHOOSE(Controls!$B$6,D1!E135,D2!E135,D3!E135,D4!E135,D5!E135,D6!E135) | F135: =CHOOSE(Controls!$B$6,D1!F135,D2!F135,D3!F135,D4!F135,D5!F135,D6!F135) | G135: =CHOOSE(Controls!$B$6,D1!G135,D2!G135,D3!G135,D4!G135,D5!G135,D6!G135) | H135: =CHOOSE(Controls!$B$6,D1!H135,D2!H135,D3!H135,D4!H135,D5!H135,D6!H135) | I135: =CHOOSE(Controls!$B$6,D1!I135,D2!I135,D3!I135,D4!I135,D5!I135,D6!I135) | J135: =CHOOSE(Controls!$B$6,D1!J135,D2!J135,D3!J135,D4!J135,D5!J135,D6!J135) | K135: =CHOOSE(Controls!$B$6,D1!K135,D2!K135,D3!K135,D4!K135,D5!K135,D6!K135) | L135: =CHOOSE(Controls!$B$6,D1!L135,D2!L135,D3!L135,D4!L135,D5!L135,D6!L135) | ... O135: =CHOOSE(Controls!$B$6,D1!O135,D2!O135,D3!O135,D4!O135,D5!O135,D6!O135)
A136: R&D SBC | B136: CALC | C136: $M | D136: R&D cash x SBC rate. | E136: =CHOOSE(Controls!$B$6,D1!E136,D2!E136,D3!E136,D4!E136,D5!E136,D6!E136) | F136: =CHOOSE(Controls!$B$6,D1!F136,D2!F136,D3!F136,D4!F136,D5!F136,D6!F136) | G136: =CHOOSE(Controls!$B$6,D1!G136,D2!G136,D3!G136,D4!G136,D5!G136,D6!G136) | H136: =CHOOSE(Controls!$B$6,D1!H136,D2!H136,D3!H136,D4!H136,D5!H136,D6!H136) | I136: =CHOOSE(Controls!$B$6,D1!I136,D2!I136,D3!I136,D4!I136,D5!I136,D6!I136) | J136: =CHOOSE(Controls!$B$6,D1!J136,D2!J136,D3!J136,D4!J136,D5!J136,D6!J136) | K136: =CHOOSE(Controls!$B$6,D1!K136,D2!K136,D3!K136,D4!K136,D5!K136,D6!K136) | L136: =CHOOSE(Controls!$B$6,D1!L136,D2!L136,D3!L136,D4!L136,D5!L136,D6!L136) | ... O136: =CHOOSE(Controls!$B$6,D1!O136,D2!O136,D3!O136,D4!O136,D5!O136,D6!O136)
A137: S&M SBC | B137: CALC | C137: $M | D137: S&M cash x SBC rate. | E137: =CHOOSE(Controls!$B$6,D1!E137,D2!E137,D3!E137,D4!E137,D5!E137,D6!E137) | F137: =CHOOSE(Controls!$B$6,D1!F137,D2!F137,D3!F137,D4!F137,D5!F137,D6!F137) | G137: =CHOOSE(Controls!$B$6,D1!G137,D2!G137,D3!G137,D4!G137,D5!G137,D6!G137) | H137: =CHOOSE(Controls!$B$6,D1!H137,D2!H137,D3!H137,D4!H137,D5!H137,D6!H137) | I137: =CHOOSE(Controls!$B$6,D1!I137,D2!I137,D3!I137,D4!I137,D5!I137,D6!I137) | J137: =CHOOSE(Controls!$B$6,D1!J137,D2!J137,D3!J137,D4!J137,D5!J137,D6!J137) | K137: =CHOOSE(Controls!$B$6,D1!K137,D2!K137,D3!K137,D4!K137,D5!K137,D6!K137) | L137: =CHOOSE(Controls!$B$6,D1!L137,D2!L137,D3!L137,D4!L137,D5!L137,D6!L137) | ... O137: =CHOOSE(Controls!$B$6,D1!O137,D2!O137,D3!O137,D4!O137,D5!O137,D6!O137)
A138: G&A SBC | B138: CALC | C138: $M | D138: G&A cash x SBC rate. | E138: =CHOOSE(Controls!$B$6,D1!E138,D2!E138,D3!E138,D4!E138,D5!E138,D6!E138) | F138: =CHOOSE(Controls!$B$6,D1!F138,D2!F138,D3!F138,D4!F138,D5!F138,D6!F138) | G138: =CHOOSE(Controls!$B$6,D1!G138,D2!G138,D3!G138,D4!G138,D5!G138,D6!G138) | H138: =CHOOSE(Controls!$B$6,D1!H138,D2!H138,D3!H138,D4!H138,D5!H138,D6!H138) | I138: =CHOOSE(Controls!$B$6,D1!I138,D2!I138,D3!I138,D4!I138,D5!I138,D6!I138) | J138: =CHOOSE(Controls!$B$6,D1!J138,D2!J138,D3!J138,D4!J138,D5!J138,D6!J138) | K138: =CHOOSE(Controls!$B$6,D1!K138,D2!K138,D3!K138,D4!K138,D5!K138,D6!K138) | L138: =CHOOSE(Controls!$B$6,D1!L138,D2!L138,D3!L138,D4!L138,D5!L138,D6!L138) | ... O138: =CHOOSE(Controls!$B$6,D1!O138,D2!O138,D3!O138,D4!O138,D5!O138,D6!O138)
A139: Total SBC | B139: CALC | C139: $M | D139: Sum of function SBC. | E139: =CHOOSE(Controls!$B$6,D1!E139,D2!E139,D3!E139,D4!E139,D5!E139,D6!E139) | F139: =CHOOSE(Controls!$B$6,D1!F139,D2!F139,D3!F139,D4!F139,D5!F139,D6!F139) | G139: =CHOOSE(Controls!$B$6,D1!G139,D2!G139,D3!G139,D4!G139,D5!G139,D6!G139) | H139: =CHOOSE(Controls!$B$6,D1!H139,D2!H139,D3!H139,D4!H139,D5!H139,D6!H139) | I139: =CHOOSE(Controls!$B$6,D1!I139,D2!I139,D3!I139,D4!I139,D5!I139,D6!I139) | J139: =CHOOSE(Controls!$B$6,D1!J139,D2!J139,D3!J139,D4!J139,D5!J139,D6!J139) | K139: =CHOOSE(Controls!$B$6,D1!K139,D2!K139,D3!K139,D4!K139,D5!K139,D6!K139) | L139: =CHOOSE(Controls!$B$6,D1!L139,D2!L139,D3!L139,D4!L139,D5!L139,D6!L139) | ... O139: =CHOOSE(Controls!$B$6,D1!O139,D2!O139,D3!O139,D4!O139,D5!O139,D6!O139)
A140: DEPRECIATION & AMORTIZATION
A141: Amort life - models (yrs) | B141: IN | C141: yr | D141: Life of capitalized models. | E141: =CHOOSE(Controls!$B$6,D1!E141,D2!E141,D3!E141,D4!E141,D5!E141,D6!E141) | F141: =CHOOSE(Controls!$B$6,D1!F141,D2!F141,D3!F141,D4!F141,D5!F141,D6!F141) | G141: =CHOOSE(Controls!$B$6,D1!G141,D2!G141,D3!G141,D4!G141,D5!G141,D6!G141) | H141: =CHOOSE(Controls!$B$6,D1!H141,D2!H141,D3!H141,D4!H141,D5!H141,D6!H141) | I141: =CHOOSE(Controls!$B$6,D1!I141,D2!I141,D3!I141,D4!I141,D5!I141,D6!I141) | J141: =CHOOSE(Controls!$B$6,D1!J141,D2!J141,D3!J141,D4!J141,D5!J141,D6!J141) | K141: =CHOOSE(Controls!$B$6,D1!K141,D2!K141,D3!K141,D4!K141,D5!K141,D6!K141) | L141: =CHOOSE(Controls!$B$6,D1!L141,D2!L141,D3!L141,D4!L141,D5!L141,D6!L141) | ... O141: =CHOOSE(Controls!$B$6,D1!O141,D2!O141,D3!O141,D4!O141,D5!O141,D6!O141)
A142: Amort of capitalized frontier models | B142: CALC | C142: $M | D142: 2-yr straight-line of cap pool. | E142: =CHOOSE(Controls!$B$6,D1!E142,D2!E142,D3!E142,D4!E142,D5!E142,D6!E142) | F142: =CHOOSE(Controls!$B$6,D1!F142,D2!F142,D3!F142,D4!F142,D5!F142,D6!F142) | G142: =CHOOSE(Controls!$B$6,D1!G142,D2!G142,D3!G142,D4!G142,D5!G142,D6!G142) | H142: =CHOOSE(Controls!$B$6,D1!H142,D2!H142,D3!H142,D4!H142,D5!H142,D6!H142) | I142: =CHOOSE(Controls!$B$6,D1!I142,D2!I142,D3!I142,D4!I142,D5!I142,D6!I142) | J142: =CHOOSE(Controls!$B$6,D1!J142,D2!J142,D3!J142,D4!J142,D5!J142,D6!J142) | K142: =CHOOSE(Controls!$B$6,D1!K142,D2!K142,D3!K142,D4!K142,D5!K142,D6!K142) | L142: =CHOOSE(Controls!$B$6,D1!L142,D2!L142,D3!L142,D4!L142,D5!L142,D6!L142) | ... O142: =CHOOSE(Controls!$B$6,D1!O142,D2!O142,D3!O142,D4!O142,D5!O142,D6!O142)
A143: Owned GPU / datacenter capex | B143: IN | C143: $M | D143: Owned hardware capex (Fluidstack $50B ramps 2026+). | E143: =CHOOSE(Controls!$B$6,D1!E143,D2!E143,D3!E143,D4!E143,D5!E143,D6!E143) | F143: =CHOOSE(Controls!$B$6,D1!F143,D2!F143,D3!F143,D4!F143,D5!F143,D6!F143) | G143: =CHOOSE(Controls!$B$6,D1!G143,D2!G143,D3!G143,D4!G143,D5!G143,D6!G143) | H143: =CHOOSE(Controls!$B$6,D1!H143,D2!H143,D3!H143,D4!H143,D5!H143,D6!H143) | I143: =CHOOSE(Controls!$B$6,D1!I143,D2!I143,D3!I143,D4!I143,D5!I143,D6!I143) | J143: =CHOOSE(Controls!$B$6,D1!J143,D2!J143,D3!J143,D4!J143,D5!J143,D6!J143) | K143: =CHOOSE(Controls!$B$6,D1!K143,D2!K143,D3!K143,D4!K143,D5!K143,D6!K143) | L143: =CHOOSE(Controls!$B$6,D1!L143,D2!L143,D3!L143,D4!L143,D5!L143,D6!L143) | ... O143: =CHOOSE(Controls!$B$6,D1!O143,D2!O143,D3!O143,D4!O143,D5!O143,D6!O143)
A144: Depreciation life - HW (yrs) | B144: IN | C144: yr | D144: Life of owned accelerators. | E144: =CHOOSE(Controls!$B$6,D1!E144,D2!E144,D3!E144,D4!E144,D5!E144,D6!E144) | F144: =CHOOSE(Controls!$B$6,D1!F144,D2!F144,D3!F144,D4!F144,D5!F144,D6!F144) | G144: =CHOOSE(Controls!$B$6,D1!G144,D2!G144,D3!G144,D4!G144,D5!G144,D6!G144) | H144: =CHOOSE(Controls!$B$6,D1!H144,D2!H144,D3!H144,D4!H144,D5!H144,D6!H144) | I144: =CHOOSE(Controls!$B$6,D1!I144,D2!I144,D3!I144,D4!I144,D5!I144,D6!I144) | J144: =CHOOSE(Controls!$B$6,D1!J144,D2!J144,D3!J144,D4!J144,D5!J144,D6!J144) | K144: =CHOOSE(Controls!$B$6,D1!K144,D2!K144,D3!K144,D4!K144,D5!K144,D6!K144) | L144: =CHOOSE(Controls!$B$6,D1!L144,D2!L144,D3!L144,D4!L144,D5!L144,D6!L144) | ... O144: =CHOOSE(Controls!$B$6,D1!O144,D2!O144,D3!O144,D4!O144,D5!O144,D6!O144)
A145: Depreciation of owned GPU / datacenter | B145: CALC | C145: $M | D145: Vintage straight-line depreciation. | E145: =CHOOSE(Controls!$B$6,D1!E145,D2!E145,D3!E145,D4!E145,D5!E145,D6!E145) | F145: =CHOOSE(Controls!$B$6,D1!F145,D2!F145,D3!F145,D4!F145,D5!F145,D6!F145) | G145: =CHOOSE(Controls!$B$6,D1!G145,D2!G145,D3!G145,D4!G145,D5!G145,D6!G145) | H145: =CHOOSE(Controls!$B$6,D1!H145,D2!H145,D3!H145,D4!H145,D5!H145,D6!H145) | I145: =CHOOSE(Controls!$B$6,D1!I145,D2!I145,D3!I145,D4!I145,D5!I145,D6!I145) | J145: =CHOOSE(Controls!$B$6,D1!J145,D2!J145,D3!J145,D4!J145,D5!J145,D6!J145) | K145: =CHOOSE(Controls!$B$6,D1!K145,D2!K145,D3!K145,D4!K145,D5!K145,D6!K145) | L145: =CHOOSE(Controls!$B$6,D1!L145,D2!L145,D3!L145,D4!L145,D5!L145,D6!L145) | ... O145: =CHOOSE(Controls!$B$6,D1!O145,D2!O145,D3!O145,D4!O145,D5!O145,D6!O145)
A146: Amort of prepaid cloud commits (reclass) | B146: MEMO | C146: $M | D146: Reclass memo. NOT added to P&L D&A (guard). | E146: =CHOOSE(Controls!$B$6,D1!E146,D2!E146,D3!E146,D4!E146,D5!E146,D6!E146) | F146: =CHOOSE(Controls!$B$6,D1!F146,D2!F146,D3!F146,D4!F146,D5!F146,D6!F146) | G146: =CHOOSE(Controls!$B$6,D1!G146,D2!G146,D3!G146,D4!G146,D5!G146,D6!G146) | H146: =CHOOSE(Controls!$B$6,D1!H146,D2!H146,D3!H146,D4!H146,D5!H146,D6!H146) | I146: =CHOOSE(Controls!$B$6,D1!I146,D2!I146,D3!I146,D4!I146,D5!I146,D6!I146) | J146: =CHOOSE(Controls!$B$6,D1!J146,D2!J146,D3!J146,D4!J146,D5!J146,D6!J146) | K146: =CHOOSE(Controls!$B$6,D1!K146,D2!K146,D3!K146,D4!K146,D5!K146,D6!K146) | L146: =CHOOSE(Controls!$B$6,D1!L146,D2!L146,D3!L146,D4!L146,D5!L146,D6!L146) | ... O146: =CHOOSE(Controls!$B$6,D1!O146,D2!O146,D3!O146,D4!O146,D5!O146,D6!O146)
A147: Total D&A | B147: CALC | C147: $M | D147: Model amort + owned HW dep (prepaid-cloud excluded). | E147: =CHOOSE(Controls!$B$6,D1!E147,D2!E147,D3!E147,D4!E147,D5!E147,D6!E147) | F147: =CHOOSE(Controls!$B$6,D1!F147,D2!F147,D3!F147,D4!F147,D5!F147,D6!F147) | G147: =CHOOSE(Controls!$B$6,D1!G147,D2!G147,D3!G147,D4!G147,D5!G147,D6!G147) | H147: =CHOOSE(Controls!$B$6,D1!H147,D2!H147,D3!H147,D4!H147,D5!H147,D6!H147) | I147: =CHOOSE(Controls!$B$6,D1!I147,D2!I147,D3!I147,D4!I147,D5!I147,D6!I147) | J147: =CHOOSE(Controls!$B$6,D1!J147,D2!J147,D3!J147,D4!J147,D5!J147,D6!J147) | K147: =CHOOSE(Controls!$B$6,D1!K147,D2!K147,D3!K147,D4!K147,D5!K147,D6!K147) | L147: =CHOOSE(Controls!$B$6,D1!L147,D2!L147,D3!L147,D4!L147,D5!L147,D6!L147) | ... O147: =CHOOSE(Controls!$B$6,D1!O147,D2!O147,D3!O147,D4!O147,D5!O147,D6!O147)
A148: P&L SUMMARY (memo)
A149: Gross profit | B149: CALC | C149: $M | D149: Revenue - cost of revenue. | E149: =CHOOSE(Controls!$B$6,D1!E149,D2!E149,D3!E149,D4!E149,D5!E149,D6!E149) | F149: =CHOOSE(Controls!$B$6,D1!F149,D2!F149,D3!F149,D4!F149,D5!F149,D6!F149) | G149: =CHOOSE(Controls!$B$6,D1!G149,D2!G149,D3!G149,D4!G149,D5!G149,D6!G149) | H149: =CHOOSE(Controls!$B$6,D1!H149,D2!H149,D3!H149,D4!H149,D5!H149,D6!H149) | I149: =CHOOSE(Controls!$B$6,D1!I149,D2!I149,D3!I149,D4!I149,D5!I149,D6!I149) | J149: =CHOOSE(Controls!$B$6,D1!J149,D2!J149,D3!J149,D4!J149,D5!J149,D6!J149) | K149: =CHOOSE(Controls!$B$6,D1!K149,D2!K149,D3!K149,D4!K149,D5!K149,D6!K149) | L149: =CHOOSE(Controls!$B$6,D1!L149,D2!L149,D3!L149,D4!L149,D5!L149,D6!L149) | ... O149: =CHOOSE(Controls!$B$6,D1!O149,D2!O149,D3!O149,D4!O149,D5!O149,D6!O149)
A150: Operating income (ex-SBC) | B150: CALC | C150: $M | D150: GP - R&D - S&M - G&A - D&A. | E150: =CHOOSE(Controls!$B$6,D1!E150,D2!E150,D3!E150,D4!E150,D5!E150,D6!E150) | F150: =CHOOSE(Controls!$B$6,D1!F150,D2!F150,D3!F150,D4!F150,D5!F150,D6!F150) | G150: =CHOOSE(Controls!$B$6,D1!G150,D2!G150,D3!G150,D4!G150,D5!G150,D6!G150) | H150: =CHOOSE(Controls!$B$6,D1!H150,D2!H150,D3!H150,D4!H150,D5!H150,D6!H150) | I150: =CHOOSE(Controls!$B$6,D1!I150,D2!I150,D3!I150,D4!I150,D5!I150,D6!I150) | J150: =CHOOSE(Controls!$B$6,D1!J150,D2!J150,D3!J150,D4!J150,D5!J150,D6!J150) | K150: =CHOOSE(Controls!$B$6,D1!K150,D2!K150,D3!K150,D4!K150,D5!K150,D6!K150) | L150: =CHOOSE(Controls!$B$6,D1!L150,D2!L150,D3!L150,D4!L150,D5!L150,D6!L150) | ... O150: =CHOOSE(Controls!$B$6,D1!O150,D2!O150,D3!O150,D4!O150,D5!O150,D6!O150)
A151: Operating income (incl-SBC) | B151: CALC | C151: $M | D151: After stock-based comp. | E151: =CHOOSE(Controls!$B$6,D1!E151,D2!E151,D3!E151,D4!E151,D5!E151,D6!E151) | F151: =CHOOSE(Controls!$B$6,D1!F151,D2!F151,D3!F151,D4!F151,D5!F151,D6!F151) | G151: =CHOOSE(Controls!$B$6,D1!G151,D2!G151,D3!G151,D4!G151,D5!G151,D6!G151) | H151: =CHOOSE(Controls!$B$6,D1!H151,D2!H151,D3!H151,D4!H151,D5!H151,D6!H151) | I151: =CHOOSE(Controls!$B$6,D1!I151,D2!I151,D3!I151,D4!I151,D5!I151,D6!I151) | J151: =CHOOSE(Controls!$B$6,D1!J151,D2!J151,D3!J151,D4!J151,D5!J151,D6!J151) | K151: =CHOOSE(Controls!$B$6,D1!K151,D2!K151,D3!K151,D4!K151,D5!K151,D6!K151) | L151: =CHOOSE(Controls!$B$6,D1!L151,D2!L151,D3!L151,D4!L151,D5!L151,D6!L151) | ... O151: =CHOOSE(Controls!$B$6,D1!O151,D2!O151,D3!O151,D4!O151,D5!O151,D6!O151)
...

Sheet D1
A1: Base/Run-rate (data block D1)
A2: Line Item | B2: Type | C2: Unit | D2: What it is | E2: 2022 | F2: 2023 | G2: 2024 | H2: 2025 | I2: 2026 | J2: 2027 | K2: 2028 | L2: 2029 | M2: 2030 | N2: 2031 | O2: 2032
A3: REVENUE
A4: Booked revenue | B4: IN | C4: $M | D4: Anchor. 2022-26 PitchBook TTM (10/100/1,000/9,000/47,000); 2027-32 base case. PB carries 55,000 for 2027 as a conservative mark. | E4: 10 | F4: 100 | G4: 1000 | H4: 9000 | I4: 47000 | J4: 80000 | K4: 115000 | L4: 150000 | M4: 185000 | N4: 215000 | O4: 245000
A5: API PRICING AND BLENDED EFFECTIVE RATE
A6: Model mix % - Mythos | B6: IN | C6: % | D6: Token share, flagship tier (Fable 5 / Mythos 5, $10/$50). Introduced 2026. | E6: 0 | F6: 0 | G6: 0 | H6: 0 | I6: 0.03 | J6: 0.05 | K6: 0.06 | L6: 0.07 | M6: 0.08 | N6: 0.09 | O6: 0.1
A7: Model mix % - Opus | B7: IN | C7: % | D7: Token share, Opus ($15/$75 to Aug-2025, cut to $5/$25 at Opus 4.5). | E7: 0 | F7: 0.1 | G7: 0.08 | H7: 0.1 | I7: 0.12 | J7: 0.12 | K7: 0.12 | L7: 0.12 | M7: 0.12 | N7: 0.12 | O7: 0.12
A8: Model mix % - Sonnet | B8: IN | C8: % | D8: Token share, Sonnet workhorse ($3/$15). | E8: 0.4 | F8: 0.3 | G8: 0.32 | H8: 0.45 | I8: 0.45 | J8: 0.44 | K8: 0.43 | L8: 0.42 | M8: 0.41 | N8: 0.4 | O8: 0.4
A9: Model mix % - Haiku | B9: IN | C9: % | D9: Token share, Haiku ($0.25/$1.25 -> $1/$5). | E9: 0.6 | F9: 0.6 | G9: 0.6 | H9: 0.45 | I9: 0.4 | J9: 0.39 | K9: 0.39 | L9: 0.39 | M9: 0.39 | N9: 0.39 | O9: 0.38
A10: List input $/Mtok - Mythos | B10: IN | C10: $ | D10: List input price, flagship. | E10: 15 | F10: 15 | G10: 15 | H10: 15 | I10: 15 | J10: 15 | K10: 14 | L10: 13 | M10: 12 | N10: 12 | O10: 11
A11: List input $/Mtok - Opus | B11: IN | C11: $ | D11: List input price, Opus. | E11: 11 | F11: 8 | G11: 15 | H11: 15 | I11: 5 | J11: 5 | K11: 5 | L11: 4.5 | M11: 4.5 | N11: 4 | O11: 4
A12: List input $/Mtok - Sonnet | B12: IN | C12: $ | D12: List input price, Sonnet. | E12: 3 | F12: 3 | G12: 3 | H12: 3 | I12: 3 | J12: 3 | K12: 3 | L12: 2.5 | M12: 2.5 | N12: 2 | O12: 2
A13: List input $/Mtok - Haiku | B13: IN | C13: $ | D13: List input price, Haiku. | E13: 0.8 | F13: 0.8 | G13: 0.25 | H13: 0.8 | I13: 1 | J13: 1 | K13: 1 | L13: 0.9 | M13: 0.9 | N13: 0.8 | O13: 0.8
A14: List output $/Mtok - Mythos | B14: IN | C14: $ | D14: List output price, flagship. | E14: 75 | F14: 75 | G14: 75 | H14: 75 | I14: 75 | J14: 70 | K14: 65 | L14: 60 | M14: 55 | N14: 55 | O14: 50
A15: List output $/Mtok - Opus | B15: IN | C15: $ | D15: List output price, Opus. | E15: 33 | F15: 24 | G15: 75 | H15: 75 | I15: 25 | J15: 25 | K15: 22 | L15: 22 | M15: 20 | N15: 20 | O15: 18
A16: List output $/Mtok - Sonnet | B16: IN | C16: $ | D16: List output price, Sonnet. | E16: 15 | F16: 15 | G16: 15 | H16: 15 | I16: 15 | J16: 15 | K16: 13 | L16: 13 | M16: 12 | N16: 10 | O16: 10
A17: List output $/Mtok - Haiku | B17: IN | C17: $ | D17: List output price, Haiku. | E17: 2.4 | F17: 2.4 | G17: 1.25 | H17: 4 | I17: 5 | J17: 5 | K17: 4.5 | L17: 4.5 | M17: 4 | N17: 4 | O17: 3.6
... A27: Blended effective $/Mtok | B27: CALC | C27: $ | D27: Mix-weighted, adjusted for input share, caching, batch. | E27: 2.9806452 | F27: 3.4768421 | G27: 3.793749 | H27: 4.1467112 | I27: 3.0571739 | J27: 2.9587834 | K27: 2.6527823 | L27: 2.3780343 | M27: 2.2407352 | N27: 2.0581018 | O27: 1.9921081
A28: NON-API REVENUE STREAMS
A29: # Enterprise contracts (>$1M ARR) | B29: IN | C29: count | D29: ~1,000+ at $1M+ ACV by 2026. | E29: 0 | F29: 5 | G29: 60 | H29: 300 | I29: 1000 | J29: 1700 | K29: 2400 | L29: 3100 | M29: 3700 | N29: 4200 | O29: 4600
A30: Committed-use discount % (memo) | B30: IN | C30: % | D30: Volume discount realized on enterprise API. | E30: 0 | F30: 0.05 | G30: 0.1 | H30: 0.12 | I30: 0.15 | J30: 0.15 | K30: 0.16 | L30: 0.16 | M30: 0.17 | N30: 0.17 | O30: 0.18
A31: Active enterprise dashboard seats | B31: IN | C31: count | D31: Console/admin seats. | E31: 0 | F31: 2000 | G31: 40000 | H31: 250000 | I31: 900000 | J31: 1600000 | K31: 2300000 | L31: 3000000 | M31: 3600000 | N31: 4100000 | O31: 4500000
A32: Enterprise platform fee / seat / mo | B32: IN | C32: $ | D32: Monthly platform fee per seat. | E32: 0 | F32: 30 | G32: 35 | H32: 40 | I32: 45 | J32: 48 | K32: 50 | L32: 52 | M32: 54 | N32: 55 | O32: 56
A33: Enterprise seat revenue | B33: CALC | C33: $M | D33: seats x fee x 12. | E33: 0 | F33: 0.72 | G33: 16.8 | H33: 120 | I33: 486 | J33: 921.6 | K33: 1380 | L33: 1872 | M33: 2332.8 | N33: 2706 | O33: 3024
A34: Consumer subscription revenue (anchor) | B34: IN | C34: $M | D34: Claude Pro ($20) + Max ($100/$200). | E34: 0 | F34: 8 | G34: 120 | H34: 1300 | I34: 6600 | J34: 11200 | K34: 16100 | L34: 21000 | M34: 25900 | N34: 30100 | O34: 34300
A35: Blended consumer ARPU ($/mo) | B35: IN | C35: $ | D35: Blend of Pro and Max. | E35: 20 | F35: 20 | G35: 21 | H35: 23 | I35: 26 | J35: 28 | K35: 29 | L35: 30 | M35: 31 | N35: 32 | O35: 33
A36: Paying consumer subs (implied) | B36: PLUG | C36: Count | D36: consumer rev / (ARPU x 12). | E36: 0 | F36: 33333.333 | G36: 476190.48 | H36: 4710144.9 | I36: 21153846 | J36: 33333333 | K36: 46264368 | L36: 58333333 | M36: 69623656 | N36: 78385417 | O36: 86616162
A37: Active developer seats | B37: IN | C37: Count | D37: Claude Code seats (Feb-2025). | E37: 0 | F37: 0 | G37: 0 | H37: 350000 | I37: 1100000 | J37: 1800000 | K37: 2500000 | L37: 3100000 | M37: 3600000 | N37: 4000000 | O37: 4300000
A38: Base seat fee ($/mo) | B38: IN | C38: $ | D38: Claude Code base seat fee. | E38: 0 | F38: 0 | G38: 0 | H38: 20 | I38: 22 | J38: 24 | K38: 25 | L38: 26 | M38: 27 | N38: 28 | O38: 28
A39: Claude Code base seat revenue | B39: CALC | C39: $M | D39: seats x fee x 12. | E39: 0 | F39: 0 | G39: 0 | H39: 84 | I39: 290.4 | J39: 518.4 | K39: 750 | L39: 967.2 | M39: 1166.4 | N39: 1344 | O39: 1444.8
A40: Avg overage tokens / dev / mo | B40: IN | C40: Mtok | D40: Usage above base seat. | E40: 0 | F40: 0 | G40: 0 | H40: 12 | I40: 20 | J40: 26 | K40: 30 | L40: 33 | M40: 36 | N40: 38 | O40: 40
... A60: Total non-API revenue | B60: CALC | C60: $M | D60: Sum of non-API streams. | E60: 0 | F60: 17.72 | G60: 300.115 | H60: 3188.7792 | I60: 13998.754 | J60: 23319.133 | K60: 32789.275 | L60: 41925.307 | M60: 50563.131 | N60: 57976.56 | O60: 64889.009
A61: FIRST PARTY DIRECT API REVENUE
A62: First-party API revenue | B62: PLUG | C62: $M | D62: Booked revenue minus non-API streams. | E62: 10 | F62: 82.28 | G62: 699.885 | H62: 5811.2208 | I62: 33001.246 | J62: 56680.867 | K62: 82210.725 | L62: 108074.69 | M62: 134436.87 | N62: 157023.44 | O62: 180110.99
A63: API TOKEN ENGINE
A64: Total tokens processed (all) | B64: PLUG | C64: T | D64: API revenue / blended $/Mtok (trillions). | E64: 3.3549784 | F64: 23.665153 | G64: 184.48374 | H64: 1401.4047 | I64: 10794.69 | J64: 19156.816 | K64: 30990.377 | L64: 45447.071 | M64: 59996.768 | N64: 76295.274 | O64: 90412.257
A65: Total input tokens | B65: CALC | C65: T | D65: tokens x input share. | E65: 2.5974026 | F65: 18.683015 | G65: 151.21618 | H65: 1208.1075 | I65: 9386.6874 | J65: 16857.998 | K65: 27459.828 | L65: 40663.169 | M65: 53770.689 | N65: 68470.117 | O65: 81229.762
A66: Total output tokens | B66: CALC | C66: T | D66: tokens x (1 - input share). | E66: 0.75757576 | F66: 4.9821375 | G66: 33.26756 | H66: 193.29721 | I66: 1408.0031 | J66: 2298.8179 | K66: 3530.5493 | L66: 4783.9022 | M66: 6226.0797 | N66: 7825.1563 | O66: 9182.4948
A67: Total first-party API calls | B67: CALC | C67: B | D67: tokens / tokens-per-call (billions). | E67: 2.1645022 | F67: 12.455344 | G67: 60.486472 | H67: 241.62151 | I67: 1173.3359 | J67: 1532.5452 | K67: 1961.4163 | L67: 2391.9511 | M67: 2830.0362 | N67: 3260.4818 | O67: 3531.7288
A68: Memo: calls / contract / day | B68: CALC | C68: # | D68: calls / contracts / 365. | E68: 5930142.9 | F68: 6824845.8 | G68: 2761939.4 | H68: 2206589.1 | I68: 3214619 | J68: 2469855.4 | K68: 2239059.7 | L68: 2113964.8 | M68: 2095547 | N68: 2126863.5 | O68: 2103471.6
A69: COSTS - Inference and infrastructure
A70: Billed tokens (Anthropic-served) | B70: LINK | C70: T | D70: API + consumer + Claude Code (excl Bedrock/Vertex). | E70: 3.3549784 | F70: 23.685153 | G70: 184.88374 | H70: 1457.8047 | I70: 11092.69 | J70: 19780.416 | K70: 31982.377 | L70: 46796.671 | M70: 61701.968 | N70: 78295.274 | O70: 92676.257
A71: Free-tier tokens served | B71: IN | C71: T | D71: Non-billed free-tier usage. | E71: 1.6774892 | F71: 10.658319 | G71: 73.953496 | H71: 510.23166 | I71: 3327.8071 | J71: 5538.5164 | K71: 8315.4181 | L71: 11699.168 | M71: 14808.472 | N71: 18007.913 | O71: 20388.776
A72: Internal / testing tokens | B72: IN | C72: T | D72: Evals/red-team/internal. | E72: 1.0064935 | F72: 5.9212882 | G72: 36.976748 | H72: 218.67071 | I72: 1331.1229 | J72: 2175.8457 | K72: 3198.2377 | L72: 4679.6671 | M72: 5553.1772 | N72: 7046.5746 | O72: 7414.1005
A73: Gross tokens served | B73: CALC | C73: T | D73: billed + free + internal. | E73: 6.038961 | F73: 40.26476 | G73: 295.81398 | H73: 2186.7071 | I73: 15751.62 | J73: 27494.778 | K73: 43496.033 | L73: 63175.506 | M73: 82063.618 | N73: 103349.76 | O73: 120479.13
A74: Tokens per GPU-hour | B74: IN | C74: tok/hr | D74: Serving throughput (back-solved for consistency). | E74: 3358566.6 | F74: 3155545.4 | G74: 2862716 | H74: 2822349.3 | I74: 4051153.3 | J74: 4176724 | K74: 4555605.6 | L74: 5105091.4 | M74: 5419767.5 | N74: 5930671.9 | O74: 6138599.2
A75: Required GPU-hours | B75: CALC | C75: hr | D75: gross tokens / tokens-per-GPU-hour. | E75: 1798076.9 | F75: 12760000 | G75: 1.0333333e+08 | H75: 7.7478261e+08 | I75: 3.8881818e+09 | J75: 6.5828571e+09 | K75: 9.5478049e+09 | L75: 12375000000 | M75: 1.5141538e+10 | N75: 1.7426316e+10 | O75: 1.9626486e+10
A76: Fleet utilization % | B76: IN | C76: % | D76: Effective serving utilization. | E76: 0.55 | F76: 0.58 | G76: 0.62 | H76: 0.66 | I76: 0.7 | J76: 0.72 | K76: 0.74 | L76: 0.75 | M76: 0.76 | N76: 0.77 | O76: 0.78
A77: Total provisioned GPU-hours | B77: CALC | C77: hr | D77: required / utilization. | E77: 3269230.8 | F77: 22000000 | G77: 1.6666667e+08 | H77: 1.173913e+09 | I77: 5.5545455e+09 | J77: 9.1428571e+09 | K77: 1.2902439e+10 | L77: 16500000000 | M77: 1.9923077e+10 | N77: 2.2631579e+10 | O77: 2.5162162e+10
A78: Blended $/GPU-hour | B78: IN | C78: $ | D78: Owned + rented all-in hourly cost. | E78: 2.6 | F78: 2.5 | G78: 2.4 | H78: 2.3 | I78: 2.2 | J78: 2.1 | K78: 2.05 | L78: 2 | M78: 1.95 | N78: 1.9 | O78: 1.85
A79: Inference compute cost | B79: CALC | C79: $M | D79: Declining share of revenue; GPU-hrs x $/GPU-hr. | E79: 8.5 | F79: 55 | G79: 400 | H79: 2700 | I79: 12220 | J79: 19200 | K79: 26450 | L79: 33000 | M79: 38850 | N79: 43000 | O79: 46550
A80: Data egress volume (PB) | B80: IN | C80: PB | D80: Outbound data volume. | E80: 0.5 | F80: 3 | G80: 20 | H80: 120 | I80: 480 | J80: 800 | K80: 1150 | L80: 1500 | M80: 1850 | N80: 2150 | O80: 2450
A81: Egress cost ($/TB) | B81: IN | C81: $ | D81: Blended egress unit cost. | E81: 20 | F81: 18 | G81: 16 | H81: 14 | I81: 12 | J81: 11 | K81: 10 | L81: 9 | M81: 9 | N81: 8 | O81: 8
... A84: API gateway and load-balancing | B84: IN | C84: $M | D84: Edge/gateway/LB. | E84: 0.3 | F84: 2 | G84: 10 | H84: 55 | I84: 200 | J84: 320 | K84: 440 | L84: 560 | M84: 680 | N84: 780 | O84: 880
A85: COSTS - SAFETY, PAYMENTS, SUPPORT
A86: Content moderation cost $/Mtok | B86: IN | C86: $ | D86: Classifier cost per Mtok gross. | E86: 0.05 | F86: 0.05 | G86: 0.04 | H86: 0.035 | I86: 0.03 | J86: 0.028 | K86: 0.026 | L86: 0.025 | M86: 0.024 | N86: 0.023 | O86: 0.022
A87: Automated moderation cost | B87: CALC | C87: $M | D87: gross tokens x $/Mtok. | E87: 0.30194805 | F87: 2.013238 | G87: 11.832559 | H87: 76.534749 | I87: 472.54861 | J87: 769.85378 | K87: 1130.8969 | L87: 1579.3877 | M87: 1969.5268 | N87: 2377.0445 | O87: 2650.5409
A88: HITL review volume | B88: IN | C88: Count | D88: Human safety reviews / yr. | E88: 20000 | F88: 120000 | G88: 700000 | H88: 3500000 | I88: 12000000 | J88: 19000000 | K88: 26000000 | L88: 33000000 | M88: 39000000 | N88: 44000000 | O88: 48000000
A89: Cost per HITL review | B89: IN | C89: $ | D89: BPO hourly x hours. | E89: 4 | F89: 4 | G89: 3.8 | H89: 3.6 | I89: 3.5 | J89: 3.4 | K89: 3.3 | L89: 3.2 | M89: 3.2 | N89: 3.1 | O89: 3
A90: HITL review cost | B90: CALC | C90: $M | D90: volume x cost. | E90: 0.08 | F90: 0.48 | G90: 2.66 | H90: 12.6 | I90: 42 | J90: 64.6 | K90: 85.8 | L90: 105.6 | M90: 124.8 | N90: 136.4 | O90: 144
A91: B2B gross cash collections | B91: LINK | C91: $M | D91: API + seats + CC + FT + PT + PS. | E91: 10 | F91: 84.8 | G91: 747.9 | H91: 6424 | I91: 35342 | J91: 61142 | K91: 88720 | L91: 116478 | M91: 144676 | N91: 168647 | O91: 193038
A92: Payment processing fee % (Stripe) | B92: IN | C92: % | D92: Blended processor fee. | E92: 0.029 | F92: 0.028 | G92: 0.027 | H92: 0.026 | I92: 0.025 | J92: 0.024 | K92: 0.024 | L92: 0.023 | M92: 0.023 | N92: 0.022 | O92: 0.022
A93: B2B payment processing cost | B93: CALC | C93: $M | D93: collections x fee. | E93: 0.29 | F93: 2.3744 | G93: 20.1933 | H93: 167.024 | I93: 883.55 | J93: 1467.408 | K93: 2129.28 | L93: 2678.994 | M93: 3327.548 | N93: 3710.234 | O93: 4246.836
A94: Mobile share of consumer revenue % | B94: IN | C94: % | D94: Consumer via mobile stores. | E94: 0 | F94: 0.2 | G94: 0.3 | H94: 0.35 | I94: 0.38 | J94: 0.4 | K94: 0.4 | L94: 0.4 | M94: 0.39 | N94: 0.39 | O94: 0.38
A95: B2C mobile collections | B95: CALC | C95: $M | D95: consumer rev x mobile share. | E95: 0 | F95: 1.6 | G95: 36 | H95: 455 | I95: 2508 | J95: 4480 | K95: 6440 | L95: 8400 | M95: 10101 | N95: 11739 | O95: 13034
A96: App store take-rate % | B96: IN | C96: % | D96: Apple/Google store take. | E96: 0 | F96: 0.3 | G96: 0.3 | H96: 0.28 | I96: 0.2 | J96: 0.2 | K96: 0.18 | L96: 0.18 | M96: 0.17 | N96: 0.17 | O96: 0.15
A97: App store cost | B97: CALC | C97: $M | D97: mobile collections x take. | E97: 0 | F97: 0.48 | G97: 10.8 | H97: 127.4 | I97: 501.6 | J97: 896 | K97: 1159.2 | L97: 1512 | M97: 1717.17 | N97: 1995.63 | O97: 1955.1
... A106: Memo: implied gross margin % | B106: CALC | C106: % | D106: Inference-only gross margin. | E106: 0.030605195 | F106: 0.36418362 | G106: 0.53679914 | H106: 0.64648458 | I106: 0.69225194 | J106: 0.71317646 | K106: 0.72429775 | L106: 0.73448534 | M106: 0.74519012 | N106: 0.75564615 | O106: 0.76722654
A107: OpEx & Comp (ex-SBC)
A108: R&D headcount | B108: IN | C108: count | D108: Research + eng (~65-75% of total). | E108: 40 | F108: 130 | G108: 270 | H108: 700 | I108: 3250 | J108: 4800 | K108: 6000 | L108: 6900 | M108: 7500 | N108: 7900 | O108: 8300
A109: Fully-burdened R&D cash comp ($/head) | B109: IN | C109: $ | D109: Levels.fyi eng $619-841k, research ~$746k median. | E109: 400000 | F109: 420000 | G109: 450000 | H109: 480000 | I109: 520000 | J109: 545000 | K109: 565000 | L109: 580000 | M109: 595000 | N109: 605000 | O109: 615000
A110: R&D personnel cost | B110: CALC | C110: $M | D110: heads x comp. | E110: 16 | F110: 54.6 | G110: 121.5 | H110: 336 | I110: 1690 | J110: 2616 | K110: 3390 | L110: 4002 | M110: 4462.5 | N110: 4779.5 | O110: 5104.5
A111: RLHF & data annotation | B111: IN | C111: $M | D111: Human feedback/annotation. | E111: 2 | F111: 8 | G111: 60 | H111: 300 | I111: 620 | J111: 900 | K111: 1150 | L111: 1400 | M111: 1600 | N111: 1750 | O111: 1900
A112: Proprietary data licensing | B112: IN | C112: $M | D112: Licensed training data. | E112: 0 | F112: 3 | G112: 25 | H112: 120 | I112: 400 | J112: 620 | K112: 820 | L112: 1000 | M112: 1150 | N112: 1280 | O112: 1400
A113: Experimental / failed training runs | B113: IN | C113: $M | D113: Abandoned run compute. | E113: 3 | F113: 12 | G113: 90 | H113: 380 | I113: 620 | J113: 850 | K113: 1050 | L113: 1250 | M113: 1400 | N113: 1520 | O113: 1650
A114: Internal tooling & subscriptions | B114: IN | C114: $M | D114: Dev tooling/SaaS. | E114: 1 | F114: 4 | G114: 30 | H114: 150 | I114: 380 | J114: 560 | K114: 720 | L114: 880 | M114: 1010 | N114: 1130 | O114: 1240
A115: Capitalizable frontier-training runs | B115: IN | C115: $M | D115: Capitalizable portion (~30% of training). | E115: 10.5 | F115: 36 | G115: 1050 | H115: 1215 | I115: 6063 | J115: 8400 | K115: 10350 | L115: 11700 | M115: 12765 | N115: 13545 | O115: 13965
A116: Cap toggle (1=capitalized, 0=ASC 730 expense) | B116: IN | C116: 0/1 | D116: 0 = expense training to R&D (base). | E116: 0 | F116: 0 | G116: 0 | H116: 0 | I116: 0 | J116: 0 | K116: 0 | L116: 0 | M116: 0 | N116: 0 | O116: 0
A117: Training compute expenses to R&D | B117: CALC | C117: $M | D117: Training (expensed) + research compute. Primary loss driver. | E117: 41 | F117: 145 | G117: 4050 | H117: 4950 | I117: 24440 | J117: 34400 | K117: 42550 | L117: 48000 | M117: 52725 | N117: 55900 | O117: 57575
A118: Total R&D (ex-SBC) | B118: CALC | C118: $M | D118: Personnel + RLHF + licensing + failed + tooling + training. | E118: 63 | F118: 226.6 | G118: 4376.5 | H118: 6236 | I118: 28150 | J118: 39946 | K118: 49680 | L118: 56532 | M118: 62347.5 | N118: 66359.5 | O118: 68869.5
A119: S&M Headcount | B119: IN | C119: count | D119: GTM heads (small org). | E119: 8 | F119: 30 | G119: 70 | H119: 180 | I119: 900 | J119: 1450 | K119: 1900 | L119: 2250 | M119: 2500 | N119: 2700 | O119: 2850
... A133: One-time litigation services | B133: IN | C133: $M | D133: Non-recurring litigation. | E133: 0 | F133: 0 | G133: 5 | H133: 40 | I133: 150 | J133: 90 | K133: 60 | L133: 50 | M133: 45 | N133: 40 | O133: 40
A134: STOCK BASED COMP
A135: SBC issue rate (% of base cash comp) | B135: IN | C135: % | D135: RSU grant value as % of cash comp. | E135: 0.4 | F135: 0.45 | G135: 0.5 | H135: 0.55 | I135: 0.55 | J135: 0.5 | K135: 0.45 | L135: 0.42 | M135: 0.4 | N135: 0.38 | O135: 0.36
A136: R&D SBC | B136: CALC | C136: $M | D136: R&D cash x SBC rate. | E136: 6.4 | F136: 24.57 | G136: 60.75 | H136: 184.8 | I136: 929.5 | J136: 1308 | K136: 1525.5 | L136: 1680.84 | M136: 1785 | N136: 1816.21 | O136: 1837.62
A137: S&M SBC | B137: CALC | C137: $M | D137: S&M cash x SBC rate. | E137: 0.896 | F137: 3.915 | G137: 10.5 | H137: 30.69 | I137: 158.4 | J137: 239.25 | K137: 290.7 | L137: 330.75 | M137: 358 | N137: 374.49 | O137: 381.672
A138: G&A SBC | B138: CALC | C138: $M | D138: G&A cash x SBC rate. | E138: 1.248 | F138: 3.888 | G138: 8.4 | H138: 27.115 | I138: 140.25 | J138: 192.5 | K138: 226.8 | L138: 250.194 | M138: 262.4 | N138: 279.224 | O138: 287.64
A139: Total SBC | B139: CALC | C139: $M | D139: Sum of function SBC. | E139: 8.544 | F139: 32.373 | G139: 79.65 | H139: 242.605 | I139: 1228.15 | J139: 1739.75 | K139: 2043 | L139: 2261.784 | M139: 2405.4 | N139: 2469.924 | O139: 2506.932
A140: DEPRECIATION & AMORTIZATION
A141: Amort life - models (yrs) | B141: IN | C141: yr | D141: Life of capitalized models. | E141: 2 | F141: 2 | G141: 2 | H141: 2 | I141: 2 | J141: 2 | K141: 2 | L141: 2 | M141: 2 | N141: 2 | O141: 2
A142: Amort of capitalized frontier models | B142: CALC | C142: $M | D142: 2-yr straight-line of cap pool. | E142: 5.25 | F142: 23.25 | G142: 543 | H142: 1132.5 | I142: 3639 | J142: 7231.5 | K142: 9375 | L142: 11025 | M142: 12232.5 | N142: 13155 | O142: 13755
A143: Owned GPU / datacenter capex | B143: IN | C143: $M | D143: Owned hardware capex (Fluidstack $50B ramps 2026+). | E143: 2 | F143: 8 | G143: 40 | H143: 220 | I143: 1400 | J143: 3200 | K143: 5000 | L143: 6500 | M143: 7500 | N143: 8200 | O143: 8800
A144: Depreciation life - HW (yrs) | B144: IN | C144: yr | D144: Life of owned accelerators. | E144: 4 | F144: 4 | G144: 4 | H144: 5 | I144: 5 | J144: 5 | K144: 6 | L144: 6 | M144: 6 | N144: 6 | O144: 6
A145: Depreciation of owned GPU / datacenter | B145: CALC | C145: $M | D145: Vintage straight-line depreciation. | E145: 0.5 | F145: 2.5 | G145: 12.5 | H145: 56.5 | I145: 336 | J145: 974 | K145: 1797.3333 | L145: 2880.6667 | M145: 4086.6667 | N145: 5173.3333 | O145: 6000
A146: Amort of prepaid cloud commits (reclass) | B146: MEMO | C146: $M | D146: Reclass memo. NOT added to P&L D&A (guard). | E146: 0 | F146: 0 | G146: 20 | H146: 120 | I146: 500 | J146: 800 | K146: 1050 | L146: 1300 | M146: 1500 | N146: 1650 | O146: 1800
A147: Total D&A | B147: CALC | C147: $M | D147: Model amort + owned HW dep (prepaid-cloud excluded). | E147: 5.75 | F147: 25.75 | G147: 555.5 | H147: 1189 | I147: 3975 | J147: 8205.5 | K147: 11172.333 | L147: 13905.667 | M147: 16319.167 | N147: 18328.333 | O147: 19755
A148: P&L SUMMARY (memo)
A149: Gross profit | B149: CALC | C149: $M | D149: Revenue - cost of revenue. | E149: 0.30605195 | F149: 36.418362 | G149: 536.79914 | H149: 5818.3613 | I149: 32535.841 | J149: 57054.117 | K149: 83294.241 | L149: 110172.8 | M149: 137860.17 | N149: 162463.92 | O149: 187970.5
A150: Operating income (ex-SBC) | B150: CALC | C150: $M | D150: GP - R&D - S&M - G&A - D&A. | E150: -75.803948 | F150: -244.27164 | G150: -4514.0009 | H150: -2191.7387 | I150: -1922.1586 | J150: 5269.117 | K150: 17741.907 | L150: 34081.934 | M150: 52737.505 | N150: 70598.788 | O150: 91561.802
A151: Operating income (incl-SBC) | B151: CALC | C151: $M | D151: After stock-based comp. | E151: -84.347948 | F151: -276.64464 | G151: -4593.6509 | H151: -2434.3437 | I151: -3150.3086 | J151: 3529.367 | K151: 15698.907 | L151: 31820.15 | M151: 50332.105 | N151: 68128.864 | O151: 89054.87
...

Sheet D2
A1: Base/Recognized (data block D2)
A2: Line Item | B2: Type | C2: Unit | D2: What it is | E2: 2022 | F2: 2023 | G2: 2024 | H2: 2025 | I2: 2026 | J2: 2027 | K2: 2028 | L2: 2029 | M2: 2030 | N2: 2031 | O2: 2032
A3: REVENUE
A4: Booked revenue | B4: IN | C4: $M | D4: Anchor. 2022-26 PitchBook TTM (10/100/1,000/9,000/47,000); 2027-32 base case. PB carries 55,000 for 2027 as a conservative mark. | E4: 10 | F4: 85 | G4: 600 | H4: 4680 | I4: 23500 | J4: 49600 | K4: 82800 | L4: 120000 | M4: 157250 | N4: 189200 | O4: 220500
A5: API PRICING AND BLENDED EFFECTIVE RATE
A6: Model mix % - Mythos | B6: IN | C6: % | D6: Token share, flagship tier (Fable 5 / Mythos 5, $10/$50). Introduced 2026. | E6: 0 | F6: 0 | G6: 0 | H6: 0 | I6: 0.03 | J6: 0.05 | K6: 0.06 | L6: 0.07 | M6: 0.08 | N6: 0.09 | O6: 0.1
A7: Model mix % - Opus | B7: IN | C7: % | D7: Token share, Opus ($15/$75 to Aug-2025, cut to $5/$25 at Opus 4.5). | E7: 0 | F7: 0.1 | G7: 0.08 | H7: 0.1 | I7: 0.12 | J7: 0.12 | K7: 0.12 | L7: 0.12 | M7: 0.12 | N7: 0.12 | O7: 0.12
A8: Model mix % - Sonnet | B8: IN | C8: % | D8: Token share, Sonnet workhorse ($3/$15). | E8: 0.4 | F8: 0.3 | G8: 0.32 | H8: 0.45 | I8: 0.45 | J8: 0.44 | K8: 0.43 | L8: 0.42 | M8: 0.41 | N8: 0.4 | O8: 0.4
A9: Model mix % - Haiku | B9: IN | C9: % | D9: Token share, Haiku ($0.25/$1.25 -> $1/$5). | E9: 0.6 | F9: 0.6 | G9: 0.6 | H9: 0.45 | I9: 0.4 | J9: 0.39 | K9: 0.39 | L9: 0.39 | M9: 0.39 | N9: 0.39 | O9: 0.38
A10: List input $/Mtok - Mythos | B10: IN | C10: $ | D10: List input price, flagship. | E10: 15 | F10: 15 | G10: 15 | H10: 15 | I10: 15 | J10: 15 | K10: 14 | L10: 13 | M10: 12 | N10: 12 | O10: 11
A11: List input $/Mtok - Opus | B11: IN | C11: $ | D11: List input price, Opus. | E11: 11 | F11: 8 | G11: 15 | H11: 15 | I11: 5 | J11: 5 | K11: 5 | L11: 4.5 | M11: 4.5 | N11: 4 | O11: 4
A12: List input $/Mtok - Sonnet | B12: IN | C12: $ | D12: List input price, Sonnet. | E12: 3 | F12: 3 | G12: 3 | H12: 3 | I12: 3 | J12: 3 | K12: 3 | L12: 2.5 | M12: 2.5 | N12: 2 | O12: 2
A13: List input $/Mtok - Haiku | B13: IN | C13: $ | D13: List input price, Haiku. | E13: 0.8 | F13: 0.8 | G13: 0.25 | H13: 0.8 | I13: 1 | J13: 1 | K13: 1 | L13: 0.9 | M13: 0.9 | N13: 0.8 | O13: 0.8
A14: List output $/Mtok - Mythos | B14: IN | C14: $ | D14: List output price, flagship. | E14: 75 | F14: 75 | G14: 75 | H14: 75 | I14: 75 | J14: 70 | K14: 65 | L14: 60 | M14: 55 | N14: 55 | O14: 50
A15: List output $/Mtok - Opus | B15: IN | C15: $ | D15: List output price, Opus. | E15: 33 | F15: 24 | G15: 75 | H15: 75 | I15: 25 | J15: 25 | K15: 22 | L15: 22 | M15: 20 | N15: 20 | O15: 18
A16: List output $/Mtok - Sonnet | B16: IN | C16: $ | D16: List output price, Sonnet. | E16: 15 | F16: 15 | G16: 15 | H16: 15 | I16: 15 | J16: 15 | K16: 13 | L16: 13 | M16: 12 | N16: 10 | O16: 10
A17: List output $/Mtok - Haiku | B17: IN | C17: $ | D17: List output price, Haiku. | E17: 2.4 | F17: 2.4 | G17: 1.25 | H17: 4 | I17: 5 | J17: 5 | K17: 4.5 | L17: 4.5 | M17: 4 | N17: 4 | O17: 3.6
... A27: Blended effective $/Mtok | B27: CALC | C27: $ | D27: Mix-weighted, adjusted for input share, caching, batch. | E27: 2.9806452 | F27: 3.4768421 | G27: 3.793749 | H27: 4.1467112 | I27: 3.0571739 | J27: 2.9587834 | K27: 2.6527823 | L27: 2.3780343 | M27: 2.2407352 | N27: 2.0581018 | O27: 1.9921081
A28: NON-API REVENUE STREAMS
A29: # Enterprise contracts (>$1M ARR) | B29: IN | C29: count | D29: ~1,000+ at $1M+ ACV by 2026. | E29: 0 | F29: 4.25 | G29: 36 | H29: 156 | I29: 500 | J29: 1054 | K29: 1728 | L29: 2480 | M29: 3145 | N29: 3696 | O29: 4140
A30: Committed-use discount % (memo) | B30: IN | C30: % | D30: Volume discount realized on enterprise API. | E30: 0 | F30: 0.05 | G30: 0.1 | H30: 0.12 | I30: 0.15 | J30: 0.15 | K30: 0.16 | L30: 0.16 | M30: 0.17 | N30: 0.17 | O30: 0.18
A31: Active enterprise dashboard seats | B31: IN | C31: count | D31: Console/admin seats. | E31: 0 | F31: 1700 | G31: 24000 | H31: 130000 | I31: 450000 | J31: 992000 | K31: 1656000 | L31: 2400000 | M31: 3060000 | N31: 3608000 | O31: 4050000
A32: Enterprise platform fee / seat / mo | B32: IN | C32: $ | D32: Monthly platform fee per seat. | E32: 0 | F32: 30 | G32: 35 | H32: 40 | I32: 45 | J32: 48 | K32: 50 | L32: 52 | M32: 54 | N32: 55 | O32: 56
A33: Enterprise seat revenue | B33: CALC | C33: $M | D33: seats x fee x 12. | E33: 0 | F33: 0.612 | G33: 10.08 | H33: 62.4 | I33: 243 | J33: 571.392 | K33: 993.6 | L33: 1497.6 | M33: 1982.88 | N33: 2381.28 | O33: 2721.6
A34: Consumer subscription revenue (anchor) | B34: IN | C34: $M | D34: Claude Pro ($20) + Max ($100/$200). | E34: 0 | F34: 6.8 | G34: 72 | H34: 676 | I34: 3300 | J34: 6944 | K34: 11592 | L34: 16800 | M34: 22015 | N34: 26488 | O34: 30870
A35: Blended consumer ARPU ($/mo) | B35: IN | C35: $ | D35: Blend of Pro and Max. | E35: 20 | F35: 20 | G35: 21 | H35: 23 | I35: 26 | J35: 28 | K35: 29 | L35: 30 | M35: 31 | N35: 32 | O35: 33
A36: Paying consumer subs (implied) | B36: PLUG | C36: Count | D36: consumer rev / (ARPU x 12). | E36: 0 | F36: 28333.333 | G36: 285714.29 | H36: 2449275.4 | I36: 10576923 | J36: 20666667 | K36: 33310345 | L36: 46666667 | M36: 59180108 | N36: 68979167 | O36: 77954545
A37: Active developer seats | B37: IN | C37: Count | D37: Claude Code seats (Feb-2025). | E37: 0 | F37: 0 | G37: 0 | H37: 182000 | I37: 550000 | J37: 1116000 | K37: 1800000 | L37: 2480000 | M37: 3060000 | N37: 3520000 | O37: 3870000
A38: Base seat fee ($/mo) | B38: IN | C38: $ | D38: Claude Code base seat fee. | E38: 0 | F38: 0 | G38: 0 | H38: 20 | I38: 22 | J38: 24 | K38: 25 | L38: 26 | M38: 27 | N38: 28 | O38: 28
A39: Claude Code base seat revenue | B39: CALC | C39: $M | D39: seats x fee x 12. | E39: 0 | F39: 0 | G39: 0 | H39: 43.68 | I39: 145.2 | J39: 321.408 | K39: 540 | L39: 773.76 | M39: 991.44 | N39: 1182.72 | O39: 1300.32
A40: Avg overage tokens / dev / mo | B40: IN | C40: Mtok | D40: Usage above base seat. | E40: 0 | F40: 0 | G40: 0 | H40: 12 | I40: 20 | J40: 26 | K40: 30 | L40: 33 | M40: 36 | N40: 38 | O40: 40
... A60: Total non-API revenue | B60: CALC | C60: $M | D60: Sum of non-API streams. | E60: 0 | F60: 15.062 | G60: 180.069 | H60: 1658.1352 | I60: 6999.323 | J60: 14458.798 | K60: 23609.622 | L60: 33541.679 | M60: 42979.835 | N60: 51020.189 | O60: 58400.731
A61: FIRST PARTY DIRECT API REVENUE
A62: First-party API revenue | B62: PLUG | C62: $M | D62: Booked revenue minus non-API streams. | E62: 10 | F62: 69.938 | G62: 419.931 | H62: 3021.8648 | I62: 16500.677 | J62: 35141.202 | K62: 59190.378 | L62: 86458.321 | M62: 114270.17 | N62: 138179.81 | O62: 162099.27
A63: API TOKEN ENGINE
A64: Total tokens processed (all) | B64: PLUG | C64: T | D64: API revenue / blended $/Mtok (trillions). | E64: 3.3549784 | F64: 20.11538 | G64: 110.69024 | H64: 728.7377 | I64: 5397.3629 | J64: 11876.909 | K64: 22312.565 | L64: 36357.054 | M64: 50996.73 | N64: 67139.444 | O64: 81370.718
A65: Total input tokens | B65: CALC | C65: T | D65: tokens x input share. | E65: 2.5974026 | F65: 15.880563 | G65: 90.729708 | H65: 628.22216 | I65: 4693.359 | J65: 10451.68 | K65: 19770.627 | L65: 32529.996 | M65: 45704.616 | N65: 60253.347 | O65: 73106.505
A66: Total output tokens | B66: CALC | C66: T | D66: tokens x (1 - input share). | E66: 0.75757576 | F66: 4.2348168 | G66: 19.960536 | H66: 100.51555 | I66: 704.00386 | J66: 1425.2291 | K66: 2541.9378 | L66: 3827.0583 | M66: 5292.1134 | N66: 6886.0968 | O66: 8264.2136
A67: Total first-party API calls | B67: CALC | C67: B | D67: tokens / tokens-per-call (billions). | E67: 2.1645022 | F67: 10.587042 | G67: 36.291883 | H67: 125.64443 | I67: 586.66988 | J67: 950.15275 | K67: 1412.1877 | L67: 1913.5292 | M67: 2405.5061 | N67: 2869.207 | O67: 3178.5437
A68: Memo: calls / contract / day | B68: CALC | C68: # | D68: calls / contracts / 365. | E68: 5930142.9 | F68: 6824845.8 | G68: 2761939.4 | H68: 2206611 | I68: 3214629.5 | J68: 2469789.6 | K68: 2239008.8 | L68: 2113929.7 | M68: 2095525.5 | N68: 2126851 | O68: 2103463.5
A69: COSTS - Inference and infrastructure
A70: Billed tokens (Anthropic-served) | B70: LINK | C70: T | D70: API + consumer + Claude Code (excl Bedrock/Vertex). | E70: 3.3549784 | F70: 20.13238 | G70: 110.93024 | H70: 758.0657 | I70: 5546.3629 | J70: 12263.541 | K70: 23026.805 | L70: 37436.734 | M70: 52446.15 | N70: 68899.444 | O70: 83408.318
A71: Free-tier tokens served | B71: IN | C71: T | D71: Non-billed free-tier usage. | E71: 1.6774892 | F71: 9.059571 | G71: 44.372098 | H71: 265.323 | I71: 1663.9089 | J71: 3433.7916 | K71: 5986.9693 | L71: 9359.1835 | M71: 12587.076 | N71: 15846.872 | O71: 18349.83
A72: Internal / testing tokens | B72: IN | C72: T | D72: Evals/red-team/internal. | E72: 1.0064935 | F72: 5.033095 | G72: 22.186049 | H72: 113.70986 | I72: 665.56355 | J72: 1348.9895 | K72: 2302.6805 | L72: 3743.6734 | M72: 4720.1535 | N72: 6200.95 | O72: 6672.6655
A73: Gross tokens served | B73: CALC | C73: T | D73: billed + free + internal. | E73: 6.038961 | F73: 34.225046 | G73: 177.48839 | H73: 1137.0986 | I73: 7875.8353 | J73: 17046.322 | K73: 31316.455 | L73: 50539.591 | M73: 69753.379 | N73: 90947.266 | O73: 108430.81
A74: Tokens per GPU-hour | B74: IN | C74: tok/hr | D74: Serving throughput (back-solved for consistency). | E74: 3358566.6 | F74: 3155545.4 | G74: 2862716 | H74: 2822376.2 | I74: 4051166.2 | J74: 4176616.3 | K74: 4555505.3 | L74: 5105009.2 | M74: 5419713.4 | N74: 5930637.8 | O74: 6138576.1
A75: Required GPU-hours | B75: CALC | C75: hr | D75: gross tokens / tokens-per-GPU-hour. | E75: 1798076.9 | F75: 10846000 | G75: 62000000 | H75: 4.0288696e+08 | I75: 1.9440909e+09 | J75: 4.0813714e+09 | K75: 6.8744195e+09 | L75: 9900000000 | M75: 1.2870308e+10 | N75: 1.5335158e+10 | O75: 1.7663838e+10
A76: Fleet utilization % | B76: IN | C76: % | D76: Effective serving utilization. | E76: 0.55 | F76: 0.58 | G76: 0.62 | H76: 0.66 | I76: 0.7 | J76: 0.72 | K76: 0.74 | L76: 0.75 | M76: 0.76 | N76: 0.77 | O76: 0.78
A77: Total provisioned GPU-hours | B77: CALC | C77: hr | D77: required / utilization. | E77: 3269230.8 | F77: 18700000 | G77: 100000000 | H77: 6.1043478e+08 | I77: 2.7772727e+09 | J77: 5.6685714e+09 | K77: 9.2897561e+09 | L77: 13200000000 | M77: 1.6934615e+10 | N77: 1.9915789e+10 | O77: 2.2645946e+10
A78: Blended $/GPU-hour | B78: IN | C78: $ | D78: Owned + rented all-in hourly cost. | E78: 2.6 | F78: 2.5 | G78: 2.4 | H78: 2.3 | I78: 2.2 | J78: 2.1 | K78: 2.05 | L78: 2 | M78: 1.95 | N78: 1.9 | O78: 1.85
A79: Inference compute cost | B79: CALC | C79: $M | D79: Declining share of revenue; GPU-hrs x $/GPU-hr. | E79: 8.5 | F79: 46.75 | G79: 240 | H79: 1404 | I79: 6110 | J79: 11904 | K79: 19044 | L79: 26400 | M79: 33022.5 | N79: 37840 | O79: 41895
A80: Data egress volume (PB) | B80: IN | C80: PB | D80: Outbound data volume. | E80: 0.5 | F80: 2.55 | G80: 12 | H80: 62.4 | I80: 240 | J80: 496 | K80: 828 | L80: 1200 | M80: 1572.5 | N80: 1892 | O80: 2205
A81: Egress cost ($/TB) | B81: IN | C81: $ | D81: Blended egress unit cost. | E81: 20 | F81: 18 | G81: 16 | H81: 14 | I81: 12 | J81: 11 | K81: 10 | L81: 9 | M81: 9 | N81: 8 | O81: 8
... A84: API gateway and load-balancing | B84: IN | C84: $M | D84: Edge/gateway/LB. | E84: 0.3 | F84: 1.7 | G84: 6 | H84: 28.6 | I84: 100 | J84: 198.4 | K84: 316.8 | L84: 448 | M84: 578 | N84: 686.4 | O84: 792
A85: COSTS - SAFETY, PAYMENTS, SUPPORT
A86: Content moderation cost $/Mtok | B86: IN | C86: $ | D86: Classifier cost per Mtok gross. | E86: 0.05 | F86: 0.05 | G86: 0.04 | H86: 0.035 | I86: 0.03 | J86: 0.028 | K86: 0.026 | L86: 0.025 | M86: 0.024 | N86: 0.023 | O86: 0.022
A87: Automated moderation cost | B87: CALC | C87: $M | D87: gross tokens x $/Mtok. | E87: 0.30194805 | F87: 1.7112523 | G87: 7.0995356 | H87: 39.798449 | I87: 236.27506 | J87: 477.29703 | K87: 814.22782 | L87: 1263.4898 | M87: 1674.0811 | N87: 2091.7871 | O87: 2385.4779
A88: HITL review volume | B88: IN | C88: Count | D88: Human safety reviews / yr. | E88: 20000 | F88: 102000 | G88: 420000 | H88: 1820000 | I88: 6000000 | J88: 11780000 | K88: 18720000 | L88: 26400000 | M88: 33150000 | N88: 38720000 | O88: 43200000
A89: Cost per HITL review | B89: IN | C89: $ | D89: BPO hourly x hours. | E89: 4 | F89: 4 | G89: 3.8 | H89: 3.6 | I89: 3.5 | J89: 3.4 | K89: 3.3 | L89: 3.2 | M89: 3.2 | N89: 3.1 | O89: 3
A90: HITL review cost | B90: CALC | C90: $M | D90: volume x cost. | E90: 0.08 | F90: 0.408 | G90: 1.596 | H90: 6.552 | I90: 21 | J90: 40.052 | K90: 61.776 | L90: 84.48 | M90: 106.08 | N90: 120.032 | O90: 129.6
A91: B2B gross cash collections | B91: LINK | C91: $M | D91: API + seats + CC + FT + PT + PS. | E91: 10 | F91: 72.08 | G91: 448.74 | H91: 3340.48 | I91: 17671 | J91: 37908.04 | K91: 63878.4 | L91: 93182.4 | M91: 122974.6 | N91: 148409.36 | O91: 173734.2
A92: Payment processing fee % (Stripe) | B92: IN | C92: % | D92: Blended processor fee. | E92: 0.029 | F92: 0.028 | G92: 0.027 | H92: 0.026 | I92: 0.025 | J92: 0.024 | K92: 0.024 | L92: 0.023 | M92: 0.023 | N92: 0.022 | O92: 0.022
A93: B2B payment processing cost | B93: CALC | C93: $M | D93: collections x fee. | E93: 0.29 | F93: 2.01824 | G93: 12.11598 | H93: 86.85248 | I93: 441.775 | J93: 909.79296 | K93: 1533.0816 | L93: 2143.1952 | M93: 2828.4158 | N93: 3265.0059 | O93: 3822.1524
A94: Mobile share of consumer revenue % | B94: IN | C94: % | D94: Consumer via mobile stores. | E94: 0 | F94: 0.2 | G94: 0.3 | H94: 0.35 | I94: 0.38 | J94: 0.4 | K94: 0.4 | L94: 0.4 | M94: 0.39 | N94: 0.39 | O94: 0.38
A95: B2C mobile collections | B95: CALC | C95: $M | D95: consumer rev x mobile share. | E95: 0 | F95: 1.36 | G95: 21.6 | H95: 236.6 | I95: 1254 | J95: 2777.6 | K95: 4636.8 | L95: 6720 | M95: 8585.85 | N95: 10330.32 | O95: 11730.6
A96: App store take-rate % | B96: IN | C96: % | D96: Apple/Google store take. | E96: 0 | F96: 0.3 | G96: 0.3 | H96: 0.28 | I96: 0.2 | J96: 0.2 | K96: 0.18 | L96: 0.18 | M96: 0.17 | N96: 0.17 | O96: 0.15
A97: App store cost | B97: CALC | C97: $M | D97: mobile collections x take. | E97: 0 | F97: 0.408 | G97: 6.48 | H97: 66.248 | I97: 250.8 | J97: 555.52 | K97: 834.624 | L97: 1209.6 | M97: 1459.5945 | N97: 1756.1544 | O97: 1759.59
... A106: Memo: implied gross margin % | B106: CALC | C106: % | D106: Inference-only gross margin. | E106: 0.030605195 | F106: 0.36418362 | G106: 0.53679914 | H106: 0.6464845 | I106: 0.69225191 | J106: 0.71317671 | K106: 0.72429796 | L106: 0.73448551 | M106: 0.74519022 | N106: 0.75564621 | O106: 0.76722658
A107: OpEx & Comp (ex-SBC)
A108: R&D headcount | B108: IN | C108: count | D108: Research + eng (~65-75% of total). | E108: 40 | F108: 130 | G108: 270 | H108: 700 | I108: 3250 | J108: 4800 | K108: 6000 | L108: 6900 | M108: 7500 | N108: 7900 | O108: 8300
A109: Fully-burdened R&D cash comp ($/head) | B109: IN | C109: $ | D109: Levels.fyi eng $619-841k, research ~$746k median. | E109: 400000 | F109: 420000 | G109: 450000 | H109: 480000 | I109: 520000 | J109: 545000 | K109: 565000 | L109: 580000 | M109: 595000 | N109: 605000 | O109: 615000
A110: R&D personnel cost | B110: CALC | C110: $M | D110: heads x comp. | E110: 16 | F110: 54.6 | G110: 121.5 | H110: 336 | I110: 1690 | J110: 2616 | K110: 3390 | L110: 4002 | M110: 4462.5 | N110: 4779.5 | O110: 5104.5
A111: RLHF & data annotation | B111: IN | C111: $M | D111: Human feedback/annotation. | E111: 2 | F111: 8 | G111: 60 | H111: 300 | I111: 620 | J111: 900 | K111: 1150 | L111: 1400 | M111: 1600 | N111: 1750 | O111: 1900
A112: Proprietary data licensing | B112: IN | C112: $M | D112: Licensed training data. | E112: 0 | F112: 3 | G112: 25 | H112: 120 | I112: 400 | J112: 620 | K112: 820 | L112: 1000 | M112: 1150 | N112: 1280 | O112: 1400
A113: Experimental / failed training runs | B113: IN | C113: $M | D113: Abandoned run compute. | E113: 3 | F113: 12 | G113: 90 | H113: 380 | I113: 620 | J113: 850 | K113: 1050 | L113: 1250 | M113: 1400 | N113: 1520 | O113: 1650
A114: Internal tooling & subscriptions | B114: IN | C114: $M | D114: Dev tooling/SaaS. | E114: 1 | F114: 4 | G114: 30 | H114: 150 | I114: 380 | J114: 560 | K114: 720 | L114: 880 | M114: 1010 | N114: 1130 | O114: 1240
A115: Capitalizable frontier-training runs | B115: IN | C115: $M | D115: Capitalizable portion (~30% of training). | E115: 10.5 | F115: 30.6 | G115: 630 | H115: 631.8 | I115: 3031.5 | J115: 5208 | K115: 7452 | L115: 9360 | M115: 10850.25 | N115: 11919.6 | O115: 12568.5
A116: Cap toggle (1=capitalized, 0=ASC 730 expense) | B116: IN | C116: 0/1 | D116: 0 = expense training to R&D (base). | E116: 0 | F116: 0 | G116: 0 | H116: 0 | I116: 0 | J116: 0 | K116: 0 | L116: 0 | M116: 0 | N116: 0 | O116: 0
A117: Training compute expenses to R&D | B117: CALC | C117: $M | D117: Training (expensed) + research compute. Primary loss driver. | E117: 41 | F117: 123.25 | G117: 2430 | H117: 2574 | I117: 12220 | J117: 21328 | K117: 30636 | L117: 38400 | M117: 44816.25 | N117: 49192 | O117: 51817.5
A118: Total R&D (ex-SBC) | B118: CALC | C118: $M | D118: Personnel + RLHF + licensing + failed + tooling + training. | E118: 63 | F118: 204.85 | G118: 2756.5 | H118: 3860 | I118: 15930 | J118: 26874 | K118: 37766 | L118: 46932 | M118: 54438.75 | N118: 59651.5 | O118: 63112
A119: S&M Headcount | B119: IN | C119: count | D119: GTM heads (small org). | E119: 8 | F119: 30 | G119: 70 | H119: 180 | I119: 900 | J119: 1450 | K119: 1900 | L119: 2250 | M119: 2500 | N119: 2700 | O119: 2850
... A133: One-time litigation services | B133: IN | C133: $M | D133: Non-recurring litigation. | E133: 0 | F133: 0 | G133: 5 | H133: 40 | I133: 150 | J133: 90 | K133: 60 | L133: 50 | M133: 45 | N133: 40 | O133: 40
A134: STOCK BASED COMP
A135: SBC issue rate (% of base cash comp) | B135: IN | C135: % | D135: RSU grant value as % of cash comp. | E135: 0.4 | F135: 0.45 | G135: 0.5 | H135: 0.55 | I135: 0.55 | J135: 0.5 | K135: 0.45 | L135: 0.42 | M135: 0.4 | N135: 0.38 | O135: 0.36
A136: R&D SBC | B136: CALC | C136: $M | D136: R&D cash x SBC rate. | E136: 6.4 | F136: 24.57 | G136: 60.75 | H136: 184.8 | I136: 929.5 | J136: 1308 | K136: 1525.5 | L136: 1680.84 | M136: 1785 | N136: 1816.21 | O136: 1837.62
A137: S&M SBC | B137: CALC | C137: $M | D137: S&M cash x SBC rate. | E137: 0.896 | F137: 3.915 | G137: 10.5 | H137: 30.69 | I137: 158.4 | J137: 239.25 | K137: 290.7 | L137: 330.75 | M137: 358 | N137: 374.49 | O137: 381.672
A138: G&A SBC | B138: CALC | C138: $M | D138: G&A cash x SBC rate. | E138: 1.248 | F138: 3.888 | G138: 8.4 | H138: 27.115 | I138: 140.25 | J138: 192.5 | K138: 226.8 | L138: 250.194 | M138: 262.4 | N138: 279.224 | O138: 287.64
A139: Total SBC | B139: CALC | C139: $M | D139: Sum of function SBC. | E139: 8.544 | F139: 32.373 | G139: 79.65 | H139: 242.605 | I139: 1228.15 | J139: 1739.75 | K139: 2043 | L139: 2261.784 | M139: 2405.4 | N139: 2469.924 | O139: 2506.932
A140: DEPRECIATION & AMORTIZATION
A141: Amort life - models (yrs) | B141: IN | C141: yr | D141: Life of capitalized models. | E141: 2 | F141: 2 | G141: 2 | H141: 2 | I141: 2 | J141: 2 | K141: 2 | L141: 2 | M141: 2 | N141: 2 | O141: 2
A142: Amort of capitalized frontier models | B142: CALC | C142: $M | D142: 2-yr straight-line of cap pool. | E142: 5.25 | F142: 20.55 | G142: 330.3 | H142: 630.9 | I142: 1831.65 | J142: 4119.75 | K142: 6330 | L142: 8406 | M142: 10105.125 | N142: 11384.925 | O142: 12244.05
A143: Owned GPU / datacenter capex | B143: IN | C143: $M | D143: Owned hardware capex (Fluidstack $50B ramps 2026+). | E143: 2 | F143: 8 | G143: 40 | H143: 220 | I143: 1400 | J143: 3200 | K143: 5000 | L143: 6500 | M143: 7500 | N143: 8200 | O143: 8800
A144: Depreciation life - HW (yrs) | B144: IN | C144: yr | D144: Life of owned accelerators. | E144: 4 | F144: 4 | G144: 4 | H144: 5 | I144: 5 | J144: 5 | K144: 6 | L144: 6 | M144: 6 | N144: 6 | O144: 6
A145: Depreciation of owned GPU / datacenter | B145: CALC | C145: $M | D145: Vintage straight-line depreciation. | E145: 0.5 | F145: 2.5 | G145: 12.5 | H145: 56.5 | I145: 336 | J145: 974 | K145: 1797.3333 | L145: 2880.6667 | M145: 4086.6667 | N145: 5173.3333 | O145: 6000
A146: Amort of prepaid cloud commits (reclass) | B146: MEMO | C146: $M | D146: Reclass memo. NOT added to P&L D&A (guard). | E146: 0 | F146: 0 | G146: 20 | H146: 120 | I146: 500 | J146: 800 | K146: 1050 | L146: 1300 | M146: 1500 | N146: 1650 | O146: 1800
A147: Total D&A | B147: CALC | C147: $M | D147: Model amort + owned HW dep (prepaid-cloud excluded). | E147: 5.75 | F147: 23.05 | G147: 342.8 | H147: 687.4 | I147: 2167.65 | J147: 5093.75 | K147: 8127.3333 | L147: 11286.667 | M147: 14191.792 | N147: 16558.258 | O147: 18244.05
A148: P&L SUMMARY (memo)
A149: Gross profit | B149: CALC | C149: $M | D149: Revenue - cost of revenue. | E149: 0.30605195 | F149: 30.955608 | G149: 322.07948 | H149: 3025.5475 | I149: 16267.92 | J149: 35373.565 | K149: 59971.871 | L149: 88138.261 | M149: 117181.16 | N149: 142968.26 | O149: 169173.46
A150: Operating income (ex-SBC) | B150: CALC | C150: $M | D150: GP - R&D - S&M - G&A - D&A. | E150: -75.803948 | F150: -225.28439 | G150: -2896.0205 | H150: -2106.9525 | I150: -4162.7301 | J150: -227.68516 | K150: 9378.5379 | L150: 24266.394 | M150: 42094.621 | N150: 59581.205 | O150: 80033.211
A151: Operating income (incl-SBC) | B151: CALC | C151: $M | D151: After stock-based comp. | E151: -84.347948 | F151: -257.65739 | G151: -2975.6705 | H151: -2349.5575 | I151: -5390.8801 | J151: -1967.4352 | K151: 7335.5379 | L151: 22004.61 | M151: 39689.221 | N151: 57111.281 | O151: 77526.279
...

Sheet D3
A1: Best/Run-rate (data block D3)
A2: Line Item | B2: Type | C2: Unit | D2: What it is | E2: 2022 | F2: 2023 | G2: 2024 | H2: 2025 | I2: 2026 | J2: 2027 | K2: 2028 | L2: 2029 | M2: 2030 | N2: 2031 | O2: 2032
A3: REVENUE
A4: Booked revenue | B4: IN | C4: $M | D4: Anchor. 2022-26 PitchBook TTM (10/100/1,000/9,000/47,000); 2027-32 base case. PB carries 55,000 for 2027 as a conservative mark. | E4: 10 | F4: 100 | G4: 1000 | H4: 9000 | I4: 47000 | J4: 92000 | K4: 140000 | L4: 190000 | M4: 245000 | N4: 300000 | O4: 355000
A5: API PRICING AND BLENDED EFFECTIVE RATE
A6: Model mix % - Mythos | B6: IN | C6: % | D6: Token share, flagship tier (Fable 5 / Mythos 5, $10/$50). Introduced 2026. | E6: 0 | F6: 0 | G6: 0 | H6: 0 | I6: 0.03 | J6: 0.05 | K6: 0.06 | L6: 0.07 | M6: 0.08 | N6: 0.09 | O6: 0.1
A7: Model mix % - Opus | B7: IN | C7: % | D7: Token share, Opus ($15/$75 to Aug-2025, cut to $5/$25 at Opus 4.5). | E7: 0 | F7: 0.1 | G7: 0.08 | H7: 0.1 | I7: 0.12 | J7: 0.12 | K7: 0.12 | L7: 0.12 | M7: 0.12 | N7: 0.12 | O7: 0.12
A8: Model mix % - Sonnet | B8: IN | C8: % | D8: Token share, Sonnet workhorse ($3/$15). | E8: 0.4 | F8: 0.3 | G8: 0.32 | H8: 0.45 | I8: 0.45 | J8: 0.44 | K8: 0.43 | L8: 0.42 | M8: 0.41 | N8: 0.4 | O8: 0.4
A9: Model mix % - Haiku | B9: IN | C9: % | D9: Token share, Haiku ($0.25/$1.25 -> $1/$5). | E9: 0.6 | F9: 0.6 | G9: 0.6 | H9: 0.45 | I9: 0.4 | J9: 0.39 | K9: 0.39 | L9: 0.39 | M9: 0.39 | N9: 0.39 | O9: 0.38
A10: List input $/Mtok - Mythos | B10: IN | C10: $ | D10: List input price, flagship. | E10: 15 | F10: 15 | G10: 15 | H10: 15 | I10: 15 | J10: 15 | K10: 14 | L10: 13 | M10: 12 | N10: 12 | O10: 11
A11: List input $/Mtok - Opus | B11: IN | C11: $ | D11: List input price, Opus. | E11: 11 | F11: 8 | G11: 15 | H11: 15 | I11: 5 | J11: 5 | K11: 5 | L11: 4.5 | M11: 4.5 | N11: 4 | O11: 4
A12: List input $/Mtok - Sonnet | B12: IN | C12: $ | D12: List input price, Sonnet. | E12: 3 | F12: 3 | G12: 3 | H12: 3 | I12: 3 | J12: 3 | K12: 3 | L12: 2.5 | M12: 2.5 | N12: 2 | O12: 2
A13: List input $/Mtok - Haiku | B13: IN | C13: $ | D13: List input price, Haiku. | E13: 0.8 | F13: 0.8 | G13: 0.25 | H13: 0.8 | I13: 1 | J13: 1 | K13: 1 | L13: 0.9 | M13: 0.9 | N13: 0.8 | O13: 0.8
A14: List output $/Mtok - Mythos | B14: IN | C14: $ | D14: List output price, flagship. | E14: 75 | F14: 75 | G14: 75 | H14: 75 | I14: 75 | J14: 70 | K14: 65 | L14: 60 | M14: 55 | N14: 55 | O14: 50
A15: List output $/Mtok - Opus | B15: IN | C15: $ | D15: List output price, Opus. | E15: 33 | F15: 24 | G15: 75 | H15: 75 | I15: 25 | J15: 25 | K15: 22 | L15: 22 | M15: 20 | N15: 20 | O15: 18
A16: List output $/Mtok - Sonnet | B16: IN | C16: $ | D16: List output price, Sonnet. | E16: 15 | F16: 15 | G16: 15 | H16: 15 | I16: 15 | J16: 15 | K16: 13 | L16: 13 | M16: 12 | N16: 10 | O16: 10
A17: List output $/Mtok - Haiku | B17: IN | C17: $ | D17: List output price, Haiku. | E17: 2.4 | F17: 2.4 | G17: 1.25 | H17: 4 | I17: 5 | J17: 5 | K17: 4.5 | L17: 4.5 | M17: 4 | N17: 4 | O17: 3.6
... A27: Blended effective $/Mtok | B27: CALC | C27: $ | D27: Mix-weighted, adjusted for input share, caching, batch. | E27: 2.9806452 | F27: 3.4768421 | G27: 3.793749 | H27: 4.1467112 | I27: 3.0571739 | J27: 2.9587834 | K27: 2.6527823 | L27: 2.3780343 | M27: 2.2407352 | N27: 2.0581018 | O27: 1.9921081
A28: NON-API REVENUE STREAMS
A29: # Enterprise contracts (>$1M ARR) | B29: IN | C29: count | D29: ~1,000+ at $1M+ ACV by 2026. | E29: 0 | F29: 5 | G29: 60 | H29: 300 | I29: 1000 | J29: 1700 | K29: 2400 | L29: 3100 | M29: 3700 | N29: 4200 | O29: 4600
A30: Committed-use discount % (memo) | B30: IN | C30: % | D30: Volume discount realized on enterprise API. | E30: 0 | F30: 0.05 | G30: 0.1 | H30: 0.12 | I30: 0.15 | J30: 0.15 | K30: 0.16 | L30: 0.16 | M30: 0.17 | N30: 0.17 | O30: 0.18
A31: Active enterprise dashboard seats | B31: IN | C31: count | D31: Console/admin seats. | E31: 0 | F31: 2000 | G31: 40000 | H31: 250000 | I31: 900000 | J31: 1600000 | K31: 2300000 | L31: 3000000 | M31: 3600000 | N31: 4100000 | O31: 4500000
A32: Enterprise platform fee / seat / mo | B32: IN | C32: $ | D32: Monthly platform fee per seat. | E32: 0 | F32: 30 | G32: 35 | H32: 40 | I32: 45 | J32: 48 | K32: 50 | L32: 52 | M32: 54 | N32: 55 | O32: 56
A33: Enterprise seat revenue | B33: CALC | C33: $M | D33: seats x fee x 12. | E33: 0 | F33: 0.72 | G33: 16.8 | H33: 120 | I33: 486 | J33: 921.6 | K33: 1380 | L33: 1872 | M33: 2332.8 | N33: 2706 | O33: 3024
A34: Consumer subscription revenue (anchor) | B34: IN | C34: $M | D34: Claude Pro ($20) + Max ($100/$200). | E34: 0 | F34: 8 | G34: 120 | H34: 1300 | I34: 6600 | J34: 11200 | K34: 16100 | L34: 21000 | M34: 25900 | N34: 30100 | O34: 34300
A35: Blended consumer ARPU ($/mo) | B35: IN | C35: $ | D35: Blend of Pro and Max. | E35: 20 | F35: 20 | G35: 21 | H35: 23 | I35: 26 | J35: 28 | K35: 29 | L35: 30 | M35: 31 | N35: 32 | O35: 33
A36: Paying consumer subs (implied) | B36: PLUG | C36: Count | D36: consumer rev / (ARPU x 12). | E36: 0 | F36: 33333.333 | G36: 476190.48 | H36: 4710144.9 | I36: 21153846 | J36: 33333333 | K36: 46264368 | L36: 58333333 | M36: 69623656 | N36: 78385417 | O36: 86616162
A37: Active developer seats | B37: IN | C37: Count | D37: Claude Code seats (Feb-2025). | E37: 0 | F37: 0 | G37: 0 | H37: 350000 | I37: 1100000 | J37: 1800000 | K37: 2500000 | L37: 3100000 | M37: 3600000 | N37: 4000000 | O37: 4300000
A38: Base seat fee ($/mo) | B38: IN | C38: $ | D38: Claude Code base seat fee. | E38: 0 | F38: 0 | G38: 0 | H38: 20 | I38: 22 | J38: 24 | K38: 25 | L38: 26 | M38: 27 | N38: 28 | O38: 28
A39: Claude Code base seat revenue | B39: CALC | C39: $M | D39: seats x fee x 12. | E39: 0 | F39: 0 | G39: 0 | H39: 84 | I39: 290.4 | J39: 518.4 | K39: 750 | L39: 967.2 | M39: 1166.4 | N39: 1344 | O39: 1444.8
A40: Avg overage tokens / dev / mo | B40: IN | C40: Mtok | D40: Usage above base seat. | E40: 0 | F40: 0 | G40: 0 | H40: 12 | I40: 20 | J40: 26 | K40: 30 | L40: 33 | M40: 36 | N40: 38 | O40: 40
... A60: Total non-API revenue | B60: CALC | C60: $M | D60: Sum of non-API streams. | E60: 0 | F60: 17.72 | G60: 300.115 | H60: 3188.7792 | I60: 13998.754 | J60: 23319.133 | K60: 32789.275 | L60: 41925.307 | M60: 50563.131 | N60: 57976.56 | O60: 64889.009
A61: FIRST PARTY DIRECT API REVENUE
A62: First-party API revenue | B62: PLUG | C62: $M | D62: Booked revenue minus non-API streams. | E62: 10 | F62: 82.28 | G62: 699.885 | H62: 5811.2208 | I62: 33001.246 | J62: 68680.867 | K62: 107210.72 | L62: 148074.69 | M62: 194436.87 | N62: 242023.44 | O62: 290110.99
A63: API TOKEN ENGINE
A64: Total tokens processed (all) | B64: PLUG | C64: T | D64: API revenue / blended $/Mtok (trillions). | E64: 3.3549784 | F64: 23.665153 | G64: 184.48374 | H64: 1401.4047 | I64: 10794.69 | J64: 23212.537 | K64: 40414.445 | L64: 62267.687 | M64: 86773.694 | N64: 117595.47 | O64: 145630.14
A65: Total input tokens | B65: CALC | C65: T | D65: tokens x input share. | E65: 2.5974026 | F65: 18.683015 | G65: 151.21618 | H65: 1208.1075 | I65: 9386.6874 | J65: 20427.032 | K65: 35810.268 | L65: 55713.193 | M65: 77768.877 | N65: 105534.39 | O65: 130839.58
A66: Total output tokens | B66: CALC | C66: T | D66: tokens x (1 - input share). | E66: 0.75757576 | F66: 4.9821375 | G66: 33.26756 | H66: 193.29721 | I66: 1408.0031 | J66: 2785.5044 | K66: 4604.1773 | L66: 6554.4933 | M66: 9004.8173 | N66: 12061.073 | O66: 14790.561
A67: Total first-party API calls | B67: CALC | C67: B | D67: tokens / tokens-per-call (billions). | E67: 2.1645022 | F67: 12.455344 | G67: 60.486472 | H67: 241.62151 | I67: 1173.3359 | J67: 1857.0029 | K67: 2557.8763 | L67: 3277.2467 | M67: 4093.0988 | N67: 5025.4473 | O67: 5688.6775
A68: Memo: calls / contract / day | B68: CALC | C68: # | D68: calls / contracts / 365. | E68: 5930142.9 | F68: 6824845.8 | G68: 2761939.4 | H68: 2206589.1 | I68: 3214619 | J68: 2992752.5 | K68: 2919950.1 | L68: 2896373.5 | M68: 3030802.5 | N68: 3278178.2 | O68: 3388134.3
A69: COSTS - Inference and infrastructure
A70: Billed tokens (Anthropic-served) | B70: LINK | C70: T | D70: API + consumer + Claude Code (excl Bedrock/Vertex). | E70: 3.3549784 | F70: 23.685153 | G70: 184.88374 | H70: 1457.8047 | I70: 11092.69 | J70: 23836.137 | K70: 41406.445 | L70: 63617.287 | M70: 88478.894 | N70: 119595.47 | O70: 147894.14
A71: Free-tier tokens served | B71: IN | C71: T | D71: Non-billed free-tier usage. | E71: 1.6774892 | F71: 10.658319 | G71: 73.953496 | H71: 510.23166 | I71: 3327.8071 | J71: 6674.1183 | K71: 10765.676 | L71: 15904.322 | M71: 21234.935 | N71: 27506.957 | O71: 32536.711
A72: Internal / testing tokens | B72: IN | C72: T | D72: Evals/red-team/internal. | E72: 1.0064935 | F72: 5.9212882 | G72: 36.976748 | H72: 218.67071 | I72: 1331.1229 | J72: 2621.975 | K72: 4140.6445 | L72: 6361.7287 | M72: 7963.1005 | N72: 10763.592 | O72: 11831.531
A73: Gross tokens served | B73: CALC | C73: T | D73: billed + free + internal. | E73: 6.038961 | F73: 40.26476 | G73: 295.81398 | H73: 2186.7071 | I73: 15751.62 | J73: 33132.23 | K73: 56312.765 | L73: 85883.337 | M73: 117676.93 | N73: 157866.01 | O73: 192262.39
A74: Tokens per GPU-hour | B74: IN | C74: tok/hr | D74: Serving throughput (back-solved for consistency). | E74: 3731740.6 | F74: 3506161.6 | G74: 3180795.5 | H74: 3135943.6 | I74: 4501281.4 | J74: 4862906.1 | K74: 5383077.3 | L74: 6087778.6 | M74: 6520553.4 | N74: 7213694.8 | O74: 7511851.4
A75: Required GPU-hours | B75: CALC | C75: hr | D75: gross tokens / tokens-per-GPU-hour. | E75: 1618269.2 | F75: 11484000 | G75: 93000000 | H75: 6.9730435e+08 | I75: 3.4993636e+09 | J75: 6.8132571e+09 | K75: 1.0461073e+10 | L75: 14107500000 | M75: 1.8047077e+10 | N75: 2.1884211e+10 | O75: 2.5594541e+10
A76: Fleet utilization % | B76: IN | C76: % | D76: Effective serving utilization. | E76: 0.55 | F76: 0.58 | G76: 0.62 | H76: 0.66 | I76: 0.7 | J76: 0.72 | K76: 0.74 | L76: 0.75 | M76: 0.76 | N76: 0.77 | O76: 0.78
A77: Total provisioned GPU-hours | B77: CALC | C77: hr | D77: required / utilization. | E77: 2942307.7 | F77: 19800000 | G77: 150000000 | H77: 1.0565217e+09 | I77: 4.9990909e+09 | J77: 9.4628571e+09 | K77: 1.4136585e+10 | L77: 18810000000 | M77: 2.3746154e+10 | N77: 2.8421053e+10 | O77: 3.2813514e+10
A78: Blended $/GPU-hour | B78: IN | C78: $ | D78: Owned + rented all-in hourly cost. | E78: 2.6 | F78: 2.5 | G78: 2.4 | H78: 2.3 | I78: 2.2 | J78: 2.1 | K78: 2.05 | L78: 2 | M78: 1.95 | N78: 1.9 | O78: 1.85
A79: Inference compute cost | B79: CALC | C79: $M | D79: Declining share of revenue; GPU-hrs x $/GPU-hr. | E79: 7.65 | F79: 49.5 | G79: 360 | H79: 2430 | I79: 10998 | J79: 19872 | K79: 28980 | L79: 37620 | M79: 46305 | N79: 54000 | O79: 60705
A80: Data egress volume (PB) | B80: IN | C80: PB | D80: Outbound data volume. | E80: 0.5 | F80: 3 | G80: 20 | H80: 120 | I80: 480 | J80: 800 | K80: 1150 | L80: 1500 | M80: 1850 | N80: 2150 | O80: 2450
A81: Egress cost ($/TB) | B81: IN | C81: $ | D81: Blended egress unit cost. | E81: 20 | F81: 18 | G81: 16 | H81: 14 | I81: 12 | J81: 11 | K81: 10 | L81: 9 | M81: 9 | N81: 8 | O81: 8
... A84: API gateway and load-balancing | B84: IN | C84: $M | D84: Edge/gateway/LB. | E84: 0.3 | F84: 2 | G84: 10 | H84: 55 | I84: 200 | J84: 320 | K84: 440 | L84: 560 | M84: 680 | N84: 780 | O84: 880
A85: COSTS - SAFETY, PAYMENTS, SUPPORT
A86: Content moderation cost $/Mtok | B86: IN | C86: $ | D86: Classifier cost per Mtok gross. | E86: 0.05 | F86: 0.05 | G86: 0.04 | H86: 0.035 | I86: 0.03 | J86: 0.028 | K86: 0.026 | L86: 0.025 | M86: 0.024 | N86: 0.023 | O86: 0.022
A87: Automated moderation cost | B87: CALC | C87: $M | D87: gross tokens x $/Mtok. | E87: 0.30194805 | F87: 2.013238 | G87: 11.832559 | H87: 76.534749 | I87: 472.54861 | J87: 927.70244 | K87: 1464.1319 | L87: 2147.0834 | M87: 2824.2463 | N87: 3630.9183 | O87: 4229.7725
A88: HITL review volume | B88: IN | C88: Count | D88: Human safety reviews / yr. | E88: 20000 | F88: 120000 | G88: 700000 | H88: 3500000 | I88: 12000000 | J88: 19000000 | K88: 26000000 | L88: 33000000 | M88: 39000000 | N88: 44000000 | O88: 48000000
A89: Cost per HITL review | B89: IN | C89: $ | D89: BPO hourly x hours. | E89: 4 | F89: 4 | G89: 3.8 | H89: 3.6 | I89: 3.5 | J89: 3.4 | K89: 3.3 | L89: 3.2 | M89: 3.2 | N89: 3.1 | O89: 3
A90: HITL review cost | B90: CALC | C90: $M | D90: volume x cost. | E90: 0.08 | F90: 0.48 | G90: 2.66 | H90: 12.6 | I90: 42 | J90: 64.6 | K90: 85.8 | L90: 105.6 | M90: 124.8 | N90: 136.4 | O90: 144
A91: B2B gross cash collections | B91: LINK | C91: $M | D91: API + seats + CC + FT + PT + PS. | E91: 10 | F91: 84.8 | G91: 747.9 | H91: 6424 | I91: 35342 | J91: 73142 | K91: 113720 | L91: 156478 | M91: 204676 | N91: 253647 | O91: 303038
A92: Payment processing fee % (Stripe) | B92: IN | C92: % | D92: Blended processor fee. | E92: 0.029 | F92: 0.028 | G92: 0.027 | H92: 0.026 | I92: 0.025 | J92: 0.024 | K92: 0.024 | L92: 0.023 | M92: 0.023 | N92: 0.022 | O92: 0.022
A93: B2B payment processing cost | B93: CALC | C93: $M | D93: collections x fee. | E93: 0.29 | F93: 2.3744 | G93: 20.1933 | H93: 167.024 | I93: 883.55 | J93: 1755.408 | K93: 2729.28 | L93: 3598.994 | M93: 4707.548 | N93: 5580.234 | O93: 6666.836
A94: Mobile share of consumer revenue % | B94: IN | C94: % | D94: Consumer via mobile stores. | E94: 0 | F94: 0.2 | G94: 0.3 | H94: 0.35 | I94: 0.38 | J94: 0.4 | K94: 0.4 | L94: 0.4 | M94: 0.39 | N94: 0.39 | O94: 0.38
A95: B2C mobile collections | B95: CALC | C95: $M | D95: consumer rev x mobile share. | E95: 0 | F95: 1.6 | G95: 36 | H95: 455 | I95: 2508 | J95: 4480 | K95: 6440 | L95: 8400 | M95: 10101 | N95: 11739 | O95: 13034
A96: App store take-rate % | B96: IN | C96: % | D96: Apple/Google store take. | E96: 0 | F96: 0.3 | G96: 0.3 | H96: 0.28 | I96: 0.2 | J96: 0.2 | K96: 0.18 | L96: 0.18 | M96: 0.17 | N96: 0.17 | O96: 0.15
A97: App store cost | B97: CALC | C97: $M | D97: mobile collections x take. | E97: 0 | F97: 0.48 | G97: 10.8 | H97: 127.4 | I97: 501.6 | J97: 896 | K97: 1159.2 | L97: 1512 | M97: 1717.17 | N97: 1995.63 | O97: 1955.1
... A106: Memo: implied gross margin % | B106: CALC | C106: % | D106: Inference-only gross margin. | E106: 0.11560519 | F106: 0.41918362 | G106: 0.57679914 | H106: 0.67648458 | I106: 0.71825194 | J106: 0.7384377 | K106: 0.7487929 | L106: 0.75823739 | M106: 0.76804266 | N106: 0.77780016 | O106: 0.78821485
A107: OpEx & Comp (ex-SBC)
A108: R&D headcount | B108: IN | C108: count | D108: Research + eng (~65-75% of total). | E108: 40 | F108: 130 | G108: 270 | H108: 700 | I108: 3250 | J108: 4800 | K108: 6000 | L108: 6900 | M108: 7500 | N108: 7900 | O108: 8300
A109: Fully-burdened R&D cash comp ($/head) | B109: IN | C109: $ | D109: Levels.fyi eng $619-841k, research ~$746k median. | E109: 400000 | F109: 420000 | G109: 450000 | H109: 480000 | I109: 520000 | J109: 545000 | K109: 565000 | L109: 580000 | M109: 595000 | N109: 605000 | O109: 615000
A110: R&D personnel cost | B110: CALC | C110: $M | D110: heads x comp. | E110: 16 | F110: 54.6 | G110: 121.5 | H110: 336 | I110: 1690 | J110: 2616 | K110: 3390 | L110: 4002 | M110: 4462.5 | N110: 4779.5 | O110: 5104.5
A111: RLHF & data annotation | B111: IN | C111: $M | D111: Human feedback/annotation. | E111: 2 | F111: 8 | G111: 60 | H111: 300 | I111: 620 | J111: 900 | K111: 1150 | L111: 1400 | M111: 1600 | N111: 1750 | O111: 1900
A112: Proprietary data licensing | B112: IN | C112: $M | D112: Licensed training data. | E112: 0 | F112: 3 | G112: 25 | H112: 120 | I112: 400 | J112: 620 | K112: 820 | L112: 1000 | M112: 1150 | N112: 1280 | O112: 1400
A113: Experimental / failed training runs | B113: IN | C113: $M | D113: Abandoned run compute. | E113: 3 | F113: 12 | G113: 90 | H113: 380 | I113: 620 | J113: 850 | K113: 1050 | L113: 1250 | M113: 1400 | N113: 1520 | O113: 1650
A114: Internal tooling & subscriptions | B114: IN | C114: $M | D114: Dev tooling/SaaS. | E114: 1 | F114: 4 | G114: 30 | H114: 150 | I114: 380 | J114: 560 | K114: 720 | L114: 880 | M114: 1010 | N114: 1130 | O114: 1240
A115: Capitalizable frontier-training runs | B115: IN | C115: $M | D115: Capitalizable portion (~30% of training). | E115: 9.24 | F115: 31.68 | G115: 924 | H115: 1069.2 | I115: 5335.44 | J115: 8500.8 | K115: 11088 | L115: 13041.6 | M115: 14876.4 | N115: 16632 | O115: 17806.8
A116: Cap toggle (1=capitalized, 0=ASC 730 expense) | B116: IN | C116: 0/1 | D116: 0 = expense training to R&D (base). | E116: 0 | F116: 0 | G116: 0 | H116: 0 | I116: 0 | J116: 0 | K116: 0 | L116: 0 | M116: 0 | N116: 0 | O116: 0
A117: Training compute expenses to R&D | B117: CALC | C117: $M | D117: Training (expensed) + research compute. Primary loss driver. | E117: 36.8 | F117: 130.6 | G117: 3630 | H117: 4464 | I117: 22014.8 | J117: 35696 | K117: 46760 | L117: 54872 | M117: 63063 | N117: 70440 | O117: 75331
A118: Total R&D (ex-SBC) | B118: CALC | C118: $M | D118: Personnel + RLHF + licensing + failed + tooling + training. | E118: 58.8 | F118: 212.2 | G118: 3956.5 | H118: 5750 | I118: 25724.8 | J118: 41242 | K118: 53890 | L118: 63404 | M118: 72685.5 | N118: 80899.5 | O118: 86625.5
A119: S&M Headcount | B119: IN | C119: count | D119: GTM heads (small org). | E119: 8 | F119: 30 | G119: 70 | H119: 180 | I119: 900 | J119: 1450 | K119: 1900 | L119: 2250 | M119: 2500 | N119: 2700 | O119: 2850
... A133: One-time litigation services | B133: IN | C133: $M | D133: Non-recurring litigation. | E133: 0 | F133: 0 | G133: 5 | H133: 40 | I133: 150 | J133: 90 | K133: 60 | L133: 50 | M133: 45 | N133: 40 | O133: 40
A134: STOCK BASED COMP
A135: SBC issue rate (% of base cash comp) | B135: IN | C135: % | D135: RSU grant value as % of cash comp. | E135: 0.4 | F135: 0.45 | G135: 0.5 | H135: 0.55 | I135: 0.55 | J135: 0.5 | K135: 0.45 | L135: 0.42 | M135: 0.4 | N135: 0.38 | O135: 0.36
A136: R&D SBC | B136: CALC | C136: $M | D136: R&D cash x SBC rate. | E136: 6.4 | F136: 24.57 | G136: 60.75 | H136: 184.8 | I136: 929.5 | J136: 1308 | K136: 1525.5 | L136: 1680.84 | M136: 1785 | N136: 1816.21 | O136: 1837.62
A137: S&M SBC | B137: CALC | C137: $M | D137: S&M cash x SBC rate. | E137: 0.896 | F137: 3.915 | G137: 10.5 | H137: 30.69 | I137: 158.4 | J137: 239.25 | K137: 290.7 | L137: 330.75 | M137: 358 | N137: 374.49 | O137: 381.672
A138: G&A SBC | B138: CALC | C138: $M | D138: G&A cash x SBC rate. | E138: 1.248 | F138: 3.888 | G138: 8.4 | H138: 27.115 | I138: 140.25 | J138: 192.5 | K138: 226.8 | L138: 250.194 | M138: 262.4 | N138: 279.224 | O138: 287.64
A139: Total SBC | B139: CALC | C139: $M | D139: Sum of function SBC. | E139: 8.544 | F139: 32.373 | G139: 79.65 | H139: 242.605 | I139: 1228.15 | J139: 1739.75 | K139: 2043 | L139: 2261.784 | M139: 2405.4 | N139: 2469.924 | O139: 2506.932
A140: DEPRECIATION & AMORTIZATION
A141: Amort life - models (yrs) | B141: IN | C141: yr | D141: Life of capitalized models. | E141: 2 | F141: 2 | G141: 2 | H141: 2 | I141: 2 | J141: 2 | K141: 2 | L141: 2 | M141: 2 | N141: 2 | O141: 2
A142: Amort of capitalized frontier models | B142: CALC | C142: $M | D142: 2-yr straight-line of cap pool. | E142: 4.62 | F142: 20.46 | G142: 477.84 | H142: 996.6 | I142: 3202.32 | J142: 6918.12 | K142: 9794.4 | L142: 12064.8 | M142: 13959 | N142: 15754.2 | O142: 17219.4
A143: Owned GPU / datacenter capex | B143: IN | C143: $M | D143: Owned hardware capex (Fluidstack $50B ramps 2026+). | E143: 2 | F143: 8 | G143: 40 | H143: 220 | I143: 1400 | J143: 3200 | K143: 5000 | L143: 6500 | M143: 7500 | N143: 8200 | O143: 8800
A144: Depreciation life - HW (yrs) | B144: IN | C144: yr | D144: Life of owned accelerators. | E144: 4 | F144: 4 | G144: 4 | H144: 5 | I144: 5 | J144: 5 | K144: 6 | L144: 6 | M144: 6 | N144: 6 | O144: 6
A145: Depreciation of owned GPU / datacenter | B145: CALC | C145: $M | D145: Vintage straight-line depreciation. | E145: 0.5 | F145: 2.5 | G145: 12.5 | H145: 56.5 | I145: 336 | J145: 974 | K145: 1797.3333 | L145: 2880.6667 | M145: 4086.6667 | N145: 5173.3333 | O145: 6000
A146: Amort of prepaid cloud commits (reclass) | B146: MEMO | C146: $M | D146: Reclass memo. NOT added to P&L D&A (guard). | E146: 0 | F146: 0 | G146: 20 | H146: 120 | I146: 500 | J146: 800 | K146: 1050 | L146: 1300 | M146: 1500 | N146: 1650 | O146: 1800
A147: Total D&A | B147: CALC | C147: $M | D147: Model amort + owned HW dep (prepaid-cloud excluded). | E147: 5.12 | F147: 22.96 | G147: 490.34 | H147: 1053.1 | I147: 3538.32 | J147: 7892.12 | K147: 11591.733 | L147: 14945.467 | M147: 18045.667 | N147: 20927.533 | O147: 23219.4
A148: P&L SUMMARY (memo)
A149: Gross profit | B149: CALC | C149: $M | D149: Revenue - cost of revenue. | E149: 1.1560519 | F149: 41.918362 | G149: 576.79914 | H149: 6088.3613 | I149: 33757.841 | J149: 67936.268 | K149: 104831.01 | L149: 144065.1 | M149: 188170.45 | N149: 233340.05 | O149: 279816.27
A150: Operating income (ex-SBC) | B150: CALC | C150: $M | D150: GP - R&D - S&M - G&A - D&A. | E150: -70.123948 | F150: -221.58164 | G150: -3988.8409 | H150: -1299.8387 | I150: 2161.7214 | J150: 15168.648 | K150: 34649.272 | L150: 60062.438 | M150: 90983.285 | N150: 124335.71 | O150: 162187.17
A151: Operating income (incl-SBC) | B151: CALC | C151: $M | D151: After stock-based comp. | E151: -78.667948 | F151: -253.95464 | G151: -4068.4909 | H151: -1542.4437 | I151: 933.57139 | J151: 13428.898 | K151: 32606.272 | L151: 57800.654 | M151: 88577.885 | N151: 121865.79 | O151: 159680.24
...

Sheet D4
A1: Best/Recognized (data block D4)
A2: Line Item | B2: Type | C2: Unit | D2: What it is | E2: 2022 | F2: 2023 | G2: 2024 | H2: 2025 | I2: 2026 | J2: 2027 | K2: 2028 | L2: 2029 | M2: 2030 | N2: 2031 | O2: 2032
A3: REVENUE
A4: Booked revenue | B4: IN | C4: $M | D4: Anchor. 2022-26 PitchBook TTM (10/100/1,000/9,000/47,000); 2027-32 base case. PB carries 55,000 for 2027 as a conservative mark. | E4: 10 | F4: 85 | G4: 600 | H4: 4680 | I4: 23500 | J4: 57040 | K4: 100800 | L4: 152000 | M4: 208250 | N4: 264000 | O4: 319500
A5: API PRICING AND BLENDED EFFECTIVE RATE
A6: Model mix % - Mythos | B6: IN | C6: % | D6: Token share, flagship tier (Fable 5 / Mythos 5, $10/$50). Introduced 2026. | E6: 0 | F6: 0 | G6: 0 | H6: 0 | I6: 0.03 | J6: 0.05 | K6: 0.06 | L6: 0.07 | M6: 0.08 | N6: 0.09 | O6: 0.1
A7: Model mix % - Opus | B7: IN | C7: % | D7: Token share, Opus ($15/$75 to Aug-2025, cut to $5/$25 at Opus 4.5). | E7: 0 | F7: 0.1 | G7: 0.08 | H7: 0.1 | I7: 0.12 | J7: 0.12 | K7: 0.12 | L7: 0.12 | M7: 0.12 | N7: 0.12 | O7: 0.12
A8: Model mix % - Sonnet | B8: IN | C8: % | D8: Token share, Sonnet workhorse ($3/$15). | E8: 0.4 | F8: 0.3 | G8: 0.32 | H8: 0.45 | I8: 0.45 | J8: 0.44 | K8: 0.43 | L8: 0.42 | M8: 0.41 | N8: 0.4 | O8: 0.4
A9: Model mix % - Haiku | B9: IN | C9: % | D9: Token share, Haiku ($0.25/$1.25 -> $1/$5). | E9: 0.6 | F9: 0.6 | G9: 0.6 | H9: 0.45 | I9: 0.4 | J9: 0.39 | K9: 0.39 | L9: 0.39 | M9: 0.39 | N9: 0.39 | O9: 0.38
A10: List input $/Mtok - Mythos | B10: IN | C10: $ | D10: List input price, flagship. | E10: 15 | F10: 15 | G10: 15 | H10: 15 | I10: 15 | J10: 15 | K10: 14 | L10: 13 | M10: 12 | N10: 12 | O10: 11
A11: List input $/Mtok - Opus | B11: IN | C11: $ | D11: List input price, Opus. | E11: 11 | F11: 8 | G11: 15 | H11: 15 | I11: 5 | J11: 5 | K11: 5 | L11: 4.5 | M11: 4.5 | N11: 4 | O11: 4
A12: List input $/Mtok - Sonnet | B12: IN | C12: $ | D12: List input price, Sonnet. | E12: 3 | F12: 3 | G12: 3 | H12: 3 | I12: 3 | J12: 3 | K12: 3 | L12: 2.5 | M12: 2.5 | N12: 2 | O12: 2
A13: List input $/Mtok - Haiku | B13: IN | C13: $ | D13: List input price, Haiku. | E13: 0.8 | F13: 0.8 | G13: 0.25 | H13: 0.8 | I13: 1 | J13: 1 | K13: 1 | L13: 0.9 | M13: 0.9 | N13: 0.8 | O13: 0.8
A14: List output $/Mtok - Mythos | B14: IN | C14: $ | D14: List output price, flagship. | E14: 75 | F14: 75 | G14: 75 | H14: 75 | I14: 75 | J14: 70 | K14: 65 | L14: 60 | M14: 55 | N14: 55 | O14: 50
A15: List output $/Mtok - Opus | B15: IN | C15: $ | D15: List output price, Opus. | E15: 33 | F15: 24 | G15: 75 | H15: 75 | I15: 25 | J15: 25 | K15: 22 | L15: 22 | M15: 20 | N15: 20 | O15: 18
A16: List output $/Mtok - Sonnet | B16: IN | C16: $ | D16: List output price, Sonnet. | E16: 15 | F16: 15 | G16: 15 | H16: 15 | I16: 15 | J16: 15 | K16: 13 | L16: 13 | M16: 12 | N16: 10 | O16: 10
A17: List output $/Mtok - Haiku | B17: IN | C17: $ | D17: List output price, Haiku. | E17: 2.4 | F17: 2.4 | G17: 1.25 | H17: 4 | I17: 5 | J17: 5 | K17: 4.5 | L17: 4.5 | M17: 4 | N17: 4 | O17: 3.6
... A27: Blended effective $/Mtok | B27: CALC | C27: $ | D27: Mix-weighted, adjusted for input share, caching, batch. | E27: 2.9806452 | F27: 3.4768421 | G27: 3.793749 | H27: 4.1467112 | I27: 3.0571739 | J27: 2.9587834 | K27: 2.6527823 | L27: 2.3780343 | M27: 2.2407352 | N27: 2.0581018 | O27: 1.9921081
A28: NON-API REVENUE STREAMS
A29: # Enterprise contracts (>$1M ARR) | B29: IN | C29: count | D29: ~1,000+ at $1M+ ACV by 2026. | E29: 0 | F29: 4.25 | G29: 36 | H29: 156 | I29: 500 | J29: 1054 | K29: 1728 | L29: 2480 | M29: 3145 | N29: 3696 | O29: 4140
A30: Committed-use discount % (memo) | B30: IN | C30: % | D30: Volume discount realized on enterprise API. | E30: 0 | F30: 0.05 | G30: 0.1 | H30: 0.12 | I30: 0.15 | J30: 0.15 | K30: 0.16 | L30: 0.16 | M30: 0.17 | N30: 0.17 | O30: 0.18
A31: Active enterprise dashboard seats | B31: IN | C31: count | D31: Console/admin seats. | E31: 0 | F31: 1700 | G31: 24000 | H31: 130000 | I31: 450000 | J31: 992000 | K31: 1656000 | L31: 2400000 | M31: 3060000 | N31: 3608000 | O31: 4050000
A32: Enterprise platform fee / seat / mo | B32: IN | C32: $ | D32: Monthly platform fee per seat. | E32: 0 | F32: 30 | G32: 35 | H32: 40 | I32: 45 | J32: 48 | K32: 50 | L32: 52 | M32: 54 | N32: 55 | O32: 56
A33: Enterprise seat revenue | B33: CALC | C33: $M | D33: seats x fee x 12. | E33: 0 | F33: 0.612 | G33: 10.08 | H33: 62.4 | I33: 243 | J33: 571.392 | K33: 993.6 | L33: 1497.6 | M33: 1982.88 | N33: 2381.28 | O33: 2721.6
A34: Consumer subscription revenue (anchor) | B34: IN | C34: $M | D34: Claude Pro ($20) + Max ($100/$200). | E34: 0 | F34: 6.8 | G34: 72 | H34: 676 | I34: 3300 | J34: 6944 | K34: 11592 | L34: 16800 | M34: 22015 | N34: 26488 | O34: 30870
A35: Blended consumer ARPU ($/mo) | B35: IN | C35: $ | D35: Blend of Pro and Max. | E35: 20 | F35: 20 | G35: 21 | H35: 23 | I35: 26 | J35: 28 | K35: 29 | L35: 30 | M35: 31 | N35: 32 | O35: 33
A36: Paying consumer subs (implied) | B36: PLUG | C36: Count | D36: consumer rev / (ARPU x 12). | E36: 0 | F36: 28333.333 | G36: 285714.29 | H36: 2449275.4 | I36: 10576923 | J36: 20666667 | K36: 33310345 | L36: 46666667 | M36: 59180108 | N36: 68979167 | O36: 77954545
A37: Active developer seats | B37: IN | C37: Count | D37: Claude Code seats (Feb-2025). | E37: 0 | F37: 0 | G37: 0 | H37: 182000 | I37: 550000 | J37: 1116000 | K37: 1800000 | L37: 2480000 | M37: 3060000 | N37: 3520000 | O37: 3870000
A38: Base seat fee ($/mo) | B38: IN | C38: $ | D38: Claude Code base seat fee. | E38: 0 | F38: 0 | G38: 0 | H38: 20 | I38: 22 | J38: 24 | K38: 25 | L38: 26 | M38: 27 | N38: 28 | O38: 28
A39: Claude Code base seat revenue | B39: CALC | C39: $M | D39: seats x fee x 12. | E39: 0 | F39: 0 | G39: 0 | H39: 43.68 | I39: 145.2 | J39: 321.408 | K39: 540 | L39: 773.76 | M39: 991.44 | N39: 1182.72 | O39: 1300.32
A40: Avg overage tokens / dev / mo | B40: IN | C40: Mtok | D40: Usage above base seat. | E40: 0 | F40: 0 | G40: 0 | H40: 12 | I40: 20 | J40: 26 | K40: 30 | L40: 33 | M40: 36 | N40: 38 | O40: 40
... A60: Total non-API revenue | B60: CALC | C60: $M | D60: Sum of non-API streams. | E60: 0 | F60: 15.062 | G60: 180.069 | H60: 1658.1352 | I60: 6999.323 | J60: 14458.798 | K60: 23609.622 | L60: 33541.679 | M60: 42979.835 | N60: 51020.189 | O60: 58400.731
A61: FIRST PARTY DIRECT API REVENUE
A62: First-party API revenue | B62: PLUG | C62: $M | D62: Booked revenue minus non-API streams. | E62: 10 | F62: 69.938 | G62: 419.931 | H62: 3021.8648 | I62: 16500.677 | J62: 42581.202 | K62: 77190.378 | L62: 118458.32 | M62: 165270.17 | N62: 212979.81 | O62: 261099.27
A63: API TOKEN ENGINE
A64: Total tokens processed (all) | B64: PLUG | C64: T | D64: API revenue / blended $/Mtok (trillions). | E64: 3.3549784 | F64: 20.11538 | G64: 110.69024 | H64: 728.7377 | I64: 5397.3629 | J64: 14391.456 | K64: 29097.894 | L64: 49813.546 | M64: 73757.117 | N64: 103483.61 | O64: 131066.82
A65: Total input tokens | B65: CALC | C65: T | D65: tokens x input share. | E65: 2.5974026 | F65: 15.880563 | G65: 90.729708 | H65: 628.22216 | I65: 4693.359 | J65: 12664.482 | K65: 25782.944 | L65: 44570.015 | M65: 66103.076 | N65: 92869.909 | O65: 117755.34
A66: Total output tokens | B66: CALC | C66: T | D66: tokens x (1 - input share). | E66: 0.75757576 | F66: 4.2348168 | G66: 19.960536 | H66: 100.51555 | I66: 704.00386 | J66: 1726.9748 | K66: 3314.9499 | L66: 5243.5312 | M66: 7654.0404 | N66: 10613.704 | O66: 13311.473
A67: Total first-party API calls | B67: CALC | C67: B | D67: tokens / tokens-per-call (billions). | E67: 2.1645022 | F67: 10.587042 | G67: 36.291883 | H67: 125.64443 | I67: 586.66988 | J67: 1151.3165 | K67: 1841.6388 | L67: 2621.7656 | M67: 3479.1093 | N67: 4422.3766 | O67: 5119.7975
A68: Memo: calls / contract / day | B68: CALC | C68: # | D68: calls / contracts / 365. | E68: 5930142.9 | F68: 6824845.8 | G68: 2761939.4 | H68: 2206611 | I68: 3214629.5 | J68: 2992686.7 | K68: 2919899.2 | L68: 2896338.5 | M68: 3030781 | N68: 3278165.7 | O68: 3388126.2
A69: COSTS - Inference and infrastructure
A70: Billed tokens (Anthropic-served) | B70: LINK | C70: T | D70: API + consumer + Claude Code (excl Bedrock/Vertex). | E70: 3.3549784 | F70: 20.13238 | G70: 110.93024 | H70: 758.0657 | I70: 5546.3629 | J70: 14778.088 | K70: 29812.134 | L70: 50893.226 | M70: 75206.537 | N70: 105243.61 | O70: 133104.42
A71: Free-tier tokens served | B71: IN | C71: T | D71: Non-billed free-tier usage. | E71: 1.6774892 | F71: 9.059571 | G71: 44.372098 | H71: 265.323 | I71: 1663.9089 | J71: 4137.8648 | K71: 7751.1548 | L71: 12723.307 | M71: 18049.569 | N71: 24206.031 | O71: 29282.971
A72: Internal / testing tokens | B72: IN | C72: T | D72: Evals/red-team/internal. | E72: 1.0064935 | F72: 5.033095 | G72: 22.186049 | H72: 113.70986 | I72: 665.56355 | J72: 1625.5897 | K72: 2981.2134 | L72: 5089.3226 | M72: 6768.5883 | N72: 9471.9252 | O72: 10648.353
A73: Gross tokens served | B73: CALC | C73: T | D73: billed + free + internal. | E73: 6.038961 | F73: 34.225046 | G73: 177.48839 | H73: 1137.0986 | I73: 7875.8353 | J73: 20541.543 | K73: 40544.502 | L73: 68705.856 | M73: 100024.69 | N73: 138921.57 | O73: 173035.74
A74: Tokens per GPU-hour | B74: IN | C74: tok/hr | D74: Serving throughput (back-solved for consistency). | E74: 3731740.6 | F74: 3506161.6 | G74: 3180795.5 | H74: 3135973.5 | I74: 4501295.7 | J74: 4862802 | K74: 5382985.8 | L74: 6087706.5 | M74: 6520508.1 | N74: 7213667.6 | O74: 7511833.8
A75: Required GPU-hours | B75: CALC | C75: hr | D75: gross tokens / tokens-per-GPU-hour. | E75: 1618269.2 | F75: 9761400 | G75: 55800000 | H75: 3.6259826e+08 | I75: 1.7496818e+09 | J75: 4.2242194e+09 | K75: 7.5319727e+09 | L75: 11286000000 | M75: 1.5340015e+10 | N75: 1.9258105e+10 | O75: 2.3035086e+10
A76: Fleet utilization % | B76: IN | C76: % | D76: Effective serving utilization. | E76: 0.55 | F76: 0.58 | G76: 0.62 | H76: 0.66 | I76: 0.7 | J76: 0.72 | K76: 0.74 | L76: 0.75 | M76: 0.76 | N76: 0.77 | O76: 0.78
A77: Total provisioned GPU-hours | B77: CALC | C77: hr | D77: required / utilization. | E77: 2942307.7 | F77: 16830000 | G77: 90000000 | H77: 5.493913e+08 | I77: 2.4995455e+09 | J77: 5.8669714e+09 | K77: 1.0178341e+10 | L77: 15048000000 | M77: 2.0184231e+10 | N77: 2.5010526e+10 | O77: 2.9532162e+10
A78: Blended $/GPU-hour | B78: IN | C78: $ | D78: Owned + rented all-in hourly cost. | E78: 2.6 | F78: 2.5 | G78: 2.4 | H78: 2.3 | I78: 2.2 | J78: 2.1 | K78: 2.05 | L78: 2 | M78: 1.95 | N78: 1.9 | O78: 1.85
A79: Inference compute cost | B79: CALC | C79: $M | D79: Declining share of revenue; GPU-hrs x $/GPU-hr. | E79: 7.65 | F79: 42.075 | G79: 216 | H79: 1263.6 | I79: 5499 | J79: 12320.64 | K79: 20865.6 | L79: 30096 | M79: 39359.25 | N79: 47520 | O79: 54634.5
A80: Data egress volume (PB) | B80: IN | C80: PB | D80: Outbound data volume. | E80: 0.5 | F80: 2.55 | G80: 12 | H80: 62.4 | I80: 240 | J80: 496 | K80: 828 | L80: 1200 | M80: 1572.5 | N80: 1892 | O80: 2205
A81: Egress cost ($/TB) | B81: IN | C81: $ | D81: Blended egress unit cost. | E81: 20 | F81: 18 | G81: 16 | H81: 14 | I81: 12 | J81: 11 | K81: 10 | L81: 9 | M81: 9 | N81: 8 | O81: 8
... A84: API gateway and load-balancing | B84: IN | C84: $M | D84: Edge/gateway/LB. | E84: 0.3 | F84: 1.7 | G84: 6 | H84: 28.6 | I84: 100 | J84: 198.4 | K84: 316.8 | L84: 448 | M84: 578 | N84: 686.4 | O84: 792
A85: COSTS - SAFETY, PAYMENTS, SUPPORT
A86: Content moderation cost $/Mtok | B86: IN | C86: $ | D86: Classifier cost per Mtok gross. | E86: 0.05 | F86: 0.05 | G86: 0.04 | H86: 0.035 | I86: 0.03 | J86: 0.028 | K86: 0.026 | L86: 0.025 | M86: 0.024 | N86: 0.023 | O86: 0.022
A87: Automated moderation cost | B87: CALC | C87: $M | D87: gross tokens x $/Mtok. | E87: 0.30194805 | F87: 1.7112523 | G87: 7.0995356 | H87: 39.798449 | I87: 236.27506 | J87: 575.1632 | K87: 1054.157 | L87: 1717.6464 | M87: 2400.5927 | N87: 3195.1961 | O87: 3806.7863
A88: HITL review volume | B88: IN | C88: Count | D88: Human safety reviews / yr. | E88: 20000 | F88: 102000 | G88: 420000 | H88: 1820000 | I88: 6000000 | J88: 11780000 | K88: 18720000 | L88: 26400000 | M88: 33150000 | N88: 38720000 | O88: 43200000
A89: Cost per HITL review | B89: IN | C89: $ | D89: BPO hourly x hours. | E89: 4 | F89: 4 | G89: 3.8 | H89: 3.6 | I89: 3.5 | J89: 3.4 | K89: 3.3 | L89: 3.2 | M89: 3.2 | N89: 3.1 | O89: 3
A90: HITL review cost | B90: CALC | C90: $M | D90: volume x cost. | E90: 0.08 | F90: 0.408 | G90: 1.596 | H90: 6.552 | I90: 21 | J90: 40.052 | K90: 61.776 | L90: 84.48 | M90: 106.08 | N90: 120.032 | O90: 129.6
A91: B2B gross cash collections | B91: LINK | C91: $M | D91: API + seats + CC + FT + PT + PS. | E91: 10 | F91: 72.08 | G91: 448.74 | H91: 3340.48 | I91: 17671 | J91: 45348.04 | K91: 81878.4 | L91: 125182.4 | M91: 173974.6 | N91: 223209.36 | O91: 272734.2
A92: Payment processing fee % (Stripe) | B92: IN | C92: % | D92: Blended processor fee. | E92: 0.029 | F92: 0.028 | G92: 0.027 | H92: 0.026 | I92: 0.025 | J92: 0.024 | K92: 0.024 | L92: 0.023 | M92: 0.023 | N92: 0.022 | O92: 0.022
A93: B2B payment processing cost | B93: CALC | C93: $M | D93: collections x fee. | E93: 0.29 | F93: 2.01824 | G93: 12.11598 | H93: 86.85248 | I93: 441.775 | J93: 1088.353 | K93: 1965.0816 | L93: 2879.1952 | M93: 4001.4158 | N93: 4910.6059 | O93: 6000.1524
A94: Mobile share of consumer revenue % | B94: IN | C94: % | D94: Consumer via mobile stores. | E94: 0 | F94: 0.2 | G94: 0.3 | H94: 0.35 | I94: 0.38 | J94: 0.4 | K94: 0.4 | L94: 0.4 | M94: 0.39 | N94: 0.39 | O94: 0.38
A95: B2C mobile collections | B95: CALC | C95: $M | D95: consumer rev x mobile share. | E95: 0 | F95: 1.36 | G95: 21.6 | H95: 236.6 | I95: 1254 | J95: 2777.6 | K95: 4636.8 | L95: 6720 | M95: 8585.85 | N95: 10330.32 | O95: 11730.6
A96: App store take-rate % | B96: IN | C96: % | D96: Apple/Google store take. | E96: 0 | F96: 0.3 | G96: 0.3 | H96: 0.28 | I96: 0.2 | J96: 0.2 | K96: 0.18 | L96: 0.18 | M96: 0.17 | N96: 0.17 | O96: 0.15
A97: App store cost | B97: CALC | C97: $M | D97: mobile collections x take. | E97: 0 | F97: 0.408 | G97: 6.48 | H97: 66.248 | I97: 250.8 | J97: 555.52 | K97: 834.624 | L97: 1209.6 | M97: 1459.5945 | N97: 1756.1544 | O97: 1759.59
... A106: Memo: implied gross margin % | B106: CALC | C106: % | D106: Inference-only gross margin. | E106: 0.11560519 | F106: 0.41918362 | G106: 0.57679914 | H106: 0.6764845 | I106: 0.71825191 | J106: 0.73843791 | K106: 0.74879308 | L106: 0.75823753 | M106: 0.76804274 | N106: 0.7778002 | O106: 0.78821487
A107: OpEx & Comp (ex-SBC)
A108: R&D headcount | B108: IN | C108: count | D108: Research + eng (~65-75% of total). | E108: 40 | F108: 130 | G108: 270 | H108: 700 | I108: 3250 | J108: 4800 | K108: 6000 | L108: 6900 | M108: 7500 | N108: 7900 | O108: 8300
A109: Fully-burdened R&D cash comp ($/head) | B109: IN | C109: $ | D109: Levels.fyi eng $619-841k, research ~$746k median. | E109: 400000 | F109: 420000 | G109: 450000 | H109: 480000 | I109: 520000 | J109: 545000 | K109: 565000 | L109: 580000 | M109: 595000 | N109: 605000 | O109: 615000
A110: R&D personnel cost | B110: CALC | C110: $M | D110: heads x comp. | E110: 16 | F110: 54.6 | G110: 121.5 | H110: 336 | I110: 1690 | J110: 2616 | K110: 3390 | L110: 4002 | M110: 4462.5 | N110: 4779.5 | O110: 5104.5
A111: RLHF & data annotation | B111: IN | C111: $M | D111: Human feedback/annotation. | E111: 2 | F111: 8 | G111: 60 | H111: 300 | I111: 620 | J111: 900 | K111: 1150 | L111: 1400 | M111: 1600 | N111: 1750 | O111: 1900
A112: Proprietary data licensing | B112: IN | C112: $M | D112: Licensed training data. | E112: 0 | F112: 3 | G112: 25 | H112: 120 | I112: 400 | J112: 620 | K112: 820 | L112: 1000 | M112: 1150 | N112: 1280 | O112: 1400
A113: Experimental / failed training runs | B113: IN | C113: $M | D113: Abandoned run compute. | E113: 3 | F113: 12 | G113: 90 | H113: 380 | I113: 620 | J113: 850 | K113: 1050 | L113: 1250 | M113: 1400 | N113: 1520 | O113: 1650
A114: Internal tooling & subscriptions | B114: IN | C114: $M | D114: Dev tooling/SaaS. | E114: 1 | F114: 4 | G114: 30 | H114: 150 | I114: 380 | J114: 560 | K114: 720 | L114: 880 | M114: 1010 | N114: 1130 | O114: 1240
A115: Capitalizable frontier-training runs | B115: IN | C115: $M | D115: Capitalizable portion (~30% of training). | E115: 9.24 | F115: 26.928 | G115: 554.4 | H115: 555.984 | I115: 2667.72 | J115: 5270.496 | K115: 7983.36 | L115: 10433.28 | M115: 12644.94 | N115: 14636.16 | O115: 16026.12
A116: Cap toggle (1=capitalized, 0=ASC 730 expense) | B116: IN | C116: 0/1 | D116: 0 = expense training to R&D (base). | E116: 0 | F116: 0 | G116: 0 | H116: 0 | I116: 0 | J116: 0 | K116: 0 | L116: 0 | M116: 0 | N116: 0 | O116: 0
A117: Training compute expenses to R&D | B117: CALC | C117: $M | D117: Training (expensed) + research compute. Primary loss driver. | E117: 36.8 | F117: 111.01 | G117: 2178 | H117: 2321.28 | I117: 11007.4 | J117: 22131.52 | K117: 33667.2 | L117: 43897.6 | M117: 53603.55 | N117: 61987.2 | O117: 67797.9
A118: Total R&D (ex-SBC) | B118: CALC | C118: $M | D118: Personnel + RLHF + licensing + failed + tooling + training. | E118: 58.8 | F118: 192.61 | G118: 2504.5 | H118: 3607.28 | I118: 14717.4 | J118: 27677.52 | K118: 40797.2 | L118: 52429.6 | M118: 63226.05 | N118: 72446.7 | O118: 79092.4
A119: S&M Headcount | B119: IN | C119: count | D119: GTM heads (small org). | E119: 8 | F119: 30 | G119: 70 | H119: 180 | I119: 900 | J119: 1450 | K119: 1900 | L119: 2250 | M119: 2500 | N119: 2700 | O119: 2850
... A133: One-time litigation services | B133: IN | C133: $M | D133: Non-recurring litigation. | E133: 0 | F133: 0 | G133: 5 | H133: 40 | I133: 150 | J133: 90 | K133: 60 | L133: 50 | M133: 45 | N133: 40 | O133: 40
A134: STOCK BASED COMP
A135: SBC issue rate (% of base cash comp) | B135: IN | C135: % | D135: RSU grant value as % of cash comp. | E135: 0.4 | F135: 0.45 | G135: 0.5 | H135: 0.55 | I135: 0.55 | J135: 0.5 | K135: 0.45 | L135: 0.42 | M135: 0.4 | N135: 0.38 | O135: 0.36
A136: R&D SBC | B136: CALC | C136: $M | D136: R&D cash x SBC rate. | E136: 6.4 | F136: 24.57 | G136: 60.75 | H136: 184.8 | I136: 929.5 | J136: 1308 | K136: 1525.5 | L136: 1680.84 | M136: 1785 | N136: 1816.21 | O136: 1837.62
A137: S&M SBC | B137: CALC | C137: $M | D137: S&M cash x SBC rate. | E137: 0.896 | F137: 3.915 | G137: 10.5 | H137: 30.69 | I137: 158.4 | J137: 239.25 | K137: 290.7 | L137: 330.75 | M137: 358 | N137: 374.49 | O137: 381.672
A138: G&A SBC | B138: CALC | C138: $M | D138: G&A cash x SBC rate. | E138: 1.248 | F138: 3.888 | G138: 8.4 | H138: 27.115 | I138: 140.25 | J138: 192.5 | K138: 226.8 | L138: 250.194 | M138: 262.4 | N138: 279.224 | O138: 287.64
A139: Total SBC | B139: CALC | C139: $M | D139: Sum of function SBC. | E139: 8.544 | F139: 32.373 | G139: 79.65 | H139: 242.605 | I139: 1228.15 | J139: 1739.75 | K139: 2043 | L139: 2261.784 | M139: 2405.4 | N139: 2469.924 | O139: 2506.932
A140: DEPRECIATION & AMORTIZATION
A141: Amort life - models (yrs) | B141: IN | C141: yr | D141: Life of capitalized models. | E141: 2 | F141: 2 | G141: 2 | H141: 2 | I141: 2 | J141: 2 | K141: 2 | L141: 2 | M141: 2 | N141: 2 | O141: 2
A142: Amort of capitalized frontier models | B142: CALC | C142: $M | D142: 2-yr straight-line of cap pool. | E142: 4.62 | F142: 18.084 | G142: 290.664 | H142: 555.192 | I142: 1611.852 | J142: 3969.108 | K142: 6626.928 | L142: 9208.32 | M142: 11539.11 | N142: 13640.55 | O142: 15331.14
A143: Owned GPU / datacenter capex | B143: IN | C143: $M | D143: Owned hardware capex (Fluidstack $50B ramps 2026+). | E143: 2 | F143: 8 | G143: 40 | H143: 220 | I143: 1400 | J143: 3200 | K143: 5000 | L143: 6500 | M143: 7500 | N143: 8200 | O143: 8800
A144: Depreciation life - HW (yrs) | B144: IN | C144: yr | D144: Life of owned accelerators. | E144: 4 | F144: 4 | G144: 4 | H144: 5 | I144: 5 | J144: 5 | K144: 6 | L144: 6 | M144: 6 | N144: 6 | O144: 6
A145: Depreciation of owned GPU / datacenter | B145: CALC | C145: $M | D145: Vintage straight-line depreciation. | E145: 0.5 | F145: 2.5 | G145: 12.5 | H145: 56.5 | I145: 336 | J145: 974 | K145: 1797.3333 | L145: 2880.6667 | M145: 4086.6667 | N145: 5173.3333 | O145: 6000
A146: Amort of prepaid cloud commits (reclass) | B146: MEMO | C146: $M | D146: Reclass memo. NOT added to P&L D&A (guard). | E146: 0 | F146: 0 | G146: 20 | H146: 120 | I146: 500 | J146: 800 | K146: 1050 | L146: 1300 | M146: 1500 | N146: 1650 | O146: 1800
A147: Total D&A | B147: CALC | C147: $M | D147: Model amort + owned HW dep (prepaid-cloud excluded). | E147: 5.12 | F147: 20.584 | G147: 303.164 | H147: 611.692 | I147: 1947.852 | J147: 4943.108 | K147: 8424.2613 | L147: 12088.987 | M147: 15625.777 | N147: 18813.883 | O147: 21331.14
A148: P&L SUMMARY (memo)
A149: Gross profit | B149: CALC | C149: $M | D149: Revenue - cost of revenue. | E149: 1.1560519 | F149: 35.630608 | G149: 346.07948 | H149: 3165.9475 | I149: 16878.92 | J149: 42120.499 | K149: 75478.342 | L149: 115252.1 | M149: 159944.9 | N149: 205339.25 | O149: 251834.65
A150: Operating income (ex-SBC) | B150: CALC | C150: $M | D150: GP - R&D - S&M - G&A - D&A. | E150: -70.123948 | F150: -205.90339 | G150: -2580.3845 | H150: -1638.1245 | I150: -2119.3321 | J150: 5866.3707 | K150: 21556.881 | L150: 45080.318 | M150: 74637.074 | N150: 106901.37 | O150: 143626.91
A151: Operating income (incl-SBC) | B151: CALC | C151: $M | D151: After stock-based comp. | E151: -78.667948 | F151: -238.27639 | G151: -2660.0345 | H151: -1880.7295 | I151: -3347.4821 | J151: 4126.6207 | K151: 19513.881 | L151: 42818.534 | M151: 72231.674 | N151: 104431.45 | O151: 141119.98
...

Sheet D5
A1: Worst/Run-rate (data block D5)
A2: Line Item | B2: Type | C2: Unit | D2: What it is | E2: 2022 | F2: 2023 | G2: 2024 | H2: 2025 | I2: 2026 | J2: 2027 | K2: 2028 | L2: 2029 | M2: 2030 | N2: 2031 | O2: 2032
A3: REVENUE
A4: Booked revenue | B4: IN | C4: $M | D4: Anchor. 2022-26 PitchBook TTM (10/100/1,000/9,000/47,000); 2027-32 base case. PB carries 55,000 for 2027 as a conservative mark. | E4: 10 | F4: 100 | G4: 1000 | H4: 9000 | I4: 47000 | J4: 68000 | K4: 90000 | L4: 112000 | M4: 135000 | N4: 158000 | O4: 178000
A5: API PRICING AND BLENDED EFFECTIVE RATE
A6: Model mix % - Mythos | B6: IN | C6: % | D6: Token share, flagship tier (Fable 5 / Mythos 5, $10/$50). Introduced 2026. | E6: 0 | F6: 0 | G6: 0 | H6: 0 | I6: 0.03 | J6: 0.05 | K6: 0.06 | L6: 0.07 | M6: 0.08 | N6: 0.09 | O6: 0.1
A7: Model mix % - Opus | B7: IN | C7: % | D7: Token share, Opus ($15/$75 to Aug-2025, cut to $5/$25 at Opus 4.5). | E7: 0 | F7: 0.1 | G7: 0.08 | H7: 0.1 | I7: 0.12 | J7: 0.12 | K7: 0.12 | L7: 0.12 | M7: 0.12 | N7: 0.12 | O7: 0.12
A8: Model mix % - Sonnet | B8: IN | C8: % | D8: Token share, Sonnet workhorse ($3/$15). | E8: 0.4 | F8: 0.3 | G8: 0.32 | H8: 0.45 | I8: 0.45 | J8: 0.44 | K8: 0.43 | L8: 0.42 | M8: 0.41 | N8: 0.4 | O8: 0.4
A9: Model mix % - Haiku | B9: IN | C9: % | D9: Token share, Haiku ($0.25/$1.25 -> $1/$5). | E9: 0.6 | F9: 0.6 | G9: 0.6 | H9: 0.45 | I9: 0.4 | J9: 0.39 | K9: 0.39 | L9: 0.39 | M9: 0.39 | N9: 0.39 | O9: 0.38
A10: List input $/Mtok - Mythos | B10: IN | C10: $ | D10: List input price, flagship. | E10: 15 | F10: 15 | G10: 15 | H10: 15 | I10: 15 | J10: 15 | K10: 14 | L10: 13 | M10: 12 | N10: 12 | O10: 11
A11: List input $/Mtok - Opus | B11: IN | C11: $ | D11: List input price, Opus. | E11: 11 | F11: 8 | G11: 15 | H11: 15 | I11: 5 | J11: 5 | K11: 5 | L11: 4.5 | M11: 4.5 | N11: 4 | O11: 4
A12: List input $/Mtok - Sonnet | B12: IN | C12: $ | D12: List input price, Sonnet. | E12: 3 | F12: 3 | G12: 3 | H12: 3 | I12: 3 | J12: 3 | K12: 3 | L12: 2.5 | M12: 2.5 | N12: 2 | O12: 2
A13: List input $/Mtok - Haiku | B13: IN | C13: $ | D13: List input price, Haiku. | E13: 0.8 | F13: 0.8 | G13: 0.25 | H13: 0.8 | I13: 1 | J13: 1 | K13: 1 | L13: 0.9 | M13: 0.9 | N13: 0.8 | O13: 0.8
A14: List output $/Mtok - Mythos | B14: IN | C14: $ | D14: List output price, flagship. | E14: 75 | F14: 75 | G14: 75 | H14: 75 | I14: 75 | J14: 70 | K14: 65 | L14: 60 | M14: 55 | N14: 55 | O14: 50
A15: List output $/Mtok - Opus | B15: IN | C15: $ | D15: List output price, Opus. | E15: 33 | F15: 24 | G15: 75 | H15: 75 | I15: 25 | J15: 25 | K15: 22 | L15: 22 | M15: 20 | N15: 20 | O15: 18
A16: List output $/Mtok - Sonnet | B16: IN | C16: $ | D16: List output price, Sonnet. | E16: 15 | F16: 15 | G16: 15 | H16: 15 | I16: 15 | J16: 15 | K16: 13 | L16: 13 | M16: 12 | N16: 10 | O16: 10
A17: List output $/Mtok - Haiku | B17: IN | C17: $ | D17: List output price, Haiku. | E17: 2.4 | F17: 2.4 | G17: 1.25 | H17: 4 | I17: 5 | J17: 5 | K17: 4.5 | L17: 4.5 | M17: 4 | N17: 4 | O17: 3.6
... A27: Blended effective $/Mtok | B27: CALC | C27: $ | D27: Mix-weighted, adjusted for input share, caching, batch. | E27: 2.9806452 | F27: 3.4768421 | G27: 3.793749 | H27: 4.1467112 | I27: 3.0571739 | J27: 2.9587834 | K27: 2.6527823 | L27: 2.3780343 | M27: 2.2407352 | N27: 2.0581018 | O27: 1.9921081
A28: NON-API REVENUE STREAMS
A29: # Enterprise contracts (>$1M ARR) | B29: IN | C29: count | D29: ~1,000+ at $1M+ ACV by 2026. | E29: 0 | F29: 5 | G29: 60 | H29: 300 | I29: 1000 | J29: 1700 | K29: 2400 | L29: 3100 | M29: 3700 | N29: 4200 | O29: 4600
A30: Committed-use discount % (memo) | B30: IN | C30: % | D30: Volume discount realized on enterprise API. | E30: 0 | F30: 0.05 | G30: 0.1 | H30: 0.12 | I30: 0.15 | J30: 0.15 | K30: 0.16 | L30: 0.16 | M30: 0.17 | N30: 0.17 | O30: 0.18
A31: Active enterprise dashboard seats | B31: IN | C31: count | D31: Console/admin seats. | E31: 0 | F31: 2000 | G31: 40000 | H31: 250000 | I31: 900000 | J31: 1600000 | K31: 2300000 | L31: 3000000 | M31: 3600000 | N31: 4100000 | O31: 4500000
A32: Enterprise platform fee / seat / mo | B32: IN | C32: $ | D32: Monthly platform fee per seat. | E32: 0 | F32: 30 | G32: 35 | H32: 40 | I32: 45 | J32: 48 | K32: 50 | L32: 52 | M32: 54 | N32: 55 | O32: 56
A33: Enterprise seat revenue | B33: CALC | C33: $M | D33: seats x fee x 12. | E33: 0 | F33: 0.72 | G33: 16.8 | H33: 120 | I33: 486 | J33: 921.6 | K33: 1380 | L33: 1872 | M33: 2332.8 | N33: 2706 | O33: 3024
A34: Consumer subscription revenue (anchor) | B34: IN | C34: $M | D34: Claude Pro ($20) + Max ($100/$200). | E34: 0 | F34: 8 | G34: 120 | H34: 1300 | I34: 6600 | J34: 11200 | K34: 16100 | L34: 21000 | M34: 25900 | N34: 30100 | O34: 34300
A35: Blended consumer ARPU ($/mo) | B35: IN | C35: $ | D35: Blend of Pro and Max. | E35: 20 | F35: 20 | G35: 21 | H35: 23 | I35: 26 | J35: 28 | K35: 29 | L35: 30 | M35: 31 | N35: 32 | O35: 33
A36: Paying consumer subs (implied) | B36: PLUG | C36: Count | D36: consumer rev / (ARPU x 12). | E36: 0 | F36: 33333.333 | G36: 476190.48 | H36: 4710144.9 | I36: 21153846 | J36: 33333333 | K36: 46264368 | L36: 58333333 | M36: 69623656 | N36: 78385417 | O36: 86616162
A37: Active developer seats | B37: IN | C37: Count | D37: Claude Code seats (Feb-2025). | E37: 0 | F37: 0 | G37: 0 | H37: 350000 | I37: 1100000 | J37: 1800000 | K37: 2500000 | L37: 3100000 | M37: 3600000 | N37: 4000000 | O37: 4300000
A38: Base seat fee ($/mo) | B38: IN | C38: $ | D38: Claude Code base seat fee. | E38: 0 | F38: 0 | G38: 0 | H38: 20 | I38: 22 | J38: 24 | K38: 25 | L38: 26 | M38: 27 | N38: 28 | O38: 28
A39: Claude Code base seat revenue | B39: CALC | C39: $M | D39: seats x fee x 12. | E39: 0 | F39: 0 | G39: 0 | H39: 84 | I39: 290.4 | J39: 518.4 | K39: 750 | L39: 967.2 | M39: 1166.4 | N39: 1344 | O39: 1444.8
A40: Avg overage tokens / dev / mo | B40: IN | C40: Mtok | D40: Usage above base seat. | E40: 0 | F40: 0 | G40: 0 | H40: 12 | I40: 20 | J40: 26 | K40: 30 | L40: 33 | M40: 36 | N40: 38 | O40: 40
... A60: Total non-API revenue | B60: CALC | C60: $M | D60: Sum of non-API streams. | E60: 0 | F60: 17.72 | G60: 300.115 | H60: 3188.7792 | I60: 13998.754 | J60: 23319.133 | K60: 32789.275 | L60: 41925.307 | M60: 50563.131 | N60: 57976.56 | O60: 64889.009
A61: FIRST PARTY DIRECT API REVENUE
A62: First-party API revenue | B62: PLUG | C62: $M | D62: Booked revenue minus non-API streams. | E62: 10 | F62: 82.28 | G62: 699.885 | H62: 5811.2208 | I62: 33001.246 | J62: 44680.867 | K62: 57210.725 | L62: 70074.693 | M62: 84436.869 | N62: 100023.44 | O62: 113110.99
A63: API TOKEN ENGINE
A64: Total tokens processed (all) | B64: PLUG | C64: T | D64: API revenue / blended $/Mtok (trillions). | E64: 3.3549784 | F64: 23.665153 | G64: 184.48374 | H64: 1401.4047 | I64: 10794.69 | J64: 15101.095 | K64: 21566.31 | L64: 29467.487 | M64: 37682.663 | N64: 48599.851 | O64: 56779.544
A65: Total input tokens | B65: CALC | C65: T | D65: tokens x input share. | E65: 2.5974026 | F65: 18.683015 | G65: 151.21618 | H65: 1208.1075 | I65: 9386.6874 | J65: 13288.963 | K65: 19109.388 | L65: 26365.646 | M65: 33772.198 | N65: 43615.251 | O65: 51012.872
A66: Total output tokens | B66: CALC | C66: T | D66: tokens x (1 - input share). | E66: 0.75757576 | F66: 4.9821375 | G66: 33.26756 | H66: 193.29721 | I66: 1408.0031 | J66: 1812.1313 | K66: 2456.9213 | L66: 3101.8407 | M66: 3910.4651 | N66: 4984.6001 | O66: 5766.6724
A67: Total first-party API calls | B67: CALC | C67: B | D67: tokens / tokens-per-call (billions). | E67: 2.1645022 | F67: 12.455344 | G67: 60.486472 | H67: 241.62151 | I67: 1173.3359 | J67: 1208.0876 | K67: 1364.9563 | L67: 1550.9203 | M67: 1777.4841 | N67: 2076.9167 | O67: 2217.9509
A68: Memo: calls / contract / day | B68: CALC | C68: # | D68: calls / contracts / 365. | E68: 5930142.9 | F68: 6824845.8 | G68: 2761939.4 | H68: 2206589.1 | I68: 3214619 | J68: 1946958.2 | K68: 1558169.3 | L68: 1370676.4 | M68: 1316167.4 | N68: 1354805.4 | O68: 1320995.2
A69: COSTS - Inference and infrastructure
A70: Billed tokens (Anthropic-served) | B70: LINK | C70: T | D70: API + consumer + Claude Code (excl Bedrock/Vertex). | E70: 3.3549784 | F70: 23.685153 | G70: 184.88374 | H70: 1457.8047 | I70: 11092.69 | J70: 15724.695 | K70: 22558.31 | L70: 30817.087 | M70: 39387.863 | N70: 50599.851 | O70: 59043.544
A71: Free-tier tokens served | B71: IN | C71: T | D71: Non-billed free-tier usage. | E71: 1.6774892 | F71: 10.658319 | G71: 73.953496 | H71: 510.23166 | I71: 3327.8071 | J71: 4402.9145 | K71: 5865.1605 | L71: 7704.2716 | M71: 9453.0872 | N71: 11637.966 | O71: 12989.58
A72: Internal / testing tokens | B72: IN | C72: T | D72: Evals/red-team/internal. | E72: 1.0064935 | F72: 5.9212882 | G72: 36.976748 | H72: 218.67071 | I72: 1331.1229 | J72: 1729.7164 | K72: 2255.831 | L72: 3081.7087 | M72: 3544.9077 | N72: 4553.9866 | O72: 4723.4835
A73: Gross tokens served | B73: CALC | C73: T | D73: billed + free + internal. | E73: 6.038961 | F73: 40.26476 | G73: 295.81398 | H73: 2186.7071 | I73: 15751.62 | J73: 21857.325 | K73: 30679.301 | L73: 41603.067 | M73: 52385.858 | N73: 66791.803 | O73: 76756.607
A74: Tokens per GPU-hour | B74: IN | C74: tok/hr | D74: Serving throughput (back-solved for consistency). | E74: 2998720.1 | F74: 2817451.3 | G74: 2555996.4 | H74: 2519954.7 | I74: 3617101.1 | J74: 3487752.3 | K74: 3665888.4 | L74: 4020086.1 | M74: 4233153.3 | N74: 4656728.7 | O74: 4806193.7
A75: Required GPU-hours | B75: CALC | C75: hr | D75: gross tokens / tokens-per-GPU-hour. | E75: 2013846.2 | F75: 14291200 | G75: 1.1573333e+08 | H75: 8.6775652e+08 | I75: 4.3547636e+09 | J75: 6266880000 | K75: 8.3688585e+09 | L75: 10348800000 | M75: 1.2375138e+10 | N75: 1.4343074e+10 | O75: 1.5970352e+10
A76: Fleet utilization % | B76: IN | C76: % | D76: Effective serving utilization. | E76: 0.55 | F76: 0.58 | G76: 0.62 | H76: 0.66 | I76: 0.7 | J76: 0.72 | K76: 0.74 | L76: 0.75 | M76: 0.76 | N76: 0.77 | O76: 0.78
A77: Total provisioned GPU-hours | B77: CALC | C77: hr | D77: required / utilization. | E77: 3661538.5 | F77: 24640000 | G77: 1.8666667e+08 | H77: 1.3147826e+09 | I77: 6.2210909e+09 | J77: 8704000000 | K77: 1.1309268e+10 | L77: 13798400000 | M77: 1.6283077e+10 | N77: 1.8627368e+10 | O77: 2.0474811e+10
A78: Blended $/GPU-hour | B78: IN | C78: $ | D78: Owned + rented all-in hourly cost. | E78: 2.6 | F78: 2.5 | G78: 2.4 | H78: 2.3 | I78: 2.2 | J78: 2.1 | K78: 2.05 | L78: 2 | M78: 1.95 | N78: 1.9 | O78: 1.85
A79: Inference compute cost | B79: CALC | C79: $M | D79: Declining share of revenue; GPU-hrs x $/GPU-hr. | E79: 9.52 | F79: 61.6 | G79: 448 | H79: 3024 | I79: 13686.4 | J79: 18278.4 | K79: 23184 | L79: 27596.8 | M79: 31752 | N79: 35392 | O79: 37878.4
A80: Data egress volume (PB) | B80: IN | C80: PB | D80: Outbound data volume. | E80: 0.5 | F80: 3 | G80: 20 | H80: 120 | I80: 480 | J80: 800 | K80: 1150 | L80: 1500 | M80: 1850 | N80: 2150 | O80: 2450
A81: Egress cost ($/TB) | B81: IN | C81: $ | D81: Blended egress unit cost. | E81: 20 | F81: 18 | G81: 16 | H81: 14 | I81: 12 | J81: 11 | K81: 10 | L81: 9 | M81: 9 | N81: 8 | O81: 8
... A84: API gateway and load-balancing | B84: IN | C84: $M | D84: Edge/gateway/LB. | E84: 0.3 | F84: 2 | G84: 10 | H84: 55 | I84: 200 | J84: 320 | K84: 440 | L84: 560 | M84: 680 | N84: 780 | O84: 880
A85: COSTS - SAFETY, PAYMENTS, SUPPORT
A86: Content moderation cost $/Mtok | B86: IN | C86: $ | D86: Classifier cost per Mtok gross. | E86: 0.05 | F86: 0.05 | G86: 0.04 | H86: 0.035 | I86: 0.03 | J86: 0.028 | K86: 0.026 | L86: 0.025 | M86: 0.024 | N86: 0.023 | O86: 0.022
A87: Automated moderation cost | B87: CALC | C87: $M | D87: gross tokens x $/Mtok. | E87: 0.30194805 | F87: 2.013238 | G87: 11.832559 | H87: 76.534749 | I87: 472.54861 | J87: 612.00511 | K87: 797.66183 | L87: 1040.0767 | M87: 1257.2606 | N87: 1536.2115 | O87: 1688.6454
A88: HITL review volume | B88: IN | C88: Count | D88: Human safety reviews / yr. | E88: 20000 | F88: 120000 | G88: 700000 | H88: 3500000 | I88: 12000000 | J88: 19000000 | K88: 26000000 | L88: 33000000 | M88: 39000000 | N88: 44000000 | O88: 48000000
A89: Cost per HITL review | B89: IN | C89: $ | D89: BPO hourly x hours. | E89: 4 | F89: 4 | G89: 3.8 | H89: 3.6 | I89: 3.5 | J89: 3.4 | K89: 3.3 | L89: 3.2 | M89: 3.2 | N89: 3.1 | O89: 3
A90: HITL review cost | B90: CALC | C90: $M | D90: volume x cost. | E90: 0.08 | F90: 0.48 | G90: 2.66 | H90: 12.6 | I90: 42 | J90: 64.6 | K90: 85.8 | L90: 105.6 | M90: 124.8 | N90: 136.4 | O90: 144
A91: B2B gross cash collections | B91: LINK | C91: $M | D91: API + seats + CC + FT + PT + PS. | E91: 10 | F91: 84.8 | G91: 747.9 | H91: 6424 | I91: 35342 | J91: 49142 | K91: 63720 | L91: 78478 | M91: 94676 | N91: 111647 | O91: 126038
A92: Payment processing fee % (Stripe) | B92: IN | C92: % | D92: Blended processor fee. | E92: 0.029 | F92: 0.028 | G92: 0.027 | H92: 0.026 | I92: 0.025 | J92: 0.024 | K92: 0.024 | L92: 0.023 | M92: 0.023 | N92: 0.022 | O92: 0.022
A93: B2B payment processing cost | B93: CALC | C93: $M | D93: collections x fee. | E93: 0.29 | F93: 2.3744 | G93: 20.1933 | H93: 167.024 | I93: 883.55 | J93: 1179.408 | K93: 1529.28 | L93: 1804.994 | M93: 2177.548 | N93: 2456.234 | O93: 2772.836
A94: Mobile share of consumer revenue % | B94: IN | C94: % | D94: Consumer via mobile stores. | E94: 0 | F94: 0.2 | G94: 0.3 | H94: 0.35 | I94: 0.38 | J94: 0.4 | K94: 0.4 | L94: 0.4 | M94: 0.39 | N94: 0.39 | O94: 0.38
A95: B2C mobile collections | B95: CALC | C95: $M | D95: consumer rev x mobile share. | E95: 0 | F95: 1.6 | G95: 36 | H95: 455 | I95: 2508 | J95: 4480 | K95: 6440 | L95: 8400 | M95: 10101 | N95: 11739 | O95: 13034
A96: App store take-rate % | B96: IN | C96: % | D96: Apple/Google store take. | E96: 0 | F96: 0.3 | G96: 0.3 | H96: 0.28 | I96: 0.2 | J96: 0.2 | K96: 0.18 | L96: 0.18 | M96: 0.17 | N96: 0.17 | O96: 0.15
A97: App store cost | B97: CALC | C97: $M | D97: mobile collections x take. | E97: 0 | F97: 0.48 | G97: 10.8 | H97: 127.4 | I97: 501.6 | J97: 896 | K97: 1159.2 | L97: 1512 | M97: 1717.17 | N97: 1995.63 | O97: 1955.1
... A106: Memo: implied gross margin % | B106: CALC | C106: % | D106: Inference-only gross margin. | E106: -0.071394805 | F106: 0.29818362 | G106: 0.48879914 | H106: 0.61048458 | I106: 0.66105194 | J106: 0.68267008 | K106: 0.69437195 | L106: 0.70526171 | M106: 0.71718843 | N106: 0.72890351 | O106: 0.74201122
A107: OpEx & Comp (ex-SBC)
A108: R&D headcount | B108: IN | C108: count | D108: Research + eng (~65-75% of total). | E108: 40 | F108: 130 | G108: 270 | H108: 700 | I108: 3250 | J108: 4800 | K108: 6000 | L108: 6900 | M108: 7500 | N108: 7900 | O108: 8300
A109: Fully-burdened R&D cash comp ($/head) | B109: IN | C109: $ | D109: Levels.fyi eng $619-841k, research ~$746k median. | E109: 400000 | F109: 420000 | G109: 450000 | H109: 480000 | I109: 520000 | J109: 545000 | K109: 565000 | L109: 580000 | M109: 595000 | N109: 605000 | O109: 615000
A110: R&D personnel cost | B110: CALC | C110: $M | D110: heads x comp. | E110: 16 | F110: 54.6 | G110: 121.5 | H110: 336 | I110: 1690 | J110: 2616 | K110: 3390 | L110: 4002 | M110: 4462.5 | N110: 4779.5 | O110: 5104.5
A111: RLHF & data annotation | B111: IN | C111: $M | D111: Human feedback/annotation. | E111: 2 | F111: 8 | G111: 60 | H111: 300 | I111: 620 | J111: 900 | K111: 1150 | L111: 1400 | M111: 1600 | N111: 1750 | O111: 1900
A112: Proprietary data licensing | B112: IN | C112: $M | D112: Licensed training data. | E112: 0 | F112: 3 | G112: 25 | H112: 120 | I112: 400 | J112: 620 | K112: 820 | L112: 1000 | M112: 1150 | N112: 1280 | O112: 1400
A113: Experimental / failed training runs | B113: IN | C113: $M | D113: Abandoned run compute. | E113: 3 | F113: 12 | G113: 90 | H113: 380 | I113: 620 | J113: 850 | K113: 1050 | L113: 1250 | M113: 1400 | N113: 1520 | O113: 1650
A114: Internal tooling & subscriptions | B114: IN | C114: $M | D114: Dev tooling/SaaS. | E114: 1 | F114: 4 | G114: 30 | H114: 150 | I114: 380 | J114: 560 | K114: 720 | L114: 880 | M114: 1010 | N114: 1130 | O114: 1240
A115: Capitalizable frontier-training runs | B115: IN | C115: $M | D115: Capitalizable portion (~30% of training). | E115: 12.39 | F115: 42.48 | G115: 1239 | H115: 1433.7 | I115: 7154.34 | J115: 8425.2 | K115: 9558 | L115: 10308.48 | M115: 10991.7 | N115: 11745.72 | O115: 11972.28
A116: Cap toggle (1=capitalized, 0=ASC 730 expense) | B116: IN | C116: 0/1 | D116: 0 = expense training to R&D (base). | E116: 0 | F116: 0 | G116: 0 | H116: 0 | I116: 0 | J116: 0 | K116: 0 | L116: 0 | M116: 0 | N116: 0 | O116: 0
A117: Training compute expenses to R&D | B117: CALC | C117: $M | D117: Training (expensed) + research compute. Primary loss driver. | E117: 47.3 | F117: 166.6 | G117: 4680 | H117: 5679 | I117: 28077.8 | J117: 33524 | K117: 38160 | L117: 41081.6 | M117: 44064 | N117: 47052.4 | O117: 47917.6
A118: Total R&D (ex-SBC) | B118: CALC | C118: $M | D118: Personnel + RLHF + licensing + failed + tooling + training. | E118: 69.3 | F118: 248.2 | G118: 5006.5 | H118: 6965 | I118: 31787.8 | J118: 39070 | K118: 45290 | L118: 49613.6 | M118: 53686.5 | N118: 57511.9 | O118: 59212.1
A119: S&M Headcount | B119: IN | C119: count | D119: GTM heads (small org). | E119: 8 | F119: 30 | G119: 70 | H119: 180 | I119: 900 | J119: 1450 | K119: 1900 | L119: 2250 | M119: 2500 | N119: 2700 | O119: 2850
... A133: One-time litigation services | B133: IN | C133: $M | D133: Non-recurring litigation. | E133: 0 | F133: 0 | G133: 5 | H133: 40 | I133: 150 | J133: 90 | K133: 60 | L133: 50 | M133: 45 | N133: 40 | O133: 40
A134: STOCK BASED COMP
A135: SBC issue rate (% of base cash comp) | B135: IN | C135: % | D135: RSU grant value as % of cash comp. | E135: 0.4 | F135: 0.45 | G135: 0.5 | H135: 0.55 | I135: 0.55 | J135: 0.5 | K135: 0.45 | L135: 0.42 | M135: 0.4 | N135: 0.38 | O135: 0.36
A136: R&D SBC | B136: CALC | C136: $M | D136: R&D cash x SBC rate. | E136: 6.4 | F136: 24.57 | G136: 60.75 | H136: 184.8 | I136: 929.5 | J136: 1308 | K136: 1525.5 | L136: 1680.84 | M136: 1785 | N136: 1816.21 | O136: 1837.62
A137: S&M SBC | B137: CALC | C137: $M | D137: S&M cash x SBC rate. | E137: 0.896 | F137: 3.915 | G137: 10.5 | H137: 30.69 | I137: 158.4 | J137: 239.25 | K137: 290.7 | L137: 330.75 | M137: 358 | N137: 374.49 | O137: 381.672
A138: G&A SBC | B138: CALC | C138: $M | D138: G&A cash x SBC rate. | E138: 1.248 | F138: 3.888 | G138: 8.4 | H138: 27.115 | I138: 140.25 | J138: 192.5 | K138: 226.8 | L138: 250.194 | M138: 262.4 | N138: 279.224 | O138: 287.64
A139: Total SBC | B139: CALC | C139: $M | D139: Sum of function SBC. | E139: 8.544 | F139: 32.373 | G139: 79.65 | H139: 242.605 | I139: 1228.15 | J139: 1739.75 | K139: 2043 | L139: 2261.784 | M139: 2405.4 | N139: 2469.924 | O139: 2506.932
A140: DEPRECIATION & AMORTIZATION
A141: Amort life - models (yrs) | B141: IN | C141: yr | D141: Life of capitalized models. | E141: 2 | F141: 2 | G141: 2 | H141: 2 | I141: 2 | J141: 2 | K141: 2 | L141: 2 | M141: 2 | N141: 2 | O141: 2
A142: Amort of capitalized frontier models | B142: CALC | C142: $M | D142: 2-yr straight-line of cap pool. | E142: 6.195 | F142: 27.435 | G142: 640.74 | H142: 1336.35 | I142: 4294.02 | J142: 7789.77 | K142: 8991.6 | L142: 9933.24 | M142: 10650.09 | N142: 11368.71 | O142: 11859
A143: Owned GPU / datacenter capex | B143: IN | C143: $M | D143: Owned hardware capex (Fluidstack $50B ramps 2026+). | E143: 2 | F143: 8 | G143: 40 | H143: 220 | I143: 1400 | J143: 3200 | K143: 5000 | L143: 6500 | M143: 7500 | N143: 8200 | O143: 8800
A144: Depreciation life - HW (yrs) | B144: IN | C144: yr | D144: Life of owned accelerators. | E144: 4 | F144: 4 | G144: 4 | H144: 5 | I144: 5 | J144: 5 | K144: 6 | L144: 6 | M144: 6 | N144: 6 | O144: 6
A145: Depreciation of owned GPU / datacenter | B145: CALC | C145: $M | D145: Vintage straight-line depreciation. | E145: 0.5 | F145: 2.5 | G145: 12.5 | H145: 56.5 | I145: 336 | J145: 974 | K145: 1797.3333 | L145: 2880.6667 | M145: 4086.6667 | N145: 5173.3333 | O145: 6000
A146: Amort of prepaid cloud commits (reclass) | B146: MEMO | C146: $M | D146: Reclass memo. NOT added to P&L D&A (guard). | E146: 0 | F146: 0 | G146: 20 | H146: 120 | I146: 500 | J146: 800 | K146: 1050 | L146: 1300 | M146: 1500 | N146: 1650 | O146: 1800
A147: Total D&A | B147: CALC | C147: $M | D147: Model amort + owned HW dep (prepaid-cloud excluded). | E147: 6.695 | F147: 29.935 | G147: 653.24 | H147: 1392.85 | I147: 4630.02 | J147: 8763.77 | K147: 10788.933 | L147: 12813.907 | M147: 14736.757 | N147: 16542.043 | O147: 17859
A148: P&L SUMMARY (memo)
A149: Gross profit | B149: CALC | C149: $M | D149: Revenue - cost of revenue. | E149: -0.71394805 | F149: 29.818362 | G149: 488.79914 | H149: 5494.3613 | I149: 31069.441 | J149: 46421.566 | K149: 62493.476 | L149: 78989.312 | M149: 96820.438 | N149: 115166.75 | O149: 132078
A150: Operating income (ex-SBC) | B150: CALC | C150: $M | D150: GP - R&D - S&M - G&A - D&A. | E150: -84.068948 | F150: -276.65664 | G150: -5289.7409 | H150: -3448.5887 | I150: -7681.3786 | J150: -5045.7044 | K150: 1714.5425 | L150: 10908.605 | M150: 21941.181 | N150: 33935.511 | O150: 47222.698
A151: Operating income (incl-SBC) | B151: CALC | C151: $M | D151: After stock-based comp. | E151: -92.612948 | F151: -309.02964 | G151: -5369.3909 | H151: -3691.1937 | I151: -8909.5286 | J151: -6785.4544 | K151: -328.45751 | L151: 8646.8209 | M151: 19535.781 | N151: 31465.587 | O151: 44715.766
...

Sheet D6
A1: Worst/Recognized (data block D6)
A2: Line Item | B2: Type | C2: Unit | D2: What it is | E2: 2022 | F2: 2023 | G2: 2024 | H2: 2025 | I2: 2026 | J2: 2027 | K2: 2028 | L2: 2029 | M2: 2030 | N2: 2031 | O2: 2032
A3: REVENUE
A4: Booked revenue | B4: IN | C4: $M | D4: Anchor. 2022-26 PitchBook TTM (10/100/1,000/9,000/47,000); 2027-32 base case. PB carries 55,000 for 2027 as a conservative mark. | E4: 10 | F4: 85 | G4: 600 | H4: 4680 | I4: 23500 | J4: 42160 | K4: 64800 | L4: 89600 | M4: 114750 | N4: 139040 | O4: 160200
A5: API PRICING AND BLENDED EFFECTIVE RATE
A6: Model mix % - Mythos | B6: IN | C6: % | D6: Token share, flagship tier (Fable 5 / Mythos 5, $10/$50). Introduced 2026. | E6: 0 | F6: 0 | G6: 0 | H6: 0 | I6: 0.03 | J6: 0.05 | K6: 0.06 | L6: 0.07 | M6: 0.08 | N6: 0.09 | O6: 0.1
A7: Model mix % - Opus | B7: IN | C7: % | D7: Token share, Opus ($15/$75 to Aug-2025, cut to $5/$25 at Opus 4.5). | E7: 0 | F7: 0.1 | G7: 0.08 | H7: 0.1 | I7: 0.12 | J7: 0.12 | K7: 0.12 | L7: 0.12 | M7: 0.12 | N7: 0.12 | O7: 0.12
A8: Model mix % - Sonnet | B8: IN | C8: % | D8: Token share, Sonnet workhorse ($3/$15). | E8: 0.4 | F8: 0.3 | G8: 0.32 | H8: 0.45 | I8: 0.45 | J8: 0.44 | K8: 0.43 | L8: 0.42 | M8: 0.41 | N8: 0.4 | O8: 0.4
A9: Model mix % - Haiku | B9: IN | C9: % | D9: Token share, Haiku ($0.25/$1.25 -> $1/$5). | E9: 0.6 | F9: 0.6 | G9: 0.6 | H9: 0.45 | I9: 0.4 | J9: 0.39 | K9: 0.39 | L9: 0.39 | M9: 0.39 | N9: 0.39 | O9: 0.38
A10: List input $/Mtok - Mythos | B10: IN | C10: $ | D10: List input price, flagship. | E10: 15 | F10: 15 | G10: 15 | H10: 15 | I10: 15 | J10: 15 | K10: 14 | L10: 13 | M10: 12 | N10: 12 | O10: 11
A11: List input $/Mtok - Opus | B11: IN | C11: $ | D11: List input price, Opus. | E11: 11 | F11: 8 | G11: 15 | H11: 15 | I11: 5 | J11: 5 | K11: 5 | L11: 4.5 | M11: 4.5 | N11: 4 | O11: 4
A12: List input $/Mtok - Sonnet | B12: IN | C12: $ | D12: List input price, Sonnet. | E12: 3 | F12: 3 | G12: 3 | H12: 3 | I12: 3 | J12: 3 | K12: 3 | L12: 2.5 | M12: 2.5 | N12: 2 | O12: 2
A13: List input $/Mtok - Haiku | B13: IN | C13: $ | D13: List input price, Haiku. | E13: 0.8 | F13: 0.8 | G13: 0.25 | H13: 0.8 | I13: 1 | J13: 1 | K13: 1 | L13: 0.9 | M13: 0.9 | N13: 0.8 | O13: 0.8
A14: List output $/Mtok - Mythos | B14: IN | C14: $ | D14: List output price, flagship. | E14: 75 | F14: 75 | G14: 75 | H14: 75 | I14: 75 | J14: 70 | K14: 65 | L14: 60 | M14: 55 | N14: 55 | O14: 50
A15: List output $/Mtok - Opus | B15: IN | C15: $ | D15: List output price, Opus. | E15: 33 | F15: 24 | G15: 75 | H15: 75 | I15: 25 | J15: 25 | K15: 22 | L15: 22 | M15: 20 | N15: 20 | O15: 18
A16: List output $/Mtok - Sonnet | B16: IN | C16: $ | D16: List output price, Sonnet. | E16: 15 | F16: 15 | G16: 15 | H16: 15 | I16: 15 | J16: 15 | K16: 13 | L16: 13 | M16: 12 | N16: 10 | O16: 10
A17: List output $/Mtok - Haiku | B17: IN | C17: $ | D17: List output price, Haiku. | E17: 2.4 | F17: 2.4 | G17: 1.25 | H17: 4 | I17: 5 | J17: 5 | K17: 4.5 | L17: 4.5 | M17: 4 | N17: 4 | O17: 3.6
... A27: Blended effective $/Mtok | B27: CALC | C27: $ | D27: Mix-weighted, adjusted for input share, caching, batch. | E27: 2.9806452 | F27: 3.4768421 | G27: 3.793749 | H27: 4.1467112 | I27: 3.0571739 | J27: 2.9587834 | K27: 2.6527823 | L27: 2.3780343 | M27: 2.2407352 | N27: 2.0581018 | O27: 1.9921081
A28: NON-API REVENUE STREAMS
A29: # Enterprise contracts (>$1M ARR) | B29: IN | C29: count | D29: ~1,000+ at $1M+ ACV by 2026. | E29: 0 | F29: 4.25 | G29: 36 | H29: 156 | I29: 500 | J29: 1054 | K29: 1728 | L29: 2480 | M29: 3145 | N29: 3696 | O29: 4140
A30: Committed-use discount % (memo) | B30: IN | C30: % | D30: Volume discount realized on enterprise API. | E30: 0 | F30: 0.05 | G30: 0.1 | H30: 0.12 | I30: 0.15 | J30: 0.15 | K30: 0.16 | L30: 0.16 | M30: 0.17 | N30: 0.17 | O30: 0.18
A31: Active enterprise dashboard seats | B31: IN | C31: count | D31: Console/admin seats. | E31: 0 | F31: 1700 | G31: 24000 | H31: 130000 | I31: 450000 | J31: 992000 | K31: 1656000 | L31: 2400000 | M31: 3060000 | N31: 3608000 | O31: 4050000
A32: Enterprise platform fee / seat / mo | B32: IN | C32: $ | D32: Monthly platform fee per seat. | E32: 0 | F32: 30 | G32: 35 | H32: 40 | I32: 45 | J32: 48 | K32: 50 | L32: 52 | M32: 54 | N32: 55 | O32: 56
