Workbook
Name __123Graph_B: #REF!
Name __123Graph_D: #REF!
Name _2_0__123Grap: #REF!
Name _4_0__123Grap: #REF!
Name _fff2: #REF!
Name _fff2: #REF!
Name _fff2: #REF!
Name _Fil1: #REF!
Name _Fill: #REF!
Name _ggg2: #REF!
Name _ggg2: #REF!
Name _ggg2: #REF!
Name _Key1: #REF!
Name _Key2: #REF!
Name _Key5: #REF!
Name _Key6: #REF!
Name _Key8: #REF!
Name _Key9: #REF!
Name _MRG2: #REF!
Name _MRG2: #REF!
Name _MRG2: #REF!
Name _Sort: #REF!
Name _Table2_In1: #REF!
Name _Table2_In2: #REF!
Name _Table2_Out: #REF!
Name a: #REF!
Name aaaaaa: #REF!
Name aaaaaaa: #REF!
Name aaaaaaa: #REF!
Name aaaaaaa: #REF!
Name aasdfa: #REF!
Name aasdfa: #REF!
Name aasdfa: #REF!
Name as: #REF!
Name as: #REF!
Name as: #REF!
Name asdfas: #REF!
Name asdfas: #REF!
Name asdfas: #REF!
Name asdfasaa: #REF!
Name asdfasaa: #REF!
Name asdfasaa: #REF!
Name asdfasdf: #REF!
Name asdfasdf: #REF!
Name asdfasdf: #REF!
Name asfag2: #REF!
Name asfag2: #REF!
Name asfag2: #REF!
Name asfasg: #REF!
Name asfasg: #REF!
Name asfasg: #REF!
Name ass: #REF!
Name ass: #REF!
Name ass: #REF!
Name asss: #REF!
Name asss: #REF!
Name asss: #REF!
Name az: #REF!
Name az: #REF!
Name az: #REF!

Sheet Cover
C11: SaaS Financial Model | M11: Strictly Confidential
C13: Table of Contents
C15: Monthly Schedule
C16: Financial Model
C31: © 2015 to 2024 CFI Education Inc.
C32: This Excel model is for educational purposes only and should not be used for any other reason. All content is Copyright material of CFI Education Inc.
C33: All rights reserved. The contents of this publication, including but not limited to all written material, content layout, images, formulas, and code, are protected
C34: under international copyright and trademark laws. No part of this publication may be modified, manipulated, reproduced, distributed, or transmitted in any
C35: form by any means, including photocopying, recording, or other electronic or mechanical methods, without prior written permission of the publisher,
C36: except in the case of certain noncommercial uses permitted by copyright law.
C38: https://corporatefinanceinstitute.com/

Sheet Monthly Schedule
B4: Assumptions
B6: Customer Churn rate | C6: 0.03
B7: Average months paid upfront | C7: 12
B8: Renewal rate | C8: 0.95
B9: ARPA (Average Revenue per Account per Month)- New Accounts | C9: 100
B11: Customer Churn rate | C11: 0.03
B12: Average months paid upfront | C12: 12
B13: Renewal rate | C13: 0.95
B14: ARPA (Average Revenue per Account per Month)- New Accounts | C14: 100
B16: Customer Churn rate | C16: 0.03
B17: Average months paid upfront | C17: 12
B18: Renewal rate | C18: 0.95
B19: ARPA (Average Revenue per Account per Month)- New Accounts | C19: 100
B21: 2017 | D21: 42736 | E21: =EDATE(D21,1) -> 42767 | F21: =EDATE(E21,1) -> 42795 | G21: =EDATE(F21,1) -> 42826 | H21: =EDATE(G21,1) -> 42856 | I21: =EDATE(H21,1) -> 42887 | J21: =EDATE(I21,1) -> 42917 | K21: =EDATE(J21,1) -> 42948 | L21: =EDATE(K21,1) -> 42979 | ... O21: =EDATE(N21,1) -> 43070
B22: Number of customer accounts
B23: Opening balance | D23: 100 | E23: =D26 -> 107 | F23: =E26 -> 113.79 | G23: =F26 -> 120.3763 | H23: =G26 -> 126.76501 | I23: =H26 -> 132.96206 | J23: =I26 -> 138.9732 | K23: =J26 -> 144.804 | L23: =K26 -> 150.45988 | ... O23: =N26 -> 166.42967
B24: New customer additions | D24: 10 | E24: 10 | F24: 10 | G24: 10 | H24: 10 | I24: 10 | J24: 10 | K24: 10 | L24: 10 | M24: 10 | N24: 10 | O24: 10
B25: Customer churn | D25: =-$C$16*D23 -> -3 | E25: =-$C$16*E23 -> -3.21 | F25: =-$C$16*F23 -> -3.4137 | G25: =-$C$16*G23 -> -3.611289 | H25: =-$C$16*H23 -> -3.8029503 | I25: =-$C$16*I23 -> -3.9888618 | J25: =-$C$16*J23 -> -4.169196 | K25: =-$C$16*K23 -> -4.3441201 | ... O25: =-$C$16*O23 -> -4.9928902
B26: Total number of customer accounts | D26: =SUM(D23:D25) -> 107 | E26: =SUM(E23:E25) -> 113.79 | F26: =SUM(F23:F25) -> 120.3763 | G26: =SUM(G23:G25) -> 126.76501 | H26: =SUM(H23:H25) -> 132.96206 | I26: =SUM(I23:I25) -> 138.9732 | J26: =SUM(J23:J25) -> 144.804 | K26: =SUM(K23:K25) -> 150.45988 | ... O26: =SUM(O23:O25) -> 171.43678
B28: MRR opening balance | D28: 10000 | E28: =D32 -> 10850 | F28: =E32 -> 11687.25 | G28: =F32 -> 12511.941 | H28: =G32 -> 13324.262 | I28: =H32 -> 14124.398 | J28: =I32 -> 14912.532 | K28: =J32 -> 15688.844 | L28: =K32 -> 16453.512 | ... O28: =N32 -> 18679.379
B29: New MRR | D29: =+D24*$C$19 -> 1000 | E29: =+E24*$C$19 -> 1000 | F29: =+F24*$C$19 -> 1000 | G29: =+G24*$C$19 -> 1000 | H29: =+H24*$C$19 -> 1000 | I29: =+I24*$C$19 -> 1000 | J29: =+J24*$C$19 -> 1000 | K29: =+K24*$C$19 -> 1000 | ... O29: =+O24*$C$19 -> 1000
B30: Churned MRR | D30: =+-D37*D28 -> -200 | E30: =+-E37*E28 -> -217 | F30: =+-F37*F28 -> -233.745 | G30: =+-G37*G28 -> -250.23882 | H30: =+-H37*H28 -> -266.48524 | I30: =+-I37*I28 -> -282.48796 | J30: =+-J37*J28 -> -298.25064 | K30: =+-K37*K28 -> -313.77688 | ... O30: =+-O37*O28 -> -373.58758
B31: Expansion MRR | D31: =+D38*D28 -> 50 | E31: =+E38*E28 -> 54.25 | F31: =+F38*F28 -> 58.43625 | G31: =+G38*G28 -> 62.559706 | H31: =+H38*H28 -> 66.621311 | I31: =+I38*I28 -> 70.621991 | J31: =+J38*J28 -> 74.562661 | K31: =+K38*K28 -> 78.444221 | ... O31: =+O38*O28 -> 93.396896
B32: Net MRR | D32: =SUM(D28:D31) -> 10850 | E32: =SUM(E28:E31) -> 11687.25 | F32: =SUM(F28:F31) -> 12511.941 | G32: =SUM(G28:G31) -> 13324.262 | H32: =SUM(H28:H31) -> 14124.398 | I32: =SUM(I28:I31) -> 14912.532 | J32: =SUM(J28:J31) -> 15688.844 | K32: =SUM(K28:K31) -> 16453.512 | ... O32: =SUM(O28:O31) -> 19399.188
B33: % growth | E33: =E32/D32-1 -> 0.077165899 | F33: =F32/E32-1 -> 0.070563328 | G33: =G32/F32-1 -> 0.064923649 | H33: =H32/G32-1 -> 0.06005106 | I33: =I32/H32-1 -> 0.055799477 | J33: =J32/I32-1 -> 0.052057692 | K33: =K32/J32-1 -> 0.048739558 | L33: =L32/K32-1 -> 0.045777299 | ... O33: =O32/N32-1 -> 0.03853497
B35: ARPA (Average Revenue per Account per Month) - across installed based | D35: =+D32/D26 -> 101.40187 | E35: =+E32/E26 -> 102.70894 | F35: =+F32/F26 -> 103.94024 | G35: =+G32/G26 -> 105.10994 | H35: =+H32/H26 -> 106.22879 | I35: =+I32/I26 -> 107.30509 | J35: =+J32/J26 -> 108.34538 | K35: =+K32/K26 -> 109.35481 | ... O35: =+O32/O26 -> 113.15651
B37: % MRR Churn Rate | D37: 0.02 | E37: 0.02 | F37: 0.02 | G37: 0.02 | H37: 0.02 | I37: 0.02 | J37: 0.02 | K37: 0.02 | L37: 0.02 | M37: 0.02 | N37: 0.02 | O37: 0.02
B38: % MRR Expansion Rate | D38: 0.005 | E38: 0.005 | F38: 0.005 | G38: 0.005 | H38: 0.005 | I38: 0.005 | J38: 0.005 | K38: 0.005 | L38: 0.005 | M38: 0.005 | N38: 0.005 | O38: 0.005
B39: % Net MRR Churn Rate | D39: =+(-D30-D31)/D28 -> 0.015 | E39: =+(-E30-E31)/E28 -> 0.015 | F39: =+(-F30-F31)/F28 -> 0.015 | G39: =+(-G30-G31)/G28 -> 0.015 | H39: =+(-H30-H31)/H28 -> 0.015 | I39: =+(-I30-I31)/I28 -> 0.015 | J39: =+(-J30-J31)/J28 -> 0.015 | K39: =+(-K30-K31)/K28 -> 0.015 | ... O39: =+(-O30-O31)/O28 -> 0.015
B41: Subscription billings | D41: =D29*$C$17 -> 12000 | E41: =E29*$C$17 -> 12000 | F41: =F29*$C$17 -> 12000 | G41: =G29*$C$17 -> 12000 | H41: =H29*$C$17 -> 12000 | I41: =I29*$C$17 -> 12000 | J41: =J29*$C$17 -> 12000 | K41: =K29*$C$17 -> 12000 | ... O41: =O29*$C$17 -> 12000
B43: Annualized run rate in 2017 | D43: =SUM(D32:O32) -> 182786.62
B44: Subscription billings in 2017 | D44: =SUM(D41:O41) -> 144000
B46: =B21+1 -> 2018 | D46: =EDATE(D21,12) -> 43101 | E46: =EDATE(E21,12) -> 43132 | F46: =EDATE(F21,12) -> 43160 | G46: =EDATE(G21,12) -> 43191 | H46: =EDATE(H21,12) -> 43221 | I46: =EDATE(I21,12) -> 43252 | J46: =EDATE(J21,12) -> 43282 | K46: =EDATE(K21,12) -> 43313 | ... O46: =EDATE(O21,12) -> 43435
B47: Number of customer accounts
B48: Opening balance | D48: =O26 -> 171.43678 | E48: =D51 -> 181.29368 | F48: =E51 -> 190.85487 | G48: =F51 -> 200.12922 | H48: =G51 -> 209.12535 | I48: =H51 -> 217.85159 | J48: =I51 -> 226.31604 | K48: =J51 -> 234.52656 | L48: =K51 -> 242.49076 | ... O48: =N51 -> 264.97827
B49: New customer additions | D49: 15 | E49: 15 | F49: 15 | G49: 15 | H49: 15 | I49: 15 | J49: 15 | K49: 15 | L49: 15 | M49: 15 | N49: 15 | O49: 15
B50: Customer churn | D50: =-$C$16*D48 -> -5.1431035 | E50: =-$C$16*E48 -> -5.4388104 | F50: =-$C$16*F48 -> -5.7256461 | G50: =-$C$16*G48 -> -6.0038767 | H50: =-$C$16*H48 -> -6.2737604 | I50: =-$C$16*I48 -> -6.5355476 | J50: =-$C$16*J48 -> -6.7894811 | K50: =-$C$16*K48 -> -7.0357967 | ... O50: =-$C$16*O48 -> -7.9493481
B51: Total number of customer accounts | D51: =SUM(D48:D50) -> 181.29368 | E51: =SUM(E48:E50) -> 190.85487 | F51: =SUM(F48:F50) -> 200.12922 | G51: =SUM(G48:G50) -> 209.12535 | H51: =SUM(H48:H50) -> 217.85159 | I51: =SUM(I48:I50) -> 226.31604 | J51: =SUM(J48:J50) -> 234.52656 | K51: =SUM(K48:K50) -> 242.49076 | ... O51: =SUM(O48:O50) -> 272.02892
B53: MRR opening balance | D53: =O32 -> 19399.188 | E53: =D57 -> 20608.201 | F53: =E57 -> 21799.078 | G53: =F57 -> 22972.091 | H53: =G57 -> 24127.51 | I53: =H57 -> 25265.597 | J53: =I57 -> 26386.613 | K53: =J57 -> 27490.814 | L53: =K57 -> 28578.452 | ... O53: =N57 -> 31744.453
B54: New MRR | D54: =D49*$C$19 -> 1500 | E54: =E49*$C$19 -> 1500 | F54: =F49*$C$19 -> 1500 | G54: =G49*$C$19 -> 1500 | H54: =H49*$C$19 -> 1500 | I54: =I49*$C$19 -> 1500 | J54: =J49*$C$19 -> 1500 | K54: =K49*$C$19 -> 1500 | ... O54: =O49*$C$19 -> 1500
B55: Churned MRR | D55: =+-D62*D53 -> -387.98377 | E55: =+-E62*E53 -> -412.16401 | F55: =+-F62*F53 -> -435.98155 | G55: =+-G62*G53 -> -459.44183 | H55: =+-H62*H53 -> -482.5502 | I55: =+-I62*I53 -> -505.31195 | J55: =+-J62*J53 -> -527.73227 | K55: =+-K62*K53 -> -549.81629 | ... O55: =+-O62*O53 -> -634.88906
B56: Expansion MRR | D56: =+D63*D53 -> 96.995942 | E56: =+E63*E53 -> 103.041 | F56: =+F63*F53 -> 108.99539 | G56: =+G63*G53 -> 114.86046 | H56: =+H63*H53 -> 120.63755 | I56: =+I63*I53 -> 126.32799 | J56: =+J63*J53 -> 131.93307 | K56: =+K63*K53 -> 137.45407 | ... O56: =+O63*O53 -> 158.72227
B57: Net MRR | D57: =SUM(D53:D56) -> 20608.201 | E57: =SUM(E53:E56) -> 21799.078 | F57: =SUM(F53:F56) -> 22972.091 | G57: =SUM(G53:G56) -> 24127.51 | H57: =SUM(H53:H56) -> 25265.597 | I57: =SUM(I53:I56) -> 26386.613 | J57: =SUM(J53:J56) -> 27490.814 | K57: =SUM(K53:K56) -> 28578.452 | ... O57: =SUM(O53:O56) -> 32768.286
B58: % growth | E58: =E57/D57-1 -> 0.057786558 | F58: =F57/E57-1 -> 0.053810251 | G58: =G57/F57-1 -> 0.050296623 | H58: =H57/G57-1 -> 0.047169697 | I58: =I57/H57-1 -> 0.044369267 | J58: =J57/I57-1 -> 0.041847007 | K58: =K57/J57-1 -> 0.03956368 | L58: =L57/K57-1 -> 0.037487098 | ... O58: =O57/N57-1 -> 0.03225235
B60: ARPA (Average Revenue per Account per Month) - across installed based | D60: =+D57/D51 -> 113.67302 | E60: =+E57/E51 -> 114.21809 | F60: =+F57/F51 -> 114.78629 | G60: =+G57/G51 -> 115.37344 | H60: =+H57/H51 -> 115.97619 | I60: =+I57/I51 -> 116.59189 | J60: =+J57/J51 -> 117.21834 | K60: =+K57/K51 -> 117.85378 | ... O60: =+O57/O51 -> 120.45883
B62: % MRR Churn Rate | D62: 0.02 | E62: 0.02 | F62: 0.02 | G62: 0.02 | H62: 0.02 | I62: 0.02 | J62: 0.02 | K62: 0.02 | L62: 0.02 | M62: 0.02 | N62: 0.02 | O62: 0.02
B63: % MRR Expansion Rate | D63: 0.005 | E63: 0.005 | F63: 0.005 | G63: 0.005 | H63: 0.005 | I63: 0.005 | J63: 0.005 | K63: 0.005 | L63: 0.005 | M63: 0.005 | N63: 0.005 | O63: 0.005
B64: % Net MRR Churn Rate | D64: =+(-D55-D56)/D53 -> 0.015 | E64: =+(-E55-E56)/E53 -> 0.015 | F64: =+(-F55-F56)/F53 -> 0.015 | G64: =+(-G55-G56)/G53 -> 0.015 | H64: =+(-H55-H56)/H53 -> 0.015 | I64: =+(-I55-I56)/I53 -> 0.015 | J64: =+(-J55-J56)/J53 -> 0.015 | K64: =+(-K55-K56)/K53 -> 0.015 | ... O64: =+(-O55-O56)/O53 -> 0.015
B66: Subscription billings | D66: =D54*$C$17 -> 18000 | E66: =E54*$C$17 -> 18000 | F66: =F54*$C$17 -> 18000 | G66: =G54*$C$17 -> 18000 | H66: =H54*$C$17 -> 18000 | I66: =I54*$C$17 -> 18000 | J66: =J54*$C$17 -> 18000 | K66: =K54*$C$17 -> 18000 | ... O66: =O54*$C$17 -> 18000
B68: Annualized run rate in 2018 | D68: =SUM(D57:O57) -> 322095.9
B69: Subscription billings in 2018 | D69: =SUM(D66:O66) -> 216000
B71: =B46+1 -> 2019 | D71: =EDATE(D46,12) -> 43466 | E71: =EDATE(E46,12) -> 43497 | F71: =EDATE(F46,12) -> 43525 | G71: =EDATE(G46,12) -> 43556 | H71: =EDATE(H46,12) -> 43586 | I71: =EDATE(I46,12) -> 43617 | J71: =EDATE(J46,12) -> 43647 | K71: =EDATE(K46,12) -> 43678 | ... O71: =EDATE(O46,12) -> 43800
B72: Number of customer accounts
B73: Opening balance | D73: =O51 -> 272.02892 | E73: =D76 -> 283.86805 | F73: =E76 -> 295.35201 | G73: =F76 -> 306.49145 | H73: =G76 -> 317.29671 | I73: =H76 -> 327.77781 | J73: =I76 -> 337.94447 | K73: =J76 -> 347.80614 | L73: =K76 -> 357.37195 | ... O73: =N76 -> 384.38173
B74: New customer additions | D74: 20 | E74: 20 | F74: 20 | G74: 20 | H74: 20 | I74: 20 | J74: 20 | K74: 20 | L74: 20 | M74: 20 | N74: 20 | O74: 20
B75: Customer churn | D75: =-$C$16*D73 -> -8.1608676 | E75: =-$C$16*E73 -> -8.5160416 | F75: =-$C$16*F73 -> -8.8605604 | G75: =-$C$16*G73 -> -9.1947436 | H75: =-$C$16*H73 -> -9.5189012 | I75: =-$C$16*I73 -> -9.8333342 | J75: =-$C$16*J73 -> -10.138334 | K75: =-$C$16*K73 -> -10.434184 | ... O75: =-$C$16*O73 -> -11.531452
B76: Total number of customer accounts | D76: =SUM(D73:D75) -> 283.86805 | E76: =SUM(E73:E75) -> 295.35201 | F76: =SUM(F73:F75) -> 306.49145 | G76: =SUM(G73:G75) -> 317.29671 | H76: =SUM(H73:H75) -> 327.77781 | I76: =SUM(I73:I75) -> 337.94447 | J76: =SUM(J73:J75) -> 347.80614 | K76: =SUM(K73:K75) -> 357.37195 | ... O76: =SUM(O73:O75) -> 392.85028
B78: MRR opening balance | D78: =O57 -> 32768.286 | E78: =D82 -> 34276.762 | F78: =E82 -> 35762.611 | G78: =F82 -> 37226.172 | H78: =G82 -> 38667.779 | I78: =H82 -> 40087.762 | J78: =I82 -> 41486.446 | K78: =J82 -> 42864.149 | L78: =K82 -> 44221.187 | ... O78: =N82 -> 48171.384
B79: New MRR | D79: =D74*$C$19 -> 2000 | E79: =E74*$C$19 -> 2000 | F79: =F74*$C$19 -> 2000 | G79: =G74*$C$19 -> 2000 | H79: =H74*$C$19 -> 2000 | I79: =I74*$C$19 -> 2000 | J79: =J74*$C$19 -> 2000 | K79: =K74*$C$19 -> 2000 | ... O79: =O74*$C$19 -> 2000
B80: Churned MRR | D80: =+-D87*D78 -> -655.36573 | E80: =+-E87*E78 -> -685.53524 | F80: =+-F87*F78 -> -715.25221 | G80: =+-G87*G78 -> -744.52343 | H80: =+-H87*H78 -> -773.35558 | I80: =+-I87*I78 -> -801.75525 | J80: =+-J87*J78 -> -829.72892 | K80: =+-K87*K78 -> -857.28298 | ... O80: =+-O87*O78 -> -963.42767
B81: Expansion MRR | D81: =+D88*D78 -> 163.84143 | E81: =+E88*E78 -> 171.38381 | F81: =+F88*F78 -> 178.81305 | G81: =+G88*G78 -> 186.13086 | H81: =+H88*H78 -> 193.33889 | I81: =+I88*I78 -> 200.43881 | J81: =+J88*J78 -> 207.43223 | K81: =+K88*K78 -> 214.32075 | ... O81: =+O88*O78 -> 240.85692
B82: Net MRR | D82: =SUM(D78:D81) -> 34276.762 | E82: =SUM(E78:E81) -> 35762.611 | F82: =SUM(F78:F81) -> 37226.172 | G82: =SUM(G78:G81) -> 38667.779 | H82: =SUM(H78:H81) -> 40087.762 | I82: =SUM(I78:I81) -> 41486.446 | J82: =SUM(J78:J81) -> 42864.149 | K82: =SUM(K78:K81) -> 44221.187 | ... O82: =SUM(O78:O81) -> 49448.813
B83: % growth | E83: =E82/D82-1 -> 0.043348568 | F83: =F82/E82-1 -> 0.040924329 | G83: =G82/F82-1 -> 0.038725643 | H83: =H82/G82-1 -> 0.03672265 | I83: =I82/H82-1 -> 0.034890537 | J83: =J82/I82-1 -> 0.033208516 | K83: =K82/J82-1 -> 0.031659039 | L83: =L82/K82-1 -> 0.030227189 | ... O83: =O82/N82-1 -> 0.026518426
B85: ARPA (Average Revenue per Account per Month) - across installed based | D85: =+D82/D76 -> 120.74892 | E85: =+E82/E76 -> 121.0847 | F85: =+F82/F76 -> 121.45909 | G85: =+G82/G76 -> 121.86631 | H85: =+H82/H76 -> 122.30164 | I85: =+I82/I76 -> 122.76113 | J85: =+J82/J76 -> 123.2415 | K85: =+K82/K76 -> 123.73995 | ... O85: =+O82/O76 -> 125.8719
B87: % MRR Churn Rate | D87: 0.02 | E87: 0.02 | F87: 0.02 | G87: 0.02 | H87: 0.02 | I87: 0.02 | J87: 0.02 | K87: 0.02 | L87: 0.02 | M87: 0.02 | N87: 0.02 | O87: 0.02
B88: % MRR Expansion Rate | D88: 0.005 | E88: 0.005 | F88: 0.005 | G88: 0.005 | H88: 0.005 | I88: 0.005 | J88: 0.005 | K88: 0.005 | L88: 0.005 | M88: 0.005 | N88: 0.005 | O88: 0.005
B89: % Net MRR Churn Rate | D89: =+(-D80-D81)/D78 -> 0.015 | E89: =+(-E80-E81)/E78 -> 0.015 | F89: =+(-F80-F81)/F78 -> 0.015 | G89: =+(-G80-G81)/G78 -> 0.015 | H89: =+(-H80-H81)/H78 -> 0.015 | I89: =+(-I80-I81)/I78 -> 0.015 | J89: =+(-J80-J81)/J78 -> 0.015 | K89: =+(-K80-K81)/K78 -> 0.015 | ... O89: =+(-O80-O81)/O78 -> 0.015
B91: Subscription billings | D91: =D79*$C$17 -> 24000 | E91: =E79*$C$17 -> 24000 | F91: =F79*$C$17 -> 24000 | G91: =G79*$C$17 -> 24000 | H91: =H79*$C$17 -> 24000 | I91: =I79*$C$17 -> 24000 | J91: =J79*$C$17 -> 24000 | K91: =K79*$C$17 -> 24000 | L91: =L79*$C$17+($C$17*$C$18*D29) -> 35400 | M91: =M79*$C$17+($C$17*$C$18*E29) -> 35400 | N91: =N79*$C$17+($C$17*$C$18*F29) -> 35400 | O91: =O79*$C$17+($C$17*$C$18*G29) -> 35400
B93: Annualized run rate in 2019 | D93: =SUM(D82:O82) -> 504645.43
B94: Subscription billings in 2019 | D94: =SUM(D91:O91) -> 333600
B96: =B71+1 -> 2020 | D96: =EDATE(D71,12) -> 43831 | E96: =EDATE(E71,12) -> 43862 | F96: =EDATE(F71,12) -> 43891 | G96: =EDATE(G71,12) -> 43922 | H96: =EDATE(H71,12) -> 43952 | I96: =EDATE(I71,12) -> 43983 | J96: =EDATE(J71,12) -> 44013 | K96: =EDATE(K71,12) -> 44044 | ... O96: =EDATE(O71,12) -> 44166
B97: Number of customer accounts
B98: Opening balance | D98: =O76 -> 392.85028 | E98: =D101 -> 406.06477 | F98: =E101 -> 418.88283 | G98: =F101 -> 431.31635 | H98: =G101 -> 443.37685 | I98: =H101 -> 455.07555 | J98: =I101 -> 466.42328 | K98: =J101 -> 477.43058 | L98: =K101 -> 488.10767 | ... O98: =N101 -> 518.25519
B99: New customer additions | D99: 25 | E99: 25 | F99: 25 | G99: 25 | H99: 25 | I99: 25 | J99: 25 | K99: 25 | L99: 25 | M99: 25 | N99: 25 | O99: 25
B100: Customer churn | D100: =-$C$16*D98 -> -11.785508 | E100: =-$C$16*E98 -> -12.181943 | F100: =-$C$16*F98 -> -12.566485 | G100: =-$C$16*G98 -> -12.93949 | H100: =-$C$16*H98 -> -13.301306 | I100: =-$C$16*I98 -> -13.652266 | J100: =-$C$16*J98 -> -13.992698 | K100: =-$C$16*K98 -> -14.322918 | ... O100: =-$C$16*O98 -> -15.547656
B101: Total number of customer accounts | D101: =SUM(D98:D100) -> 406.06477 | E101: =SUM(E98:E100) -> 418.88283 | F101: =SUM(F98:F100) -> 431.31635 | G101: =SUM(G98:G100) -> 443.37685 | H101: =SUM(H98:H100) -> 455.07555 | I101: =SUM(I98:I100) -> 466.42328 | J101: =SUM(J98:J100) -> 477.43058 | K101: =SUM(K98:K100) -> 488.10767 | ... O101: =SUM(O98:O100) -> 527.70753
B103: MRR opening balance | D103: =O82 -> 49448.813 | E103: =D107 -> 51207.081 | F103: =E107 -> 52938.974 | G103: =F107 -> 54644.89 | H103: =G107 -> 56325.216 | I103: =H107 -> 57980.338 | J103: =I107 -> 59610.633 | K103: =J107 -> 61216.474 | L103: =K107 -> 62798.227 | ... O103: =N107 -> 67402.546
B104: New MRR | D104: =D99*$C$19 -> 2500 | E104: =E99*$C$19 -> 2500 | F104: =F99*$C$19 -> 2500 | G104: =G99*$C$19 -> 2500 | H104: =H99*$C$19 -> 2500 | I104: =I99*$C$19 -> 2500 | J104: =J99*$C$19 -> 2500 | K104: =K99*$C$19 -> 2500 | ... O104: =O99*$C$19 -> 2500
B105: Churned MRR | D105: =+-D112*D103 -> -988.97626 | E105: =+-E112*E103 -> -1024.1416 | F105: =+-F112*F103 -> -1058.7795 | G105: =+-G112*G103 -> -1092.8978 | H105: =+-H112*H103 -> -1126.5043 | I105: =+-I112*I103 -> -1159.6068 | J105: =+-J112*J103 -> -1192.2127 | K105: =+-K112*K103 -> -1224.3295 | ... O105: =+-O112*O103 -> -1348.0509
B106: Expansion MRR | D106: =+D113*D103 -> 247.24406 | E106: =+E113*E103 -> 256.0354 | F106: =+F113*F103 -> 264.69487 | G106: =+G113*G103 -> 273.22445 | H106: =+H113*H103 -> 281.62608 | I106: =+I113*I103 -> 289.90169 | J106: =+J113*J103 -> 298.05317 | K106: =+K113*K103 -> 306.08237 | ... O106: =+O113*O103 -> 337.01273
B107: Net MRR | D107: =SUM(D103:D106) -> 51207.081 | E107: =SUM(E103:E106) -> 52938.974 | F107: =SUM(F103:F106) -> 54644.89 | G107: =SUM(G103:G106) -> 56325.216 | H107: =SUM(H103:H106) -> 57980.338 | I107: =SUM(I103:I106) -> 59610.633 | J107: =SUM(J103:J106) -> 61216.474 | K107: =SUM(K103:K106) -> 62798.227 | ... O107: =SUM(O103:O106) -> 68891.508
B108: % growth | E108: =E107/D107-1 -> 0.033821373 | F108: =F107/E107-1 -> 0.032224186 | G108: =G107/F107-1 -> 0.030749932 | H108: =H107/G107-1 -> 0.029385094 | I108: =I107/H107-1 -> 0.028118065 | J108: =J107/I107-1 -> 0.026938826 | K108: =K107/J107-1 -> 0.02583868 | L108: =L107/K107-1 -> 0.024810041 | ... O108: =O107/N107-1 -> 0.022090587
B110: ARPA (Average Revenue per Account per Month) - across installed based | D110: =+D107/D101 -> 126.1057 | E110: =+E107/E101 -> 126.38134 | F110: =+F107/F101 -> 126.6933 | G110: =+G107/G101 -> 127.03689 | H110: =+H107/H101 -> 127.40816 | I110: =+I107/I101 -> 127.80373 | J110: =+J107/J101 -> 128.22068 | K110: =+K107/K101 -> 128.65651 | ... O110: =+O107/O101 -> 130.54865
B112: % MRR Churn Rate | D112: 0.02 | E112: 0.02 | F112: 0.02 | G112: 0.02 | H112: 0.02 | I112: 0.02 | J112: 0.02 | K112: 0.02 | L112: 0.02 | M112: 0.02 | N112: 0.02 | O112: 0.02
B113: % MRR Expansion Rate | D113: 0.005 | E113: 0.005 | F113: 0.005 | G113: 0.005 | H113: 0.005 | I113: 0.005 | J113: 0.005 | K113: 0.005 | L113: 0.005 | M113: 0.005 | N113: 0.005 | O113: 0.005
B114: % Net MRR Churn Rate | D114: =+(-D105-D106)/D103 -> 0.015 | E114: =+(-E105-E106)/E103 -> 0.015 | F114: =+(-F105-F106)/F103 -> 0.015 | G114: =+(-G105-G106)/G103 -> 0.015 | H114: =+(-H105-H106)/H103 -> 0.015 | I114: =+(-I105-I106)/I103 -> 0.015 | J114: =+(-J105-J106)/J103 -> 0.015 | K114: =+(-K105-K106)/K103 -> 0.015 | ... O114: =+(-O105-O106)/O103 -> 0.015
B116: Subscription billings | D116: =D104*$C$17+($C$17*$C$18*H29) -> 41400 | E116: =E104*$C$17+($C$17*$C$18*I29) -> 41400 | F116: =F104*$C$17+($C$17*$C$18*J29) -> 41400 | G116: =G104*$C$17+($C$17*$C$18*K29) -> 41400 | H116: =H104*$C$17+($C$17*$C$18*L29) -> 41400 | I116: =I104*$C$17+($C$17*$C$18*M29) -> 41400 | J116: =J104*$C$17+($C$17*$C$18*N29) -> 41400 | K116: =K104*$C$17+($C$17*$C$18*O29) -> 41400 | L116: =L104*$C$17+($C$17*$C$18*D54) -> 47100 | M116: =M104*$C$17+($C$17*$C$18*E54) -> 47100 | N116: =N104*$C$17+($C$17*$C$18*F54) -> 47100 | O116: =O104*$C$17+($C$17*$C$18*G54) -> 47100
B118: Annualized run rate in 2020 | D118: =SUM(D107:O107) -> 723263.05
B119: Subscription billings in 2020 | D119: =SUM(D116:O116)+$C$18*SUM(D41:O41) -> 656400
B121: =B96+1 -> 2021 | D121: =EDATE(D96,12) -> 44197 | E121: =EDATE(E96,12) -> 44228 | F121: =EDATE(F96,12) -> 44256 | G121: =EDATE(G96,12) -> 44287 | H121: =EDATE(H96,12) -> 44317 | I121: =EDATE(I96,12) -> 44348 | J121: =EDATE(J96,12) -> 44378 | K121: =EDATE(K96,12) -> 44409 | ... O121: =EDATE(O96,12) -> 44531
B122: Number of customer accounts
B123: Opening balance | D123: =O101 -> 527.70753 | E123: =D126 -> 541.87631 | F123: =E126 -> 555.62002 | G123: =F126 -> 568.95142 | H123: =G126 -> 581.88287 | I123: =H126 -> 594.42639 | J123: =I126 -> 606.5936 | K123: =J126 -> 618.39579 | L123: =K126 -> 629.84392 | ... O123: =N126 -> 662.16854
B124: New customer additions | D124: 30 | E124: 30 | F124: 30 | G124: 30 | H124: 30 | I124: 30 | J124: 30 | K124: 30 | L124: 30 | M124: 30 | N124: 30 | O124: 30
B125: Customer churn | D125: =-$C$16*D123 -> -15.831226 | E125: =-$C$16*E123 -> -16.256289 | F125: =-$C$16*F123 -> -16.668601 | G125: =-$C$16*G123 -> -17.068543 | H125: =-$C$16*H123 -> -17.456486 | I125: =-$C$16*I123 -> -17.832792 | J125: =-$C$16*J123 -> -18.197808 | K125: =-$C$16*K123 -> -18.551874 | ... O125: =-$C$16*O123 -> -19.865056
B126: Total number of customer accounts | D126: =SUM(D123:D125) -> 541.87631 | E126: =SUM(E123:E125) -> 555.62002 | F126: =SUM(F123:F125) -> 568.95142 | G126: =SUM(G123:G125) -> 581.88287 | H126: =SUM(H123:H125) -> 594.42639 | I126: =SUM(I123:I125) -> 606.5936 | J126: =SUM(J123:J125) -> 618.39579 | K126: =SUM(K123:K125) -> 629.84392 | ... O126: =SUM(O123:O125) -> 672.30348
B128: MRR opening balance | D128: =O107 -> 68891.508 | E128: =D132 -> 70858.135 | F128: =E132 -> 72795.263 | G128: =F132 -> 74703.334 | H128: =G132 -> 76582.784 | I128: =H132 -> 78434.042 | J128: =I132 -> 80257.532 | K128: =J132 -> 82053.669 | L128: =K132 -> 83822.864 | ... O128: =N132 -> 88972.807
B129: New MRR | D129: =D124*$C$19 -> 3000 | E129: =E124*$C$19 -> 3000 | F129: =F124*$C$19 -> 3000 | G129: =G124*$C$19 -> 3000 | H129: =H124*$C$19 -> 3000 | I129: =I124*$C$19 -> 3000 | J129: =J124*$C$19 -> 3000 | K129: =K124*$C$19 -> 3000 | ... O129: =O124*$C$19 -> 3000
B130: Churned MRR | D130: =+-D137*D128 -> -1377.8302 | E130: =+-E137*E128 -> -1417.1627 | F130: =+-F137*F128 -> -1455.9053 | G130: =+-G137*G128 -> -1494.0667 | H130: =+-H137*H128 -> -1531.6557 | I130: =+-I137*I128 -> -1568.6808 | J130: =+-J137*J128 -> -1605.1506 | K130: =+-K137*K128 -> -1641.0734 | ... O130: =+-O137*O128 -> -1779.4561
B131: Expansion MRR | D131: =+D138*D128 -> 344.45754 | E131: =+E138*E128 -> 354.29067 | F131: =+F138*F128 -> 363.97631 | G131: =+G138*G128 -> 373.51667 | H131: =+H138*H128 -> 382.91392 | I131: =+I138*I128 -> 392.17021 | J131: =+J138*J128 -> 401.28766 | K131: =+K138*K128 -> 410.26834 | ... O131: =+O138*O128 -> 444.86404
B132: Net MRR | D132: =SUM(D128:D131) -> 70858.135 | E132: =SUM(E128:E131) -> 72795.263 | F132: =SUM(F128:F131) -> 74703.334 | G132: =SUM(G128:G131) -> 76582.784 | H132: =SUM(H128:H131) -> 78434.042 | I132: =SUM(I128:I131) -> 80257.532 | J132: =SUM(J128:J131) -> 82053.669 | K132: =SUM(K128:K131) -> 83822.864 | ... O132: =SUM(O128:O131) -> 90638.215
...

Sheet Financial Model
B3: Other assumptions
D5: ='Monthly Schedule'!B21 -> 2017 | E5: =+D5+1 -> 2018 | F5: =+E5+1 -> 2019 | G5: =+F5+1 -> 2020 | H5: =+G5+1 -> 2021 | I5: =+H5+1 -> 2022
B7: Total number of customer accounts | D7: ='Monthly Schedule'!O26 -> 171.43678 | E7: ='Monthly Schedule'!O51 -> 272.02892 | F7: ='Monthly Schedule'!O76 -> 392.85028 | G7: ='Monthly Schedule'!O101 -> 527.70753 | H7: ='Monthly Schedule'!O126 -> 672.30348 | I7: ='Monthly Schedule'!O151 -> 823.65655
B9: Subscription billings | D9: ='Monthly Schedule'!D44 -> 144000 | E9: ='Monthly Schedule'!D69 -> 216000 | F9: ='Monthly Schedule'!D94 -> 333600 | G9: ='Monthly Schedule'!D119 -> 656400 | H9: ='Monthly Schedule'!D144 -> 865200 | I9: ='Monthly Schedule'!D169 -> 1117320
B10: Average bill size for professional services and other per account | D10: 50 | E10: 50 | F10: 50 | G10: 50 | H10: 50 | I10: 50
B11: Professional services and other billings | D11: =D10*D7 -> 8571.8391 | E11: =E10*E7 -> 13601.446 | F11: =F10*F7 -> 19642.514 | G11: =G10*G7 -> 26385.377 | H11: =H10*H7 -> 33615.174 | I11: =I10*I7 -> 41182.827
B12: Total billings | D12: =D9+D11 -> 152571.84 | E12: =E9+E11 -> 229601.45 | F12: =F9+F11 -> 353242.51 | G12: =G9+G11 -> 682785.38 | H12: =H9+H11 -> 898815.17 | I12: =I9+I11 -> 1158502.8
B14: Revenue
B16: Subscription revenue | D16: ='Monthly Schedule'!D43 -> 182786.62 | E16: ='Monthly Schedule'!D68 -> 322095.9 | F16: ='Monthly Schedule'!D93 -> 504645.43 | G16: ='Monthly Schedule'!D118 -> 723263.05 | H16: ='Monthly Schedule'!D143 -> 971966.2 | I16: ='Monthly Schedule'!D168 -> 1245764.7
B17: Professional services and other revenue | D17: =D11 -> 8571.8391 | E17: =E11 -> 13601.446 | F17: =F11 -> 19642.514 | G17: =G11 -> 26385.377 | H17: =H11 -> 33615.174 | I17: =I11 -> 41182.827
B19: Cost of revenue
B21: Cost of subscription revenue | D21: =+D22*D16 -> 27417.994 | E21: =+E22*E16 -> 48314.385 | F21: =+F22*F16 -> 75696.815 | G21: =+G22*G16 -> 108489.46 | H21: =+H22*H16 -> 145794.93 | I21: =+I22*I16 -> 186864.7
B22: % of subscription revenue | D22: 0.15 | E22: 0.15 | F22: 0.15 | G22: 0.15 | H22: 0.15 | I22: 0.15
B23: Cost of professional services and other revenue | D23: =+D24*D17 -> 7286.0633 | E23: =+E24*E17 -> 11561.229 | F23: =+F24*F17 -> 16696.137 | G23: =+G24*G17 -> 22427.57 | H23: =+H24*H17 -> 28572.898 | I23: =+I24*I17 -> 35005.403
B24: % of professional services and other revenue | D24: 0.85 | E24: 0.85 | F24: 0.85 | G24: 0.85 | H24: 0.85 | I24: 0.85
B26: Sales and marketing expenses
B28: Sales and marketing staff headcount | D28: 45 | E28: =+(E7-D7)/E29 -> 63.365763 | F28: =+(F7-E7)/F29 -> 76.108708 | G28: =+(G7-F7)/G29 -> 84.950303 | H28: =+(H7-G7)/H29 -> 91.084976 | I28: =+(I7-H7)/I29 -> 95.341472
B29: New accounts per headcount | D29: =+(D7-'Monthly Schedule'!$D$23)/D28 -> 1.5874841 | E29: =+D29 -> 1.5874841 | F29: =+E29 -> 1.5874841 | G29: =+F29 -> 1.5874841 | H29: =+G29 -> 1.5874841 | I29: =+H29 -> 1.5874841
B30: Salary (fixed component) | D30: 1000 | E30: 1000 | F30: 1000 | G30: 1000 | H30: 1000 | I30: 1000
B31: Fixed component of sales and marketing expenses | D31: =+D28*D30 -> 45000 | E31: =+E28*E30 -> 63365.763 | F31: =+F28*F30 -> 76108.708 | G31: =+G28*G30 -> 84950.303 | H31: =+H28*H30 -> 91084.976 | I31: =+I28*I30 -> 95341.472
B33: Commission rate | C33: 0.05
B34: Total commissions (including deferred portion) | D34: =+$C$33*D12 -> 7628.592 | E34: =+$C$33*E12 -> 11480.072 | F34: =+$C$33*F12 -> 17662.126 | G34: =+$C$33*G12 -> 34139.269 | H34: =+$C$33*H12 -> 44940.759 | I34: =+$C$33*I12 -> 57925.141
B35: Annual commission expense (excludes deferred portion) | D35: =$C$33*D16 -> 9139.3312 | E35: =$C$33*E16 -> 16104.795 | F35: =$C$33*F16 -> 25232.272 | G35: =$C$33*G16 -> 36163.152 | H35: =$C$33*H16 -> 48598.31 | I35: =$C$33*I16 -> 62288.233
B37: Total sales and marketing expense | D37: =+D35+D31 -> 54139.331 | E37: =+E35+E31 -> 79470.558 | F37: =+F35+F31 -> 101340.98 | G37: =+G35+G31 -> 121113.46 | H37: =+H35+H31 -> 139683.29 | I37: =+I35+I31 -> 157629.71
B39: Research and development expenses
B41: Research and development headcount | D41: 15 | E41: =D41+5 -> 20 | F41: =E41+5 -> 25 | G41: =F41+5 -> 30 | H41: =G41+5 -> 35 | I41: =H41+5 -> 40
B42: Salary (fixed component) | D42: 1500 | E42: 1500 | F42: 1500 | G42: 1500 | H42: 1500 | I42: 1500
B43: Personnel related research and development expense | D43: =+D41*D42 -> 22500 | E43: =+E41*E42 -> 30000 | F43: =+F41*F42 -> 37500 | G43: =+G41*G42 -> 45000 | H43: =+H41*H42 -> 52500 | I43: =+I41*I42 -> 60000
B44: Data center and infrastructure related costs | D44: 100 | E44: 100 | F44: 100 | G44: 100 | H44: 100 | I44: 100
B45: Total research and development expense | D45: =+D43+D44 -> 22600 | E45: =+E43+E44 -> 30100 | F45: =+F43+F44 -> 37600 | G45: =+G43+G44 -> 45100 | H45: =+H43+H44 -> 52600 | I45: =+I43+I44 -> 60100
B47: General and administrative expenses
B49: General and administrative headcount | D49: 8 | E49: =D49+1 -> 9 | F49: =E49+1 -> 10 | G49: =F49+1 -> 11 | H49: =G49+1 -> 12 | I49: =H49+1 -> 13
B50: Salary (fixed component) | D50: 1000 | E50: 1000 | F50: 1000 | G50: 1000 | H50: 1000 | I50: 1000
B51: Personnel related research and development expense | D51: =+D49*D50 -> 8000 | E51: =+E49*E50 -> 9000 | F51: =+F49*F50 -> 10000 | G51: =+G49*G50 -> 11000 | H51: =+H49*H50 -> 12000 | I51: =+I49*I50 -> 13000
B52: Rental expense and other | D52: 100 | E52: 100 | F52: 100 | G52: 100 | H52: 100 | I52: 100
B53: Total research and development expense | D53: =D51+D52 -> 8100 | E53: =E51+E52 -> 9100 | F53: =F51+F52 -> 10100 | G53: =G51+G52 -> 11100 | H53: =H51+H52 -> 12100 | I53: =I51+I52 -> 13100
B55: Balance sheet items
B57: Number of days in a year | C57: 365
B58: Current Assets
B59: Accounts Receivable Days (billings based) | D59: 45 | E59: 45 | F59: 45 | G59: 45 | H59: 45 | I59: 45
B60: Prepaid expenses and other (% of revenue) | D60: 0.15 | E60: 0.15 | F60: 0.15 | G60: 0.15 | H60: 0.15 | I60: 0.15
B62: Liabilities
B63: Accounts Payable Days | D63: 10 | E63: 10 | F63: 10 | G63: 10 | H63: 10 | I63: 10
B65: Capital Expenditures
B66: Technology | D66: 500 | E66: 200 | F66: 200 | G66: 200 | H66: 200 | I66: 200
B67: Property and equipment | D67: 500 | E67: 200 | F67: 200 | G67: 200 | H67: 200 | I67: 200
B69: Depreciation
B70: Technology - Straight-line Years | D70: 5 | E70: 5 | F70: 5 | G70: 5 | H70: 5 | I70: 5
B71: Property and Equipment - Straight-line Years | D71: 5 | E71: 5 | F71: 5 | G71: 5 | H71: 5 | I71: 5
B73: Financing
B74: Interest Rate | D74: 0.03 | E74: 0.03 | F74: 0.03 | G74: 0.03 | H74: 0.03 | I74: 0.03
B75: Debt Issued (Repaid) | D75: 5000 | E75: 0 | F75: 0 | G75: 0 | H75: 0 | I75: 0
B76: Equity Raised (Repurchased) | D76: 50000 | E76: 0 | F76: 0 | G76: 0 | H76: 0 | I76: 0
B77: Dividends Paid | D77: 0 | E77: 0 | F77: 0 | G77: 0 | H77: 0 | I77: 0
B79: Valuation
B80: Tax Rate | D80: 0.3 | E80: 0.3 | F80: 0.3 | G80: 0.3 | H80: 0.3 | I80: 0.3
B81: WACC | C81: 0.1
B82: Terminal uFCF Multiple | C82: 11
B84: Income Statement
D86: =D$5 -> 2017 | E86: =E$5 -> 2018 | F86: =F$5 -> 2019 | G86: =G$5 -> 2020 | H86: =H$5 -> 2021 | I86: =I$5 -> 2022
B88: Subscription revenue | D88: =+D16 -> 182786.62 | E88: =+E16 -> 322095.9 | F88: =+F16 -> 504645.43 | G88: =+G16 -> 723263.05 | H88: =+H16 -> 971966.2 | I88: =+I16 -> 1245764.7
B89: Professional services and other revenue | D89: =+D17 -> 8571.8391 | E89: =+E17 -> 13601.446 | F89: =+F17 -> 19642.514 | G89: =+G17 -> 26385.377 | H89: =+H17 -> 33615.174 | I89: =+I17 -> 41182.827
B90: Total revenue | D90: =+D89+D88 -> 191358.46 | E90: =+E89+E88 -> 335697.35 | F90: =+F89+F88 -> 524287.95 | G90: =+G89+G88 -> 749648.42 | H90: =+H89+H88 -> 1005581.4 | I90: =+I89+I88 -> 1286947.5
B91: % growth | E91: =+E90/D90-1 -> 0.75428534 | F91: =+F90/E90-1 -> 0.56178758 | G91: =+G90/F90-1 -> 0.42984104 | H91: =+H90/G90-1 -> 0.34140397 | I91: =+I90/H90-1 -> 0.27980442
B92: Cost of revenue | D92: =+D21+D23 -> 34704.057 | E92: =+E21+E23 -> 59875.614 | F92: =+F21+F23 -> 92392.952 | G92: =+G21+G23 -> 130917.03 | H92: =+H21+H23 -> 174367.83 | I92: =+I21+I23 -> 221870.1
B93: Gross profit | D93: =+D90-D92 -> 156654.41 | E93: =+E90-E92 -> 275821.73 | F93: =+F90-F92 -> 431895 | G93: =+G90-G92 -> 618731.4 | H93: =+H90-H92 -> 831213.55 | I93: =+I90-I92 -> 1065077.4
B94: % margin | D94: =+D93/D90 -> 0.81864373 | E94: =+E93/E90 -> 0.82163811 | F94: =+F93/F90 -> 0.82377441 | G94: =+G93/G90 -> 0.8253621 | H94: =+H93/H90 -> 0.82659998 | I94: =+I93/I90 -> 0.82759972
B95: Sales and marketing | D95: =D37 -> 54139.331 | E95: =E37 -> 79470.558 | F95: =F37 -> 101340.98 | G95: =G37 -> 121113.46 | H95: =H37 -> 139683.29 | I95: =I37 -> 157629.71
B96: % of revenue | D96: =+D95/D93 -> 0.34559724 | E96: =+E95/E93 -> 0.2881229 | F96: =+F95/F93 -> 0.23464263 | G96: =+G95/G93 -> 0.1957448 | H96: =+H95/H93 -> 0.16804741 | I96: =+I95/I93 -> 0.14799836
B97: Research and development | D97: =+D45 -> 22600 | E97: =+E45 -> 30100 | F97: =+F45 -> 37600 | G97: =+G45 -> 45100 | H97: =+H45 -> 52600 | I97: =+I45 -> 60100
B98: % of revenue | D98: =+D97/D90 -> 0.11810295 | E98: =+E97/E90 -> 0.089664099 | F98: =+F97/F90 -> 0.071716316 | G98: =+G97/G90 -> 0.060161535 | H98: =+H97/H90 -> 0.052308049 | I98: =+I97/I90 -> 0.046699652
B99: General and administrative | D99: =+D53 -> 8100 | E99: =+E53 -> 9100 | F99: =+F53 -> 10100 | G99: =+G53 -> 11100 | H99: =+H53 -> 12100 | I99: =+I53 -> 13100
B100: % of revenue | D100: =+D99/D90 -> 0.042328935 | E100: =+E99/E90 -> 0.027107751 | F100: =+F99/F90 -> 0.019264223 | G100: =+G99/G90 -> 0.014806941 | H100: =+H99/H90 -> 0.01203284 | I100: =+I99/I90 -> 0.010179125
B101: EBITDA | D101: =+D93-D95-D97-D99 -> 71815.075 | E101: =+E93-E95-E97-E99 -> 157151.17 | F101: =+F93-F95-F97-F99 -> 282854.02 | G101: =+G93-G95-G97-G99 -> 441417.94 | H101: =+H93-H95-H97-H99 -> 626830.26 | I101: =+I93-I95-I97-I99 -> 834247.68
B102: % margin | D102: =+D101/D90 -> 0.37529082 | E102: =+E101/E90 -> 0.4681335 | F102: =+F101/F90 -> 0.53950127 | G102: =+G101/G90 -> 0.58883328 | H102: =+H101/H90 -> 0.6233511 | I102: =+I101/I90 -> 0.64823755
B104: Depreciation and amortization | D104: =+-D179-D194 -> 800 | E104: =+-E179-E194 -> 1600 | F104: =+-F179-F194 -> 2400 | G104: =+-G179-G194 -> 3200 | H104: =+-H179-H194 -> 4000 | I104: =+-I179-I194 -> 4000
B105: Interest | D105: =D211 -> 150 | E105: =E211 -> 150 | F105: =F211 -> 150 | G105: =G211 -> 150 | H105: =H211 -> 150 | I105: =I211 -> 150
B106: Earnings Before Tax | D106: =+D101-D104-D105 -> 70865.075 | E106: =+E101-E104-E105 -> 155401.17 | F106: =+F101-F104-F105 -> 280304.02 | G106: =+G101-G104-G105 -> 438067.94 | H106: =+H101-H104-H105 -> 622680.26 | I106: =+I101-I104-I105 -> 830097.68
B108: Taxes | D108: =+D106*D80 -> 21259.523 | E108: =+E106*E80 -> 46620.352 | F108: =+F106*F80 -> 84091.205 | G108: =+G106*G80 -> 131420.38 | H108: =+H106*H80 -> 186804.08 | I108: =+I106*I80 -> 249029.31
B109: Net Income | D109: =+D106-D108 -> 49605.553 | E109: =+E106-E108 -> 108780.82 | F109: =+F106-F108 -> 196212.81 | G109: =+G106-G108 -> 306647.56 | H109: =+H106-H108 -> 435876.18 | I109: =+I106-I108 -> 581068.38
B111: Dividends paid | D111: =+D77 -> 0 | E111: =+E77 -> 0 | F111: =+F77 -> 0 | G111: =+G77 -> 0 | H111: =+H77 -> 0 | I111: =+I77 -> 0
B113: Balance sheet
D115: =D$86 -> 2017 | E115: =E$86 -> 2018 | F115: =F$86 -> 2019 | G115: =G$86 -> 2020 | H115: =H$86 -> 2021 | I115: =I$86 -> 2022
B116: ASSETS
B117: Current
B118: Cash | D118: =D171 -> 17566.467 | E118: =E171 -> -7981.8903 | F118: =F171 -> -19485.49 | G118: =G171 -> 148145.71 | H118: =H171 -> 417079.93 | I118: =I171 -> 801146.96
B119: Accounts Receivable | D119: =+D59*D12/$C$57 -> 18810.227 | E119: =+E59*E12/$C$57 -> 28307.028 | F119: =+F59*F12/$C$57 -> 43550.447 | G119: =+G59*G12/$C$57 -> 84179.019 | H119: =+H59*H12/$C$57 -> 110812.83 | I119: =+I59*I12/$C$57 -> 142829.12
B120: Deferred commissions | D120: =++SUM($D$34:D34)-SUM($D$35:D35) -> -1510.7393 | E120: =++SUM($D$34:E34)-SUM($D$35:E35) -> -6135.462 | F120: =++SUM($D$34:F34)-SUM($D$35:F35) -> -13705.608 | G120: =++SUM($D$34:G34)-SUM($D$35:G35) -> -15729.492 | H120: =++SUM($D$34:H34)-SUM($D$35:H35) -> -19387.043 | I120: =++SUM($D$34:I34)-SUM($D$35:I35) -> -23750.135
B121: Prepaid expenses and other current assets | D121: =+D60*D90 -> 28703.77 | E121: =+E60*E90 -> 50354.602 | F121: =+F60*F90 -> 78643.192 | G121: =+G60*G90 -> 112447.26 | H121: =+H60*H90 -> 150837.21 | I121: =+I60*I90 -> 193042.12
B122: Total Current Assets | D122: =SUM(D118:D121) -> 63569.724 | E122: =SUM(E118:E121) -> 64544.277 | F122: =SUM(F118:F121) -> 89002.541 | G122: =SUM(G118:G121) -> 329042.51 | H122: =SUM(H118:H121) -> 659342.92 | I122: =SUM(I118:I121) -> 1113268.1
B123: Technology | D123: =+D180 -> 1600 | E123: =+E180 -> 2800 | F123: =+F180 -> 3600 | G123: =+G180 -> 4000 | H123: =+H180 -> 4000 | I123: =+I180 -> 4000
B124: Property & Equipment | D124: =+D195 -> 1600 | E124: =+E195 -> 2800 | F124: =+F195 -> 3600 | G124: =+G195 -> 4000 | H124: =+H195 -> 4000 | I124: =+I195 -> 4000
B125: Total Assets | D125: =SUM(D122:D124) -> 66769.724 | E125: =SUM(E122:E124) -> 70144.277 | F125: =SUM(F122:F124) -> 96202.541 | G125: =SUM(G122:G124) -> 337042.51 | H125: =SUM(H122:H124) -> 667342.92 | I125: =SUM(I122:I124) -> 1121268.1
B127: LIABILITIES & SHAREHOLDER EQUITY
B128: Liabilities
B129: Current
B130: Accounts Payable | D130: =+D63*D92/$C$57 -> 950.79608 | E130: =+E63*E92/$C$57 -> 1640.4278 | F130: =+F63*F92/$C$57 -> 2531.3138 | G130: =+G63*G92/$C$57 -> 3586.7679 | H130: =+H63*H92/$C$57 -> 4777.2008 | I130: =+I63*I92/$C$57 -> 6078.633
B131: Deferred Revenue | D131: =+SUM($D$12:D12)-SUM($D$90:D90) -> -38786.624 | E131: =+SUM($D$12:E12)-SUM($D$90:E90) -> -144882.53 | F131: =+SUM($D$12:F12)-SUM($D$90:F90) -> -315927.96 | G131: =+SUM($D$12:G12)-SUM($D$90:G90) -> -382791.01 | H131: =+SUM($D$12:H12)-SUM($D$90:H90) -> -489557.21 | I131: =+SUM($D$12:I12)-SUM($D$90:I90) -> -618001.88
B132: Total Current Liabilities | D132: =SUM(D130:D131) -> -37835.828 | E132: =SUM(E130:E131) -> -143242.1 | F132: =SUM(F130:F131) -> -313396.65 | G132: =SUM(G130:G131) -> -379204.24 | H132: =SUM(H130:H131) -> -484780.01 | I132: =SUM(I130:I131) -> -611923.24
B133: Debt | D133: =+D209 -> 5000 | E133: =+E209 -> 5000 | F133: =+F209 -> 5000 | G133: =+G209 -> 5000 | H133: =+H209 -> 5000 | I133: =+I209 -> 5000
...
